Workbook

Sheet Proveedores
B2: Proveedor | G2: Observación: Usar estos nombres de proveedores para completar las planillas
B3: Acerco | C3: Cba | D3: Hierro
B4: Serin | C4: Cba | D4: Hierro
B5: Acero VCA S.A.S | C5: Alta gracia | D5: Hierros
B6: Almada | C6: Cba | D6: Obra gruesa | E6: cuenta corriente
B7: Alquilo BV | C7: Cba | D7: Alquiler maquinaria | E7: cuenta corriente
B8: Alquilo Todo | C8: Cba | D8: Alquiler maquinaria | E8: cuenta corriente
B9: Alquilo Todo AG | C9: Cba | D9: Alquiler maquinaria
B10: Alquilo Todo VGB | C10: Cba | D10: Alquiler maquinaria | E10: cuenta corriente
B11: Apromax | C11: Cba | D11: Obra gruesa
B12: Boccolini | C12: Cba | D12: Áridos
B13: Boderau | C13: Cba | D13: Áridos
B14: San Cayetano | C14: Cba | D14: Áridos
B15: Cerroplast | C15: Cba | D15: Media sombra
B16: Calido 20° | C16: Cba | D16: Climatización
B17: Can-Mar | C17: Calamuchita | D17: Áridos
B18: Cantera El Alto | C18: Alta gracia | D18: Hormigón
B19: Canteras | C19: Cba | D19: Porcellanato
B20: Chamtac | C20: Cba | D20: Impermeabilización
B21: CM impr. | C21: Cba | D21: Impermeabilización
B22: Enpolex | C22: Cba | D22: Molones
... B24: Prohome - Kevin | C24: Cba | D24: Domótica
B25: Conte Fer | C25: Cba-Mendiolaza | D25: Contenedor obra | L25: Alias: naracha CVU: 0000003100039046325684 Nombre: Matias Nicolas Fiora
B26: Conte Mas | C26: Cba | D26: Contenedor obra
B27: Conte Mas | C27: Cba | D27: Baño quimico
B28: Conte Top | C28: Cba | D28: Contenedor obra | E28: cuenta corriente
B29: Conte Top | C29: Cba | D29: Baño quimico | E29: cuenta corriente
B30: Contigiani | C30: Cba | D30: Obra gruesa | E30: cuenta corriente
B31: Centro Acero | C31: Cba | D31: Hierros
B32: Cristian Canziani | C32: VGB | D32: Fletes
B33: De Stefano | C33: Cba | D33: Porcellanato
B34: Deplano | C34: Cba | D34: Instalaciones | E34: cuenta corriente
B35: Dickhaus | C35: Vgb | D35: Obra gruesa
B36: Dimotec | C36: Cba | D36: Bombas hidrau
B37: Edificor | C37: Cba | D37: Porcellanato
B38: El Alto | C38: Alta gracia | D38: Áridos
B39: Electroalem | C39: Cba | D39: Electricidad | E39: cuenta corriente
B40: Enas | C40: Cba | D40: Alquiler maquinaria | E40: cuenta corriente
B41: Enpolex | C41: Cba | D41: Molones
B42: Hermida | C42: Cba | D42: Separadores
B43: Fernando Bustos | C43: Molvento | D43: Mov. Suelo | E43: cuenta corriente
B44: Fernando MHZ | C44: Cba | D44: Mov. Suelo
B45: Ferrocons | C45: Cba | D45: Obra gruesa | E45: cuenta corriente
B46: Feyro | C46: Cba | D46: Electricidad | E46: cuenta corriente
B47: Peusso | C47: Cba | D47: Electricidad
B48: Flete Cba bueno | C48: Cba | D48: Fletes
B49: Flete de ENAS | C49: Cba | D49: Fletes
B50: Flete Hugo Godoy | C50: Cba | D50: Fletes | E50: cuenta corriente
B51: Flete Jonatan | C51: Cba | D51: Fletes
B52: Flete Matias Sanchez | C52: Cba | D52: Fletes
B53: Flete Gonza Moreno | C53: Cba | D53: Fletes
B54: Flete Fede Castro | C54: Cba | D54: Fletes
B55: Frio Latina | D55: Chapa
B56: Garin | C56: Cba | D56: Mat. Pintura | E56: cuenta corriente
B57: Tecnocolón | C57: Cba | D57: Impermeabilización
B58: Goldman | C58: Cba | D58: Climatización | E58: cuenta corriente
B59: Generación Clima S.R.L. | C59: Cba | D59: Climatización
B60: Gran Ombu | C60: Cba | D60: Áridos
B61: Guaticor | C61: Cba | D61: Alquiler maquinaria | E61: cuenta corriente
B62: Gruas Izar | C62: Villa gral Belgrano | D62: Gruas
B63: Gruas mare | C63: Cba | D63: Gruas
B64: Gruas martin | C64: Cba | D64: Gruas
B65: Hierros Industriales | C65: Cba | D65: Hierro
B66: Holcim | C66: Cba | D66: Hormigón
B67: Hormiblock | C67: Cba | D67: Hormigón
B68: Hormicor | C68: Río Tercero | D68: Hormigón
B69: Hormilas | C69: Villa gral Belgrano | D69: Hormigón
B70: Indusparquet | C70: Cba | D70: Maderas
B71: Ivanar | C71: Rosario | D71: Hierro
B72: Maxi Herrero | C72: Cba | D72: Herrería
B73: Jack SRL | C73: Cba | D73: Vía seca | E73: cuenta corriente
B74: Leo Sanchez | C74: Cba | D74: Mov. Suelo | E74: cuenta corriente
B75: Pellicer | C75: Cba | D75: Mov. Suelo | E75: cuenta corriente
B76: Light | C76: Cba | D76: Iluminación
B77: Lucho Parayso | C77: Cba | D77: Maderas
B78: Luminotecnia | C78: Cba | D78: Iluminación | E78: cuenta corriente
B79: Maderas Colon | C79: Cba | D79: Maderas
B80: Maderas Cumbre | C80: Cba | D80: Maderas
B81: Maestre | C81: Cba | D81: Iluminación
B82: Merlino | C82: Cba | D82: Obra gruesa
B83: Marcos aurelio | C83: Cba | D83: Hierro
B84: Mendio SA | C84: Cba | D84: Maderas | E84: cuenta corriente
B85: Met. Panamericana | C85: Cba | D85: Plegados
B86: Miguel Ángel Papa | C86: Cba | D86: Ferreteria
B87: Natalia Marin | C87: Molvento | D87: Baño quimico | E87: cuenta corriente
B88: Nicolas Carusso | C88: Cba | D88: Áridos
B89: Nicolas Carusso | C89: Cba | D89: Mov. Suelo
B90: Onix | C90: Cba | D90: Porcellanato
B91: Rafael Calvo | C91: Molvento | D91: Revestimiento
B92: Raúl Olmedo | C92: Cba | D92: Mov. suelo
B93: Pablo Ledesma | C93: Molvento | D93: Contenedor obra | E93: cuenta corriente
B94: Pastorino | C94: Cba | D94: Matafuegos
B95: Patagonia | C95: Cba | D95: Maderas
B96: Peusso | C96: Cba | D96: Electricidad
B97: Pilca | C97: Cba | D97: Hormigón
B98: Pintecord | C98: Cba | D98: Mat. Pintura | E98: cuenta corriente
B99: Quimex | C99: Cba | D99: Impermeabilización
B100: Friolatina LTN | C100: Cba | D100: Cubierta Metalica
B101: Rogiro Aceros | C101: Bs As | D101: Hierro
B102: Roncaglia | C102: Cba | D102: Plegados | E102: cuenta corriente
...

Sheet Calendario
B2: Lunes | C2: Martes | D2: Miércoles | E2: Jueves | F2: Viernes | G2: Sábado | H2: Domingo
B3: NOVIEMBRE
E4: 45981 | F4: 45982
B5: 45985 | C5: 45986 | D5: 45987 | E5: 45988 | F5: 45989
L6: Feriados
B7: DICIEMBRE | L7: carga area computo
B8: 45992 | C8: 45993 | D8: 45994 | E8: 45995 | F8: 45996 | G8: 45997 | H8: 45998 | L8: Despues area adm manda pagos
B9: 45999 | C9: 46000 | D9: 46001 | E9: 46002 | F9: 46003 | G9: 46004 | H9: 46005 | L9: Dia de pagos
B10: 46006 | C10: 46007 | D10: 46008 | E10: 46009 | F10: 46010 | G10: 46011 | H10: 46012
B11: 46013 | C11: 46014 | D11: 46015 | E11: 46016 | F11: 46017 | G11: 46018 | H11: 46019 | L11: Todos los jueves se actualiza el tablero
B12: 46020 | C12: 46021 | D12: 46022
B13: 2026
B14: ENERO
E15: 46023 | F15: 46024
B16: 46027 | C16: 46028 | D16: 46029 | E16: 46030 | F16: 46031 | G16: 46032 | H16: 46033
B17: 46034 | C17: 46035 | D17: 46036 | E17: 46037 | F17: 46038 | G17: 46039 | H17: 46040
B18: 46041 | C18: 46042 | D18: 46043 | E18: 46044 | F18: 46045 | G18: 46046 | H18: 46047
B19: 46048 | C19: 46049 | D19: 46050 | E19: 46051 | F19: 46052 | G19: 46053
B20: FEBRERO
H21: 46054
B22: 46055 | C22: 46056 | D22: 46057 | E22: 46058 | F22: 46059 | G22: 46060 | H22: 46061
B23: 46062 | C23: 46063 | D23: 46064 | E23: 46065 | F23: 46066 | G23: 46067 | H23: 46068
B24: 46069 | C24: 46070 | D24: 46071 | E24: 46072 | F24: 46073 | G24: 46074 | H24: 46075
B25: 46076 | C25: 46077 | D25: 46078 | E25: 46079 | F25: 46080 | G25: 46081 | H25: 46082
B26: MARZO
H27: 46082
B28: 46083 | C28: 46084 | D28: 46085 | E28: 46086 | F28: 46087 | G28: 46088 | H28: 46089
B29: 46090 | C29: 46091 | D29: 46092 | E29: 46093 | F29: 46094 | G29: 46095 | H29: 46096
B30: 46097 | C30: 46098 | D30: 46099 | E30: 46100 | F30: 46101 | G30: 46102 | H30: 46103
B31: 46104 | C31: 46105 | D31: 46106 | E31: 46107 | F31: 46108 | G31: 46109 | H31: 46110
B32: 46111 | C32: 46112
B33: ABRIL
D34: 46113 | E34: 46114 | F34: 46115 | G34: 46116 | H34: 46117
B35: 46118 | C35: 46119 | D35: 46120 | E35: 46121 | F35: 46122 | G35: 46123 | H35: 46124
B36: 46125 | C36: 46126 | D36: 46127 | E36: 46128 | F36: 46129 | G36: 46130 | H36: 46131
B37: 46132 | C37: 46133 | D37: 46134 | E37: 46135 | F37: 46136 | G37: 46137 | H37: 46138
B38: 46139 | C38: 46140 | D38: 46141 | E38: 46142
B39: MAYO
F40: 46143 | G40: 46144 | H40: 46145
B41: 46146 | C41: 46147 | D41: 46148 | E41: 46149 | F41: 46150 | G41: 46151 | H41: 46152
B42: 46153 | C42: 46154 | D42: 46155 | E42: 46156 | F42: 46157 | G42: 46158 | H42: 46159
B43: 46160 | C43: 46161 | D43: 46162 | E43: 46163 | F43: 46164 | G43: 46165 | H43: 46166
B44: 46167 | C44: 46168 | D44: 46169 | E44: 46170 | F44: 46171 | G44: 46172 | H44: 46173
B45: JUNIO
B46: 46174 | C46: 46175 | D46: 46176 | E46: 46177 | F46: 46178 | G46: 46179 | H46: 46180
B47: 46181 | C47: 46182 | D47: 46183 | E47: 46184 | F47: 46185 | G47: 46186 | H47: 46187
B48: 46188 | C48: 46189 | D48: 46190 | E48: 46191 | F48: 46192 | G48: 46193 | H48: 46194
B49: 46195 | C49: 46196 | D49: 46197 | E49: 46198 | F49: 46199 | G49: 46200 | H49: 46201
B50: 46202 | C50: 46203
B51: JULIO
D52: 46204 | E52: 46205 | F52: 46206 | G52: 46207 | H52: 46208
B53: 46209 | C53: 46210 | D53: 46211 | E53: 46212 | F53: 46213 | G53: 46214 | H53: 46215
B54: 46216 | C54: 46217 | D54: 46218 | E54: 46219 | F54: 46220 | G54: 46221 | H54: 46222
B55: 46223 | C55: 46224 | D55: 46225 | E55: 46226 | F55: 46227 | G55: 46228 | H55: 46229
B56: 46230 | C56: 46231 | D56: 46232 | E56: 46233 | F56: 46234
B57: AGOSTO
G58: 46235 | H58: 46236
B59: 46237 | C59: 46238 | D59: 46239 | E59: 46240 | F59: 46241 | G59: 46242 | H59: 46243
B60: 46244 | C60: 46245 | D60: 46246 | E60: 46247 | F60: 46248 | G60: 46249 | H60: 46250
B61: 46251 | C61: 46252 | D61: 46253 | E61: 46254 | F61: 46255 | G61: 46256 | H61: 46257
B62: 46258 | C62: 46259 | D62: 46260 | E62: 46261 | F62: 46262 | G62: 46263 | H62: 46264
B63: 46265
B64: SEPTIEMBRE
B66: 46265 | C66: 46266 | D66: 46267 | E66: 46268 | F66: 46269 | G66: 46270 | H66: 46271
B67: 46272 | C67: 46273 | D67: 46274 | E67: 46275 | F67: 46276 | G67: 46277 | H67: 46278
B68: 46279 | C68: 46280 | D68: 46281 | E68: 46282 | F68: 46283 | G68: 46284 | H68: 46285
B69: 46286 | C69: 46287 | D69: 46288 | E69: 46289 | F69: 46290 | G69: 46291 | H69: 46292
B70: 46293 | C70: 46294 | D70: 46295
B71: OCTUBRE
E73: 46296 | F73: 46297 | G73: 46298 | H73: 46299
B74: 46303 | C74: 46304 | D74: 46305 | E74: 46306 | F74: 46307 | G74: 46308 | H74: 46309
B75: 46310 | C75: 46311 | D75: 46312 | E75: 46313 | F75: 46314 | G75: 46315 | H75: 46316
B76: 46317 | C76: 46318 | D76: 46319 | E76: 46320 | F76: 46321 | G76: 46322 | H76: 46323
B77: 46324 | C77: 46325 | D77: 46326

Sheet Obra SG
D2: GASTOS MATERIAL OBRA
D3: Cliente: | E3: SG
D4: Domicilio: | F4: Localidad:
B9: OBRA | C9: Fecha de FC | D9: Condición | E9: Razón social | F9: Descripción | G9: Proveedor | H9: Rubro | I9: Importe final Pesos (Iva incluido) | J9: Importe final USD (Iva incluido) | K9: Observaciones | L9: Estado Factura Cliente | M9: Estado Factura Bauvek | N9: Estado material | O9: Resarcimiento Bauvek | P9: Nº Remito | Q9: Encargado
B10: =+$E$3 -> SG
B11: =+$E$3 -> SG
B12: =+$E$3 -> SG
B13: =+$E$3 -> SG | C13: 45988 | D13: Fact-A-27083 | E13: Guillermo Fiore | F13: 2 placas antihumedad y perfiles z | G13: Jack | H13: Durlock | I13: 91470.24 | K13: A bauvek | L13: Cuenta Corriente
B14: =+$E$3 -> SG | C14: 45989 | D14: Fact-A-27097 | E14: Guillermo Fiore | F14: 4 placas comunes y 2 puntas atorn. | G14: Jack | H14: Durlock | I14: 58182.63 | K14: A bauvek | L14: Cuenta Corriente
B15: =+$E$3 -> SG | C15: 45988 | D15: Fact-A-08640 | E15: Guillermo Fiore | F15: Materiales de pintura, rodillos y lijas | G15: Garin | H15: Pintura | K15: A proveedor | L15: Pagado
B16: =+$E$3 -> SG | C16: 45996 | D16: Fact-A-27313 | E16: Guillermo Fiore | F16: 1 cinta tramada y 1 lata de masilla | G16: Jack | H16: Durlock | I16: 26266.89 | K16: A bauvek | L16: Cuenta Corriente
B17: =+$E$3 -> SG | C17: 46001 | D17: Efectivo | F17: Flete de tejuelas de Almada a obra SG | G17: Flete Hugo Godoy | H17: Fletes | I17: 57000 | K17: A bauvek | L17: Pagado
B18: =+$E$3 -> SG | C18: 46001 | D18: Efectivo | F18: Devolucion de andamios de obra a Guaticor | G18: Flete Hugo Godoy | H18: Fletes | I18: 57000 | K18: A bauvek | L18: Pagado
B19: =+$E$3 -> SG | C19: 46006 | D19: Efectivo | F19: Una placa vibradora | G19: Alquilo Todo | H19: Alquiler | I19: 60000 | K19: A bauvek | L19: Pagado
B20: =+$E$3 -> SG | C20: 46008 | D20: Efectivo | F20: Flete de pegamento de contigiani y pintura de garin | G20: Flete Hugo Godoy | H20: Fletes | I20: 72000 | K20: A bauvek | L20: Pagado
A21: Pasado quincena | C21: 46022
B22: =+$E$3 -> SG | C22: 46028 | D22: Fact-B-22514 | E22: Guillermo Fiore | F22: Alambre tejido + ganchos + alambre 2.2, etc | G22: Cerco | H22: Terminacion | I22: 85271.19 | K22: A proveedor | L22: Pagado
B23: =+$E$3 -> SG | C23: 46029 | D23: Fact-B-171951 | E23: Guillermo Fiore | F23: Material de plomeria | G23: Saniplast | H23: Plomeria | I23: 465269.3 | K23: A proveedor | L23: Pagado
B24: =+$E$3 -> SG | C24: 46029 | D24: Fact-B-171950 | E24: Guillermo Fiore | F24: Bomba presurizadora | G24: Saniplast | H24: Plomeria | I24: 385891.6 | K24: A proveedor | L24: Pagado
B25: =+$E$3 -> SG | C25: 46031 | D25: Efectivo | E25: Sin Factura | F25: Flete de materiales de CERCO, CONTIGIANI y SANIPLAST a obra | G25: Flete Hugo Godoy | H25: Fletes | I25: 37500 | K25: Pago en efectivo | L25: Pagado
B26: =+$E$3 -> SG | C26: 46031 | D26: Fact-B-140685 | E26: Guillermo Fiore | F26: Bastidores, modulos, teclas, etc. | G26: Feyro | H26: Electricidad | I26: 230000.02 | K26: A proveedor | L26: Pagado
B27: =+$E$3 -> SG | C27: 46031 | D27: Fact-B-140686 | E27: Guillermo Fiore | F27: Cables | G27: Feyro | H27: Electricidad | I27: 380000.3 | K27: A proveedor | L27: Pagado
B28: =+$E$3 -> SG | C28: 46031 | D28: Fact-B-140687 | E28: Guillermo Fiore | F28: 7 Luz led embutido de ingreso | G28: Feyro | H28: Electricidad | I28: 360000.02 | K28: A proveedor | L28: Pagado
B29: =+$E$3 -> SG | C29: 46031 | D29: Fact-B-140688 | E29: Guillermo Fiore | F29: Plafones, lamparas, spots | G29: Feyro | H29: Electricidad | I29: 587500.04 | K29: A proveedor | L29: Pagado
B30: =+$E$3 -> SG | C30: 46034 | D30: Fact-B-14076 | E30: Consumidor final | F30: Tornillos, tarugos y disco videa | G30: Ferreteros | H30: Ferretería | I30: 12214.95 | K30: Pago Mariana de Bauvek, recuperar | L30: Pagado
B31: =+$E$3 -> SG | C31: 46035 | D31: Efectivo | E31: Sin Factura | F31: 1 viaje de tierra negra | G31: Nicolas Carusso | H31: Mov. De suelo | I31: 190000 | K31: A bauvek | L31: Pagado
B32: =+$E$3 -> SG | C32: 46035 | D32: Efectivo | E32: Sin Factura | F32: Flete de materiales de saniplast, retirar hercal y adoquines y llevar a obra arzola | G32: Flete Hugo Godoy | H32: Fletes | I32: 65000 | K32: Pago en efectivo | L32: Pagado
A33: Pasado quincena | C33: 46037
B34: =+$E$3 -> SG | C34: 46038 | D34: Fact-B-00106530 | E34: Consumidor final | F34: Porcelanato de cocina + pastina | G34: Edificor | H34: Revestimiento | I34: 255311.44 | K34: A proveedor | L34: Pagado
B35: =+$E$3 -> SG | C35: 46036 | D35: Efectivo | E35: Sin Factura | F35: Flete de materiales de SANIPLAST a obra | G35: Flete Hugo Godoy | H35: Fletes | I35: 60000 | K35: A bauvek | L35: Pagado
B36: =+$E$3 -> SG | C36: 46043 | D36: Fact-A-27097 | E36: A cuenta bauvek | F36: Travesaños largos | G36: Jack | H36: Durlock | I36: 16506.52 | K36: A bauvek | L36: Pagado
B37: =+$E$3 -> SG | C37: 46044 | D37: NC-A-28345 | E37: A cuenta bauvek | F37: Devolucion Travesaños largos | G37: Jack | H37: Durlock | I37: -16506.52 | K37: A bauvek | L37: Pagado
B38: =+$E$3 -> SG | C38: 46044 | D38: Fact-A-28343 | E38: A cuenta bauvek | F38: Travesaños cortos | G38: Jack | H38: Durlock | I38: 18237.7 | K38: A bauvek | L38: Pagado
A39: Pasado quincena | C39: 46051
A40: Pasado quincena | C40: 46065
A41: Prox cierre | C41: 46093
B42: =+$E$3 -> SG
B43: =+$E$3 -> SG
B44: =+$E$3 -> SG
B45: =+$E$3 -> SG
B46: =+$E$3 -> SG
B47: =+$E$3 -> SG
B48: =+$E$3 -> SG
B49: =+$E$3 -> SG
B50: =+$E$3 -> SG
B51: =+$E$3 -> SG
B52: =+$E$3 -> SG
B53: =+$E$3 -> SG
... B58: =+$E$3 -> SG
G60: TOTAL | H60: =SUM(I10:I58) -> 3554116.3

Sheet Obra HR
D2: GASTOS MATERIAL OBRA
D3: Cliente: | E3: Hernan Reboni
D4: Domicilio: | E4: Lote 456 | F4: Localidad: | H4: El Terrón
B9: OBRA | C9: Fecha de FC | D9: Condición | E9: Razón social | F9: Descripción | G9: Proveedor | H9: Rubro | I9: Importe final Pesos (Iva incluido) | J9: Importe final USD (Iva incluido) | K9: Observaciones | L9: Estado Factura Cliente | M9: Estado Factura Bauvek | N9: Estado material | O9: Resarcimiento Bauvek | P9: Nº Remito | Q9: Encargado
B10: =+$E$3 -> Hernan Reboni
A11: Pasado quincena | C11: 46037
B12: =+$E$3 -> Hernan Reboni
B13: =+$E$3 -> Hernan Reboni
B14: =+$E$3 -> Hernan Reboni
B15: =+$E$3 -> Hernan Reboni
B16: =+$E$3 -> Hernan Reboni
B17: =+$E$3 -> Hernan Reboni
B18: =+$E$3 -> Hernan Reboni
B19: =+$E$3 -> Hernan Reboni
B20: =+$E$3 -> Hernan Reboni
B21: =+$E$3 -> Hernan Reboni
B22: =+$E$3 -> Hernan Reboni
B23: =+$E$3 -> Hernan Reboni
... B49: =+$E$3 -> Hernan Reboni
G51: TOTAL | H51: =SUM(I10:I49) -> 0

Sheet Obra FAR
D2: GASTOS MATERIAL OBRA
D3: Cliente: | E3: REMODELACION ARZOLA
D4: Domicilio: | E4: Huascar 8631, Arguello | F4: Localidad: | H4: Arguello
B9: OBRA | C9: Fecha de FC | D9: Condición | E9: Razón social | F9: Descripción | G9: Proveedor | H9: Rubro | I9: Importe final Pesos (Iva incluido) | J9: Importe final USD (Iva incluido) | K9: Observaciones | L9: Estado Factura Cliente | M9: Estado Factura Bauvek | N9: Estado material | O9: Resarcimiento Bauvek | P9: Nº Remito | Q9: Encargado | R9: Columna1 | S9: Columna2
B10: =+$E$3 -> REMODELACION ARZOLA | C10: 45863 | D10: PRES - 24300 | E10: BAUVEK S.A.S. | F10: Materiales de DURLOCK | G10: Jack | H10: Obra Gruesa | I10: =1228234.35 -> 1228234.4 | L10: Pagado | M10: Pagado
B11: =+$E$3 -> REMODELACION ARZOLA | C11: 45860 | D11: FACT 13-6500-A | E11: BAUVEK S.A.S. | F11: Materiales de OBRA GRUESA | G11: Almada | H11: Obra Gruesa | I11: 1086246.8 | L11: Pagado | M11: Pagado
B12: =+$E$3 -> REMODELACION ARZOLA | C12: 45870 | D12: Efectivo | E12: Sin Factura | F12: 1 VIAJE DE ARENA GRUESA Y 1/2 VIAJE DE GRANZA | G12: Nico Carusso | H12: Obra Gruesa | I12: 280000 | L12: Pagado | M12: Pagado
B13: =+$E$3 -> REMODELACION ARZOLA | C13: 45866 | D13: Efectivo | E13: Sin Factura | F13: 1 ROLLO DE GEOMEMBRANA Y 20KG DE ALAMBRE ATAR | G13: Almada | H13: Obra Gruesa | I13: 184187.15 | K13: Material que se llevo del QB | L13: Pagado | M13: Pagado
B14: =+$E$3 -> REMODELACION ARZOLA | C14: 45856 | D14: Efectivo | E14: Sin Factura | F14: 1 PAQUETE DE SOLERAS | G14: Jack | H14: Obra Gruesa | I14: 30223.92 | K14: Material que se llevo del QB | L14: Pagado | M14: Pagado
B15: =+$E$3 -> REMODELACION ARZOLA | C15: 45870 | D15: Efectivo | E15: Sin Factura | F15: EQUIPOS BAJO SILUETA Y SPLIT | G15: Goldman | H15: Calefacción | I15: 6694875.3 | L15: Pagado | M15: Pagado
B16: =+$E$3 -> REMODELACION ARZOLA | C16: 45861 | D16: Efectivo | E16: Sin Factura | F16: CORTAR ARBOLES | G16: Gabriel Bobcat | H16: Limpieza de arboles | I16: 600000 | L16: Pagado | M16: Pagado
B17: =+$E$3 -> REMODELACION ARZOLA | C17: 45863 | D17: PRES - 24583 | E17: BAUVEK S.A.S. | F17: MATERIAL DURLOCK PAREDES Y CIELORASO | G17: Jack | H17: Obra Gruesa | I17: 685091.44 | L17: Pagado | M17: Pagado
B18: =+$E$3 -> REMODELACION ARZOLA | C18: 45881 | D18: Efectivo | E18: Sin Factura | F18: MATERIAL DE OBRA GRUESA PARA AMPLIACION | G18: Almada | H18: Obra Gruesa | I18: 3700000 | L18: Pagado | M18: Pagado
B19: =+$E$3 -> REMODELACION ARZOLA | C19: 45888 | D19: Efectivo | E19: Sin Factura | F19: LADRILLOS PARA AMPLIACION | G19: Almada | H19: Obra Gruesa | I19: 1200000 | L19: Pagado | M19: Pagado
B20: =+$E$3 -> REMODELACION ARZOLA | C20: 45881 | D20: Efectivo | E20: Sin Factura | F20: REVOQUE FINO - 8 BOLSAS | G20: Almada | H20: Obra Gruesa | I20: 49966.44 | L20: Pagado | M20: Pagado
B21: =+$E$3 -> REMODELACION ARZOLA | C21: 45881 | D21: Efectivo | E21: Sin Factura | F21: MATERIALES DE KIT Y CONDUCTOS | G21: Adrian Giordano | H21: Calefacción | I21: 3773588 | L21: Pagado | M21: Pagado
B22: =+$E$3 -> REMODELACION ARZOLA | C22: 45881 | D22: Efectivo | E22: Sin Factura | F22: MANO DE OBRA INSTALCION EQUIPOS | G22: Adrian Giordano | H22: Calefacción | I22: 780000 | L22: Pagado | M22: Pagado
B23: =+$E$3 -> REMODELACION ARZOLA | C23: 45888 | D23: FACT 61575 | E23: BAUVEK S.A.S. | F23: MATERIALES DE ELECTRICIDAD | G23: Feyro | H23: Electricidad | I23: 630433.74 | L23: Pagado | M23: Pagado
B24: =+$E$3 -> REMODELACION ARZOLA | C24: 45888 | D24: NC 24853 | E24: Sin Factura | F24: DEVOLUCIÓN DE UNOS TARUGOS | G24: Jack | H24: Obra Gruesa | I24: -8294 | L24: Pagado | M24: Pagado
B25: =+$E$3 -> REMODELACION ARZOLA | C25: 45888 | D25: Efectivo | E25: Sin Factura | F25: TARUGOS + TORNILLOS FISHER 8mm | G25: Jack | H25: Obra Gruesa | I25: 61470 | L25: Pagado | M25: Pagado
B26: =+$E$3 -> REMODELACION ARZOLA | C26: 45890 | D26: Efectivo | E26: Sin Factura | F26: MATERIAL DE DURLOCK | G26: Jack | H26: Obra Gruesa | I26: 227142.84 | L26: Pagado | M26: Pagado
... B30: =+$E$3 -> REMODELACION ARZOLA | C30: 45902 | D30: Efectivo | E30: Sin Factura | F30: HORMIGÓN DE FUNDACIÓN 4m3 (adicionales/con remito) | G30: Hormiblock | H30: Obra Gruesa | I30: 439200 | L30: Pagado | M30: Pagado
B31: =+$E$3 -> REMODELACION ARZOLA | C31: 45896 | D31: FACT 38416 | E31: BAUVEK S.A.S. | F31: Material de agua | G31: Deplano | H31: Plomeria | I31: 707214.44 | L31: Pagado | M31: Pagado | N31: Recibido en obra
B32: =+$E$3 -> REMODELACION ARZOLA | C32: 45897 | D32: Efectivo | E32: Sin Factura | F32: 1 VIAJE DE ARENA GRUESA | G32: Nico Carusso | H32: Obra Gruesa | I32: 130000 | L32: Pagado | M32: Pagado
B33: =+$E$3 -> REMODELACION ARZOLA | C33: 45898 | D33: Efectivo | E33: Sin Factura | F33: 3 cámaras de seguridad Kit Wifi | G33: Seguridad Centro | H33: Instalaciones | I33: 218500 | L33: Pagado | M33: Pagado
B34: =+$E$3 -> REMODELACION ARZOLA | C34: 45903 | D34: FACT 48252 | E34: BAUVEK S.A.S. | F34: Material de cloaca y pluvial | G34: Deplano | H34: Plomeria | I34: 11897.06 | L34: Pagado | M34: Pagado | N34: Recibido en obra
B35: =+$E$3 -> REMODELACION ARZOLA | C35: 45903 | D35: FACT 48243 | E35: BAUVEK S.A.S. | F35: Material de cloaca y pluvial | G35: Deplano | H35: Plomeria | I35: 40920 | L35: Pagado | M35: Pagado | N35: Recibido en obra
B36: =+$E$3 -> REMODELACION ARZOLA | C36: 45903 | D36: FACT 38526 | E36: BAUVEK S.A.S. | F36: Material de cloaca y pluvial | G36: Deplano | H36: Plomeria | I36: 348461.78 | L36: Pagado | M36: Pagado | N36: Recibido en obra
B37: =+$E$3 -> REMODELACION ARZOLA | C37: 45903 | D37: FACT 38525 | E37: BAUVEK S.A.S. | F37: Material de cloaca y pluvial | G37: Deplano | H37: Plomeria | I37: 239753.93 | L37: Pagado | M37: Pagado | N37: Recibido en obra
B38: =+$E$3 -> REMODELACION ARZOLA | C38: 45904 | D38: Efectivo | E38: Sin Factura | F38: 1/2 VIAJE DE ARENA FINA | G38: Nico Carusso | H38: Obra Gruesa | I38: 160000 | L38: Pagado | M38: Pagado
B39: =+$E$3 -> REMODELACION ARZOLA | C39: 45909 | D39: FACT 9004 | E39: BAUVEK S.A.S. | F39: Rodillo de pintura | G39: Garin | H39: Pintura | I39: 10538.6 | L39: Pagado | M39: Pagado
B40: =+$E$3 -> REMODELACION ARZOLA | C40: 45909 | D40: FACT 62298 | E40: BAUVEK S.A.S. | F40: Materiales electricos | G40: Feyro | H40: Electricidad | I40: 664000.02 | L40: Pagado | M40: Pagado
B41: =+$E$3 -> REMODELACION ARZOLA | C41: 45918 | D41: Efectivo | E41: Sin Factura | F41: 6 palet del portante del 18 | G41: Almada | H41: Obra Gruesa | I41: 671534.8 | L41: Pagado | M41: Pagado
B42: =+$E$3 -> REMODELACION ARZOLA | C42: 45918 | D42: Efectivo | E42: Sin Factura | F42: 1 viaje de arena | G42: Nico Carusso | H42: Aridos | I42: 140000 | L42: Pagado | M42: Pagado
B43: =+$E$3 -> REMODELACION ARZOLA | C43: 45919 | D43: Efectivo | E43: Sin Factura | F43: Materiales para losa | G43: Almada | H43: Obra Gruesa | I43: 2723000 | L43: Pagado | M43: Pagado
B44: =+$E$3 -> REMODELACION ARZOLA | C44: 45930 | D44: Efectivo | E44: Sin Factura | F44: 1 viaje de arena | G44: Nico Carusso | H44: Aridos | I44: 140000 | L44: Pagado | M44: Pagado
B45: =+$E$3 -> REMODELACION ARZOLA | C45: 45943 | D45: Efectivo | E45: Sin Factura | F45: 250 ladrillos comunes | G45: Almada | H45: Obra Gruesa | I45: 52339.83 | L45: Pagado | M45: Pagado
B46: =+$E$3 -> REMODELACION ARZOLA | C46: 45943 | D46: Efectivo | E46: Sin Factura | F46: Hierro y block portante para el cerco | G46: Almada | H46: Obra Gruesa | I46: 3181511.6 | L46: Pagado | M46: Pagado
B47: =+$E$3 -> REMODELACION ARZOLA | C47: 45948 | D47: Efectivo | E47: Sin Factura | F47: 1 viaje de arena | G47: Nico Carusso | H47: Aridos | I47: 140000 | L47: Pagado | M47: Pagado
B48: =+$E$3 -> REMODELACION ARZOLA | C48: 45954 | D48: Efectivo | E48: Sin Factura | F48: 1 viaje de arena | G48: Nico Carusso | H48: Aridos | I48: 140000 | L48: Pagado | M48: Pagado
B49: =+$E$3 -> REMODELACION ARZOLA | C49: 45966 | D49: Efectivo | E49: Sin Factura | F49: 1/2 viaje de arena y 1/2 viaje de granza | G49: Nico Carusso | H49: Aridos | I49: 210000 | L49: Pagado | M49: Pagado
B50: =+$E$3 -> REMODELACION ARZOLA | C50: 45978 | D50: Efectivo | E50: A cuenta de Bauvek | F50: 1 viaje de arena gruesa de 7,5 m3 | G50: Boccolini Aridos | H50: Obra Gruesa | I50: 147000 | K50: Pago en efectivo | L50: Pagado | M50: Pagado
B51: =+$E$3 -> REMODELACION ARZOLA | C51: 45980 | D51: Efectivo | E51: A cuenta de Bauvek | F51: 1 rollo de geomembrana y 3 bolsas de fino | G51: Almada | H51: Obra Gruesa | I51: 110000 | K51: Pago en efectivo | L51: Pagado | M51: Pagado
A53: Pasado quincena | B53: =+$E$3 -> REMODELACION ARZOLA | C53: 45980 | D53: Efectivo | E53: A cuenta de Bauvek | F53: Flete del rollo y las bolsas de fino | G53: Flete Hugo Godoy | H53: Fletes | I53: 52000 | K53: Pago en efectivo | L53: Pagado | M53: Pagado
B54: =+$E$3 -> REMODELACION ARZOLA | C54: 45988 | D54: Efectivo | E54: A cuenta de Bauvek | F54: 1 viaje de arena gruesa de 7,5 m3 | G54: Boccolini Aridos | H54: Obra Gruesa | I54: 147000 | K54: Pago en efectivo | L54: Pagado | M54: Pagado
B55: =+$E$3 -> REMODELACION ARZOLA | C55: 45992 | D55: FACT 30753 | E55: A cuenta de Bauvek | F55: Materiales de pintura | G55: Garin | H55: Pintura | I55: 210564.26 | L55: Pagado | M55: Pagado
B56: =+$E$3 -> REMODELACION ARZOLA | C56: 45995 | D56: Efectivo | E56: Sin Factura | F56: 1 viaje de piedra + flete | G56: Claudio | H56: Revestimiento | I56: 1350000 | K56: Pago en efectivo | L56: Pagado | M56: Pagado
B57: =+$E$3 -> REMODELACION ARZOLA | C57: 45996 | D57: Efectivo | E57: Sin Factura | F57: 1 viaje de arena gruesa de 7,5 m3 | G57: Boccolini Aridos | H57: Obra Gruesa | I57: 147000 | K57: Pago en efectivo | L57: Pagado | M57: Pagado
C58: 45996
A59: Pasado quincena | B59: =+$E$3 -> REMODELACION ARZOLA | C59: 46009 | D59: FACT 65867 | E59: A cuenta de Bauvek | F59: Materiales de electricidad, cables etc. | G59: Feyro | H59: Electricidad | I59: 1245940.9 | K59: Pago con cheque | L59: Pagado | M59: Pagado
B60: =+$E$3 -> REMODELACION ARZOLA | C60: 46009 | D60: FACT 06967 | E60: A cuenta de Bauvek | F60: Material portante, hierros, etc | G60: Almada | H60: Obra Gruesa | I60: 850250.94 | L60: Pagado | M60: Pagado
B61: =+$E$3 -> REMODELACION ARZOLA | C61: 46020 | D61: Efectivo | E61: Sin Factura | F61: 1 viaje de grancilla de 1 m3 | G61: Boccolini Aridos | H61: Obra Gruesa | I61: 80000 | K61: Pago en efectivo | L61: Pagado | M61: Pagado
C62: 46022
A63: Pasado quincena | B63: =+$E$3 -> REMODELACION ARZOLA | C63: 46024 | D63: Efectivo | E63: Sin Factura | F63: 1 palet de hercal, 650 ladrillos comunes | G63: Almada | H63: Obra Gruesa | I63: 570312.13 | L63: Pagado | M63: Pagado
B64: =+$E$3 -> REMODELACION ARZOLA | C64: 46024 | D64: Efectivo | E64: Sin Factura | F64: 30 m2 de piedra de revestimiento | G64: Claudio | H64: Revestimiento | I64: 850000 | L64: Pagado | M64: Pagado
B65: =+$E$3 -> REMODELACION ARZOLA | C65: 46028 | E65: A cuenta de Bauvek | F65: Materiales de plomeria | G65: Deplano | H65: Plomería | I65: 232408.6 | K65: Pago en efectivo | L65: Pagado | M65: Pagado | N65: Recibido en obra
B66: =+$E$3 -> REMODELACION ARZOLA | C66: 46031 | D66: Efectivo | E66: Sin Factura | F66: Flete de materiales de Deplano | G66: Flete Hugo Godoy | H66: Fletes | I66: 37500 | K66: Pago en efectivo | L66: Pagado | M66: Pagado
B67: =+$E$3 -> REMODELACION ARZOLA | C67: 46034 | D67: Efectivo | E67: Sin Factura | F67: 2 m2 de arena + 1 m3 de grancilla | G67: Boccolini Aridos | H67: Obra Gruesa | I67: 135000 | K67: Se entrega el lunes | L67: Pagado | M67: Pagado
B68: =+$E$3 -> REMODELACION ARZOLA | C68: 46035 | D68: Efectivo | E68: Sin Factura | F68: 1 palet de cemento, 6 mallas sima | G68: Almada | H68: Obra Gruesa | I68: 693000 | K68: el martes 13 lo dejan en obra | L68: Pagado | M68: Pagado
C69: 46037
A70: Pasado quincena | B70: =+$E$3 -> REMODELACION ARZOLA | C70: 46037 | D70: Efectivo | E70: Sin Factura | F70: Flete de hercal y adoquines desde la obra de SG | G70: Flete Hugo Godoy | H70: Fletes | I70: 54000 | L70: Pagado | M70: Pagado
B71: =+$E$3 -> REMODELACION ARZOLA | C71: 46041 | D71: FACT 28218 | E71: A cuenta de Bauvek | F71: 12 montantes de 35mm | G71: Jack SRL | H71: Obra Gruesa | I71: 37154.5 | L71: Pagado | M71: Pagado | N71: Pendiente
B72: =+$E$3 -> REMODELACION ARZOLA | C72: 46041 | D72: NC 28219 | E72: A cuenta de Bauvek | F72: 1 paquete de soleras de 70mm | G72: Jack SRL | H72: Obra Gruesa | I72: Todavia no se devolvió
B73: =+$E$3 -> REMODELACION ARZOLA | C73: 46041 | D73: FACT 10033 | E73: A cuenta de Bauvek | F73: 1 lata de latex blanco | G73: Garin | H73: Pintura | I73: 148111.31 | L73: Pagado | M73: Pagado | N73: Recibido en obra
B74: =+$E$3 -> REMODELACION ARZOLA | C74: 46050 | D74: FACT 53187 | E74: A cuenta de Bauvek | F74: Materiales de plomeria | G74: Deplano | H74: Plomeria | I74: 182293.87 | L74: Pagado | M74: Pagado | N74: Recibido en obra
B75: =+$E$3 -> REMODELACION ARZOLA | C75: 46041 | D75: Efectivo | E75: Sin Factura | F75: Flete de hercal y adoquines desde la obra de SG y pintura de garin | G75: Flete Hugo Godoy | H75: Fletes | I75: 56000 | K75: Pago en efectivo | L75: Pagado | N75: Recibido en obra
B76: =+$E$3 -> REMODELACION ARZOLA | C76: 46044 | D76: FACT 69537 | E76: A cuenta de Bauvek | F76: Materiales porcellanato interior | G76: Ferrocons | H76: Revestimiento | I76: 4895427.2 | K76: Pago con cheque | L76: Pagado | R76: Con echeq a 0-30-60 días
B77: =+$E$3 -> REMODELACION ARZOLA | C77: 46031 | D77: S/N | E77: Sin Factura | F77: Impermeabilización de techo | G77: Jessica Quimax | H77: Impermeabilización | I77: 2157408.9 | K77: A bauvek | L77: Pagado | M77: Pagado | N77: Recibido en obra | U77: 46044 | V77: 46075 | W77: 46103
B78: =+$E$3 -> REMODELACION ARZOLA | C78: 46050 | D78: S/N | E78: Sin Factura | F78: Flete de materiales de Deplano | G78: Flete Hugo Godoy | H78: Fletes | I78: 52000 | K78: A bauvek | L78: Pagado | N78: Recibido en obra
B79: =+$E$3 -> REMODELACION ARZOLA | C79: 46051 | D79: FACT 67297 | E79: A cuenta de Bauvek | F79: Materiales de electricidad | G79: Feyro | H79: Electricidad | I79: 163932.2 | K79: A bauvek | L79: Pagado | M79: Pagado | N79: Recibido en obra
B80: =+$E$3 -> REMODELACION ARZOLA | C80: 46051 | E80: A cuenta de Bauvek | F80: Guardacantos para nicho y baño | G80: Ferrocons | H80: Revestimiento | I80: 91577.39 | K80: A bauvek | L80: Cuenta Corriente | M80: Pagado | N80: Recibido en obra
C81: 46051
A82: Pasado quincena | B82: =+$E$3 -> REMODELACION ARZOLA | C82: 46052 | D82: FACT 53259 | E82: A cuenta de Bauvek | F82: Materiales de plomeria | G82: Deplano | H82: Plomeria | I82: 4021.95 | K82: A bauvek | L82: Pagado | M82: Pagado | N82: Recibido en obra
B83: =+$E$3 -> REMODELACION ARZOLA | C83: 46055 | D83: FACT 28527 | E83: A cuenta de Bauvek | F83: Placas, cintas y sellador, tornillos | G83: Jack SRL | H83: Obra Gruesa | I83: 90594.73 | K83: A bauvek | L83: Pagado | M83: Pagado | N83: Recibido en obra | S83: Falta entregar las placas
B84: =+$E$3 -> REMODELACION ARZOLA | C84: 46056 | D84: FACT 0041330 | E84: A cuenta de Bauvek | F84: Codos de 100 y codos de 63 (cloaca) | G84: Deplano | H84: Plomeria | I84: 24294.99 | K84: A bauvek | L84: Pagado | M84: Pagado | N84: Recibido en obra
B85: =+$E$3 -> REMODELACION ARZOLA | C85: 46056 | D85: FACT 0041331 | E85: A cuenta de Bauvek | F85: Materiales de agua p/ colocar cuadro de ducha | G85: Deplano | H85: Plomeria | I85: 11480.17 | K85: A bauvek | L85: Pagado | M85: Pagado | N85: Recibido en obra
B86: =+$E$3 -> REMODELACION ARZOLA | C86: 46058 | D86: FACT 0010111 | E86: A cuenta de Bauvek | F86: Material de pintura general | G86: Garin | H86: Pintura | I86: 1001437.1 | K86: A bauvek | L86: Pagado | M86: Pagado | N86: Recibido en obra | S86: Lo entregan el lunes
B87: =+$E$3 -> REMODELACION ARZOLA | C87: 46064 | D87: FACT 28700 | E87: A cuenta de Bauvek | F87: 8 soleras y 8 montantes de 35mm | G87: Jack SRL | H87: Obra Gruesa | I87: 46239.04 | K87: A bauvek | L87: Pagado | M87: Pagado | N87: Recibido en obra
A88: Pasado quincena | C88: 46065
B89: =+$E$3 -> REMODELACION ARZOLA | C89: 46066 | D89: FACT 0053753 | E89: A cuenta de Bauvek | F89: Material de plomeria | G89: Deplano | H89: Plomeria | I89: 137479.28 | K89: A bauvek | L89: Pagado | M89: Pagado | N89: Recibido en obra
B90: =+$E$3 -> REMODELACION ARZOLA | C90: 46071 | D90: Nota de Credito 011489 | E90: A cuenta de Bauvek | F90: Codos y manguitos | G90: Deplano | H90: Plomeria | I90: -33938.58 | K90: A bauvek | L90: Pagado | M90: Pagado | N90: Recibido en obra
B91: =+$E$3 -> REMODELACION ARZOLA | C91: 46071 | D91: FACT 0053810 | E91: A cuenta de Bauvek | F91: Codos y manguitos | G91: Deplano | H91: Plomeria | I91: 32953.27 | K91: A bauvek | L91: Pagado | M91: Pagado | N91: Recibido en obra
B92: =+$E$3 -> REMODELACION ARZOLA | C92: 46071 | D92: FACT 0053814 | E92: A cuenta de Bauvek | F92: Mat. p/ instalacion de inodoros PA | G92: Deplano | H92: Plomeria | I92: 22742.4 | K92: A bauvek | L92: Pagado | M92: Pagado | N92: Recibido en obra
B93: =+$E$3 -> REMODELACION ARZOLA | C93: 46071 | D93: Nota de Credito 10009 | E93: A cuenta de Bauvek | F93: 3 Tubos cloacas negro Awaduct | G93: Deplano | H93: Plomeria | I93: -86006.08 | K93: A bauvek | L93: Pagado | M93: Pagado | N93: Recibido en obra
B94: =+$E$3 -> REMODELACION ARZOLA | C94: 46071 | D94: FACT 0053818 | E94: A cuenta de Bauvek | F94: 4 Tubos cloacas negro duratop | G94: Deplano | H94: Plomeria | I94: 87835.86 | K94: A bauvek | L94: Pagado | M94: Pagado | N94: Recibido en obra
B95: =+$E$3 -> REMODELACION ARZOLA | C95: 46073 | E95: A cuenta de Bauvek | F95: 2 tachos de masilla y cinta tramada | G95: Jack SRL | H95: Durlock | I95: 51450.75 | K95: A bauvek | L95: Pagado | M95: Pagado | N95: Recibido en obra
C96: 46079
A97: Pasado quincena | B97: =+$E$3 -> REMODELACION ARZOLA | C97: 46080 | F97: 1 cuerpo y medio de andamios. 1 cuerpo de barandas y 1 tablon | G97: Guaticor | H97: Alquiler | I97: 60400 | K97: a Bauvek | L97: Pagado | M97: Pagado | N97: Recibido en obra
A98: Pasado quincena | C98: 46093
A99: Pasado quincena | C99: 46107
B100: =+$E$3 -> REMODELACION ARZOLA | C100: 46107 | E100: s/n | F100: Flete de jack, ferrocons, deplano a arguello | G100: Flete Hugo Godoy | H100: Fletes | I100: 56000 | K100: a proveedor | L100: Pagado | M100: Pagado | N100: Recibido en obra
B101: =+$E$3 -> REMODELACION ARZOLA | C101: 46113 | E101: s/n | F101: Flete de Feyro a arguello | G101: Flete Hugo Godoy | H101: Fletes | I101: 37000 | K101: a Bauvek | L101: Pagado | M101: Pagado | N101: Recibido en obra
A102: Pasado quincena | C102: 46121
B103: =+$E$3 -> REMODELACION ARZOLA
B104: =+$E$3 -> REMODELACION ARZOLA
B105: =+$E$3 -> REMODELACION ARZOLA
B106: =+$E$3 -> REMODELACION ARZOLA
B107: =+$E$3 -> REMODELACION ARZOLA
A108: Prox cierre | B108: =+$E$3 -> REMODELACION ARZOLA | C108: 46136
B109: =+$E$3 -> REMODELACION ARZOLA
...

Sheet Obra JS
D2: GASTOS MATERIAL OBRA
D3: Cliente: | E3: JULIETA SANTIAGO - IVAN PETRINI
D4: Domicilio: | E4: MZA 58 - LOTE 10 | F4: Localidad: | H4: Molvento
B9: OBRA | C9: Fecha de FC | D9: Condición | E9: Razón social | F9: Descripción | G9: Proveedor | H9: Rubro | I9: Importe final Pesos (Iva incluido) | J9: Importe final USD (Iva incluido) | K9: Observaciones | L9: Estado Factura Cliente | M9: Estado Factura Bauvek | N9: Estado material | O9: Resarcimiento Bauvek | P9: Nº Remito | Q9: Encargado | R9: Columna1
B10: =+$E$3 -> JULIETA SANTIAGO - IVAN PETRINI | C10: 45734 | D10: Fact-A-23399 | E10: PETRINI IVAN | F10: Puntales de pino para cerco | G10: Mendio | H10: Obra Preliminar | I10: 295210.23 | K10: A proveedor | L10: Pagado | M10: Pagado | N10: Recibido en obra
B11: =+$E$3 -> JULIETA SANTIAGO - IVAN PETRINI | C11: 45733 | D11: Fact-A-12403 | E11: PETRINI IVAN | F11: Media sombra para cerco | G11: Cerroplast | H11: Obra Preliminar | I11: 247755.37 | K11: A proveedor | L11: Pagado | M11: Pagado | N11: Recibido en obra
B12: =+$E$3 -> JULIETA SANTIAGO - IVAN PETRINI | C12: 45751 | D12: Fact-A-283011 | E12: PETRINI IVAN | F12: Material de hierro | G12: Serin | H12: Obra Gruesa | I12: 18176362 | K12: A proveedor | L12: Pagado | M12: Pagado | N12: Recibido en obra
B13: =+$E$3 -> JULIETA SANTIAGO - IVAN PETRINI | C13: 45751 | D13: Fact-A-158348 | E13: PETRINI IVAN | F13: Material de hierro - alambres y clavos | G13: Serin | H13: Obra Gruesa | I13: 895017.35 | K13: A proveedor | L13: Pagado | M13: Pagado | N13: Recibido en obra
B14: =+$E$3 -> JULIETA SANTIAGO - IVAN PETRINI | C14: 45758 | D14: Fact-A-158599 | E14: PETRINI IVAN | F14: Material para porton | G14: Serin | H14: Obra Gruesa | I14: 222592.8 | K14: A proveedor | L14: Pagado | M14: Pagado | N14: Recibido en obra
B15: =+$E$3 -> JULIETA SANTIAGO - IVAN PETRINI | C15: 45772 | D15: Efectivo | E15: Sin factura | F15: Obrador y baño quimico x 6 meses | G15: Natalia Obrador | H15: Obra Gruesa | I15: 1100000 | K15: A bauvek | L15: Pagado | M15: Pagado | N15: Recibido en obra
B16: =+$E$3 -> JULIETA SANTIAGO - IVAN PETRINI | C16: 45792 | G16: Mendio | I16: 622770 | K16: A bauvek | L16: Pagado | M16: Pagado | N16: Recibido en obra
B17: =+$E$3 -> JULIETA SANTIAGO - IVAN PETRINI | C17: 45800 | D17: Efectivo | E17: Sin factura | F17: Hormigon de fundaciones pilotes | G17: Hormiblock | H17: Obra Gruesa | I17: 8960000 | K17: A bauvek | L17: Pagado | M17: Pagado | N17: Recibido en obra
B18: =+$E$3 -> JULIETA SANTIAGO - IVAN PETRINI | C18: 45821 | H18: Obra Gruesa | I18: 3480000 | K18: A bauvek | L18: Pagado | M18: Pagado
B19: =+$E$3 -> JULIETA SANTIAGO - IVAN PETRINI | C19: 45825 | D19: Efectivo | E19: Sin factura | F19: Hormigon de vigas de fundacion | G19: Hormiblock | H19: Obra Gruesa | I19: 6305000 | K19: A bauvek | L19: Pagado | M19: Pagado | N19: Recibido en obra
B20: =+$E$3 -> JULIETA SANTIAGO - IVAN PETRINI | C20: 45825 | D20: Efectivo | E20: Sin factura | F20: Tablas cepilladas, fenolicos, etc | G20: Mendio | H20: Obra Gruesa | I20: 5900970 | K20: A bauvek | L20: Pagado | M20: Pagado | N20: Recibido en obra
B21: =+$E$3 -> JULIETA SANTIAGO - IVAN PETRINI | C21: 45825 | D21: Efectivo | E21: Sin factura | F21: Planchuelas para columnas | G21: Roncaglia | H21: Obra Metalica | I21: 73000 | K21: A bauvek | L21: Pagado | M21: Pagado | N21: Recibido en obra
B22: =+$E$3 -> JULIETA SANTIAGO - IVAN PETRINI | C22: 45831 | D22: Fact-A-286400 | E22: PETRINI IVAN | F22: 28 hierro del 16 | G22: Serin | H22: Obra Gruesa | I22: 907493.44 | K22: A proveedor | L22: Pagado | M22: Pagado | N22: Recibido en obra
B23: =+$E$3 -> JULIETA SANTIAGO - IVAN PETRINI | C23: 45831 | D23: Fact-A-286401 | E23: PETRINI IVAN | F23: 100 mallas | G23: Serin | H23: Obra Gruesa | I23: 1327719.7 | K23: A proveedor | L23: Pagado | M23: Pagado | N23: Recibido en obra
B24: =+$E$3 -> JULIETA SANTIAGO - IVAN PETRINI | C24: 45859 | D24: Fact-A- | E24: PETRINI IVAN | F24: Material de obra gruesa (facturado) | G24: Apromax | H24: Obra Gruesa | I24: 12500000 | K24: A proveedor | L24: Pagado | M24: Pagado | N24: Recibido en obra
B25: =+$E$3 -> JULIETA SANTIAGO - IVAN PETRINI | C25: 45859 | D25: Efectivo | E25: PETRINI IVAN | F25: Material de obra gruesa (en efectivo) | G25: Apromax | H25: Obra Gruesa | I25: 12598800 | K25: A proveedor | L25: Pagado | M25: Pagado | N25: Recibido en obra
B26: =+$E$3 -> JULIETA SANTIAGO - IVAN PETRINI | C26: 45861 | D26: Fact-A-287740 | E26: PETRINI IVAN | F26: Hierros del 8, 12 y 16 | G26: Serin | H26: Obra Gruesa | I26: 3471631.1 | K26: A proveedor | L26: Pagado | M26: Pagado | N26: Recibido en obra
B27: =+$E$3 -> JULIETA SANTIAGO - IVAN PETRINI | C27: 45869 | D27: Efectivo | E27: Sin factura | F27: Acopio de aridos | G27: San Cayetano | H27: Obra Gruesa | I27: 3200000 | K27: A bauvek | L27: Pagado | M27: Pagado | N27: Acopio
B28: =+$E$3 -> JULIETA SANTIAGO - IVAN PETRINI | C28: 45877 | D28: Fact-A-287741 | E28: PETRINI IVAN | F28: 1º cuota de ENAS | G28: ENAS | H28: Obra Gruesa | I28: 4862385 | K28: A proveedor | L28: Pagado | M28: Pagado | N28: Recibido en obra
B29: =+$E$3 -> JULIETA SANTIAGO - IVAN PETRINI | C29: 45888 | D29: Efectivo | E29: Sin factura | F29: Hormigon de vigas de fundacion 10m3 mas | G29: Hormiblock | H29: Obra Gruesa | I29: 1158000 | K29: A bauvek | L29: Pagado | M29: Pagado | N29: Recibido en obra
B30: =+$E$3 -> JULIETA SANTIAGO - IVAN PETRINI | C30: 45891 | D30: Efectivo | E30: Sin factura | F30: Flete de alambron del 6 y clavos | G30: Flete Hugo Godoy | H30: Fletes | I30: 73500 | K30: A bauvek | L30: Pagado | M30: Pagado | N30: Recibido en obra
... B55: =+$E$3 -> JULIETA SANTIAGO - IVAN PETRINI | C55: 45972 | D55: Fact-A-050006 | E55: PETRINI IVAN | F55: Hormigon H25 | G55: Holcim | H55: Obra Gruesa | I55: 5227200 | K55: A proveedor | L55: Pagado | M55: Pagado | N55: Recibido en obra
B56: =+$E$3 -> JULIETA SANTIAGO - IVAN PETRINI | C56: 45986 | D56: NCA - 14156 | E56: PETRINI IVAN | F56: Devoluc. caños de cloacas y cojinetes | G56: Saniplast | H56: Instalaciones | I56: -488080 | K56: A cliente | L56: Pagado | M56: Pagado
B57: =+$E$3 -> JULIETA SANTIAGO - IVAN PETRINI | C57: 45995 | D57: Fact-A-065327 | E57: PETRINI IVAN | F57: Caño corrugado semipesado | G57: Feyro | H57: Electricidad | I57: 541000.71 | K57: A proveedor | L57: Pagado | M57: Pagado | N57: Recibido en obra
A58: Pasado quincena | C58: 45996
B59: =+$E$3 -> JULIETA SANTIAGO - IVAN PETRINI | C59: 46003 | D59: Fact-A-027601 | E59: PETRINI IVAN | F59: Tablas, fenolicos, puntales de THº PB | G59: Mendio | H59: Obra Gruesa | I59: 3751773.8 | L59: Pagado | M59: Pagado | N59: Recibido en obra
B60: =+$E$3 -> JULIETA SANTIAGO - IVAN PETRINI | C60: 46009 | D60: Fact-A-0293934 | E60: PETRINI IVAN | F60: 4 Perfiles UPN180 | G60: Serin | H60: Herreria | I60: 2612931.4 | L60: Pagado | M60: Pagado | N60: Recibido en obra
B61: =+$E$3 -> JULIETA SANTIAGO - IVAN PETRINI | D61: Efectivo | E61: Sin factura | F61: Placa de 30x30x1/2 pulgada | G61: Roncaglia | H61: Herreria | I61: 29000 | L61: Pagado | M61: Pagado | N61: Recibido en obra
B62: =+$E$3 -> JULIETA SANTIAGO - IVAN PETRINI | C62: 46003 | D62: Fact-A-003857 | E62: PETRINI IVAN | F62: Buñas | G62: Maderas Colón | H62: Obra Gruesa | I62: 74954.85 | L62: Pagado | M62: Pagado | N62: Recibido en obra
B63: =+$E$3 -> JULIETA SANTIAGO - IVAN PETRINI | C63: 46008 | D63: Fact-A-0000945 | E63: PETRINI IVAN | F63: Hormigon visto H25 Tabiques PB | G63: Pilca | H63: Hormigón | I63: 8224776.5 | L63: Pagado | M63: Pagado | N63: Pendiente
B64: =+$E$3 -> JULIETA SANTIAGO - IVAN PETRINI | C64: 46008 | D64: Fact-A-0072462 | E64: PETRINI IVAN | F64: Materiales de gas | G64: Saniplast | H64: Plomería | I64: 1846912.6 | L64: Pagado | M64: Pagado | N64: Recibido en obra
B65: =+$E$3 -> JULIETA SANTIAGO - IVAN PETRINI | C65: 46003 | D65: Fact-A-001155 | E65: PETRINI IVAN | F65: Alambron del 6, alambre de atar, clavos y alambre del 4 | G65: Hierros Industriales | H65: Obra Gruesa | I65: 1273790.2 | L65: Pagado | M65: Pagado | N65: Recibido en obra
A66: Pasado quincena | C66: 46022
B67: =+$E$3 -> JULIETA SANTIAGO - IVAN PETRINI | C67: 46035 | D67: Efectivo | E67: Sin factura | F67: Flete de alambron del 6 y chanfles | G67: Flete Hugo Godoy | H67: Fletes | I67: 95000 | K67: A bauvek | L67: Pagado | M67: Pagado | N67: Recibido en obra
A68: Pasado quincena | C68: 46037
B69: =+$E$3 -> JULIETA SANTIAGO - IVAN PETRINI | C69: 46041 | D69: Transeferencia | E69: Sin factura | F69: Flete del canguro desde Alq Todo VGB a obra | G69: Cristian Canziani | H69: Fletes | I69: 60000 | K69: A bauvek | L69: Pagado | M69: Pagado | N69: Recibido en obra
B70: =+$E$3 -> JULIETA SANTIAGO - IVAN PETRINI | C70: 46041 | D70: Transeferencia | F70: 1 Compactadora canguro BS52 y BS600 - alquiler 4 días | G70: Alquilo Todo VGB | H70: Alquiler | I70: 160000 | K70: A bauvek | L70: Pagado | M70: Pagado | N70: Recibido en obra
B71: =+$E$3 -> JULIETA SANTIAGO - IVAN PETRINI | C71: 46044 | D71: Transeferencia | F71: 1 Vibrador - alquiler 1 día | G71: Alquilo Todo VGB | H71: Alquiler | I71: 26000 | K71: A bauvek | L71: Pagado | M71: Pagado | N71: Recibido en obra
B72: =+$E$3 -> JULIETA SANTIAGO - IVAN PETRINI | C72: 46044 | D72: Transeferencia | F72: 1 Vibrador - BAUVEK - alquiler 1 día | G72: Maquinarias BV | H72: Alquiler | I72: 26000 | K72: A bauvek | L72: Pagado | M72: Pagado | N72: Recibido en obra
B73: =+$E$3 -> JULIETA SANTIAGO - IVAN PETRINI | C73: 46045 | D73: Transeferencia | E73: Sin factura | F73: Flete del canguro y vibra desde obra a Alq Todo VGB | G73: Cristian Canziani | H73: Fletes | I73: 60000 | K73: A bauvek | L73: Pagado | M73: Pagado | N73: Recibido en obra
B74: =+$E$3 -> JULIETA SANTIAGO - IVAN PETRINI | C74: 45975 | D74: Fact-A-14771 | E74: Bauvek SAS | F74: Nylon 200 micrones para contrapiso PSS | G74: Cerroplast | H74: Obra Gruesa | I74: 73589.18 | K74: A bauvek | L74: Pagado | M74: Pagado | N74: Recibido en obra
A75: Pasado quincena | C75: 46051
B76: =+$E$3 -> JULIETA SANTIAGO - IVAN PETRINI | C76: 46050 | D76: Fact-A-028148 | E76: PETRINI IVAN | F76: Maderas cepilladas para tabiques vistos PB | G76: Mendio | H76: Obra Gruesa | I76: 3445412.8 | K76: A proveedor | L76: Pagado | M76: Pagado | N76: Recibido en obra
B77: =+$E$3 -> JULIETA SANTIAGO - IVAN PETRINI | C77: 46048 | D77: Fact-A-003063 | E77: PETRINI IVAN | F77: Alquiler material Nº 6558A1 | G77: Enas | H77: Apuntalamiento | I77: 1117193 | K77: A proveedor | L77: Pagado | M77: Pagado | N77: Recibido en obra
B78: =+$E$3 -> JULIETA SANTIAGO - IVAN PETRINI | C78: 46049 | D78: Fact-A-003074 | E78: PETRINI IVAN | F78: Alquiler material Nº 6558A0 | G78: Enas | H78: Apuntalamiento | I78: 2909123.5 | K78: A proveedor | L78: Pagado | M78: Pagado | N78: Recibido en obra
B79: =+$E$3 -> JULIETA SANTIAGO - IVAN PETRINI | C79: 46050 | D79: Fact-A-003094 | E79: PETRINI IVAN | F79: Alquiler material Nº 6558A1 | G79: Enas | H79: Apuntalamiento | I79: 974291.4 | K79: A proveedor | L79: Pagado | M79: Pagado | N79: Recibido en obra
B80: =+$E$3 -> JULIETA SANTIAGO - IVAN PETRINI | C80: 46052 | D80: Fact-A-295490 | E80: PETRINI IVAN | F80: Hierros para mitad losa PB | G80: Serin | H80: Hierros | I80: 12521395 | K80: A proveedor | L80: Pagado | M80: Pagado | N80: Recibido en obra
B81: =+$E$3 -> JULIETA SANTIAGO - IVAN PETRINI | C81: 46052 | D81: Fact-A-170541 | E81: PETRINI IVAN | F81: Alambres, clavos y mallas tabiques PB | G81: Serin | H81: Hierros | I81: 1241964.5 | K81: A proveedor | L81: Pagado | M81: Pagado | N81: Recibido en obra
A82: Pasado quincena | C82: 46065
B83: =+$E$3 -> JULIETA SANTIAGO - IVAN PETRINI | C83: 46065 | D83: cuenta corriente | F83: MOV SUELO RESUMEN AL 22-01-2026 | G83: Fernando Bustos | H83: MOV SUELO | I83: 7332500 | K83: A bauvek | L83: Pagado | M83: Pagado | N83: Recibido en obra
B84: =+$E$3 -> JULIETA SANTIAGO - IVAN PETRINI | C84: 46071 | D84: Fact-A-00003098 | E84: PETRINI IVAN | F84: Alquiler material Nº 6558A0 | G84: Enas | H84: Apuntalamiento | I84: 2952760.4 | K84: A proveedor | L84: Pagado | M84: Pagado | N84: Recibido en obra
A85: Pasado quincena | C85: 46079
B86: =+$E$3 -> JULIETA SANTIAGO - IVAN PETRINI | C86: 46080 | D86: Fact-A-0296547 | E86: PETRINI IVAN | F86: Hierros para 2da mitad losa PB | G86: Serin | H86: Hierros | I86: 2976584 | K86: A proveedor | L86: Pagado | M86: Pagado | N86: Recibido en obra
B87: =+$E$3 -> JULIETA SANTIAGO - IVAN PETRINI | C87: 46083 | D87: Fact-A-0028598 | E87: PETRINI IVAN | F87: Tablas cepilladas, fenolicos, pntales p/ LOSA PB | G87: Mendio SA | H87: Maderas | I87: 13441242 | K87: A proveedor | L87: Pagado | M87: Pagado | N87: Pendiente | P87: No ha ido todavia por tema lluvia
B88: =+$E$3 -> JULIETA SANTIAGO - IVAN PETRINI | C88: 46083 | D88: Fact-A-001014 | E88: PETRINI IVAN | F88: Hormigon adeudado (7 m3 H17 y 6 m3 de H25) | G88: Pilca | H88: Hormigon | I88: 2444608.7 | K88: A proveedor | L88: Pagado | M88: Pagado | N88: Recibido en obra
B89: =+$E$3 -> JULIETA SANTIAGO - IVAN PETRINI | C89: 46083 | D89: Fact-A-001015 | E89: PETRINI IVAN | F89: Hormigon para parte de tabique PB (14 m3 de H25) | G89: Pilca | H89: Hormigon | I89: 3152201.6 | K89: A proveedor | L89: Pagado | M89: Pagado | N89: Recibido en obra
B90: =+$E$3 -> JULIETA SANTIAGO - IVAN PETRINI | C90: 46077 | D90: cuenta corriente | E90: Sin factura | F90: 2 vibros alquiler de 1 día | G90: Alquilo BV | H90: Maquinaria | I90: 64000 | K90: A proveedor | L90: Pagado | M90: Pagado | N90: Recibido en obra
B91: =+$E$3 -> JULIETA SANTIAGO - IVAN PETRINI | C91: 46078 | D91: Fact-A-03115 | E91: PETRINI IVAN | F91: Alquiler Enas Contrato 6558 A1 | G91: Enas | H91: Apuntalamiento | I91: 986957.18 | K91: A proveedor | L91: Pagado | M91: Pagado | N91: Recibido en obra
B92: =+$E$3 -> JULIETA SANTIAGO - IVAN PETRINI | C92: 46089 | D92: Fact-A-003121 | E92: PETRINI IVAN | F92: Alquiler Enas Contrato 6558 A0 y RTO 3426 (1/2 al 2/3) | G92: Enas | H92: Apuntalamiento | I92: 2310480.9 | K92: A proveedor | L92: Pagado | M92: Pagado | N92: Recibido en obra
B93: =+$E$3 -> JULIETA SANTIAGO - IVAN PETRINI | D93: Efectivo | E93: Sin factura | F93: Alquiler de 2º obrador | G93: Natalia Marin | H93: Obra gruesa | I93: 980000 | K93: A bauvek | L93: Pagado | M93: Pagado | N93: Recibido en obra
B94: =+$E$3 -> JULIETA SANTIAGO - IVAN PETRINI | D94: Efectivo | E94: Sin factura | F94: Alambron del 6 de la obra de Silene y Guille | G94: Alquilo BV | H94: Alambre | I94: 312085 | K94: A bauvek | L94: Pagado | M94: Pagado | N94: Recibido en obra | P94: Este material se saco del alambron que sobro en obra de guille y silene. Plata a favor de silene y guille
B95: =+$E$3 -> JULIETA SANTIAGO - IVAN PETRINI | C95: 46094 | D95: S/N | E95: Sin factura | F95: Traslado alambron | G95: Flete Hugo Godoy | I95: 110000 | K95: A bauvek | L95: Pagado | M95: Pagado | N95: Recibido en obra
A96: Pasado quincena | C96: 46093
B97: =+$E$3 -> JULIETA SANTIAGO - IVAN PETRINI | C97: 46107 | D97: S/N | E97: Sin factura | F97: 1 Vibrador - alquiler 1 día (chino) | G97: Alquilo BV | I97: 42000 | K97: A bauvek | L97: Pagado | M97: Pagado
B98: =+$E$3 -> JULIETA SANTIAGO - IVAN PETRINI | C98: 46107 | D98: S/N | E98: Sin factura | F98: 1 Vibrador - alquiler 1 día | G98: Alquilo BV | I98: 42000 | K98: A bauvek | L98: Pagado | M98: Pagado
A99: Pasado quincena | C99: 46107
B100: =+$E$3 -> JULIETA SANTIAGO - IVAN PETRINI | C100: 46108 | D100: Fact-A-10883 | E100: PETRINI IVAN | F100: 160 bolsas de Sika monotop y 80 de cemento | G100: Apromax | H100: Obra gruesa | I100: 7462743 | K100: A proveedor | L100: Pagado | N100: Acopio
B101: =+$E$3 -> JULIETA SANTIAGO - IVAN PETRINI | C101: 46108 | D101: Fact-A-10884 | E101: PETRINI IVAN | F101: 1º cuota de Enas Contrato 6558 A2 | G101: Enas | H101: Apuntalamiento | I101: 1383937.5 | K101: A proveedor | L101: Pagado
B102: =+$E$3 -> JULIETA SANTIAGO - IVAN PETRINI | C102: 46111 | D102: Fact-A-0006687 | E102: PETRINI IVAN | F102: Rolados del asador y hogar + sombreretes | G102: Roncaglia | H102: Herrería | I102: 867000 | K102: A proveedor | L102: Pagado
A103: Pasado quincena | B103: =+$E$3 -> JULIETA SANTIAGO - IVAN PETRINI | C103: 46121
B104: =+$E$3 -> JULIETA SANTIAGO - IVAN PETRINI | C104: 46127 | D104: Fact-A-0006749 | E104: PETRINI IVAN | F104: (diferencia) Rolados del asador y hogar + sombreretes | G104: Roncaglia | H104: Herrería | I104: 255000 | K104: A proveedor | L104: Pagado | N104: Recibido en obra
B105: =+$E$3 -> JULIETA SANTIAGO - IVAN PETRINI | C105: 46128 | D105: Fact-A-0000157 | E105: PETRINI IVAN | F105: Separadores para losa PB | G105: Hermida | H105: Separadores | I105: 180774 | K105: A proveedor | L105: Pagado | N105: Recibido en obra
B106: =+$E$3 -> JULIETA SANTIAGO - IVAN PETRINI | C106: 46136 | D106: Fact-A-000298836 | E106: PETRINI IVAN | F106: Perfiles W, C y caños estr para cubierta losa PB (una parte) | G106: Serin | H106: Herrería | I106: 4055259.3 | K106: A proveedor | L106: Pagado | N106: Recibido en obra
B107: =+$E$3 -> JULIETA SANTIAGO - IVAN PETRINI | C107: 46132 | D107: Fact-A-0001275 | E107: PETRINI IVAN | F107: Molones de telgopor | G107: Enpolex | H107: Telgopor | I107: 643921.79 | K107: A proveedor | L107: Pagado | N107: Pendiente
B108: =+$E$3 -> JULIETA SANTIAGO - IVAN PETRINI | C108: 46134 | D108: Fact-A-0005737 | E108: PETRINI IVAN | F108: Anclajes mecánicos para PB | G108: Miguel Ángel Papa | H108: Ferretería | I108: 199228.92 | K108: A proveedor | L108: Pagado | N108: Pendiente
B109: =+$E$3 -> JULIETA SANTIAGO - IVAN PETRINI | C109: 46132 | D109: Fact-A-0010504 | E109: PETRINI IVAN | F109: Pintura para perfilerá metálica | G109: Garin | H109: Pintura | I109: 528124.88 | K109: A proveedor | L109: Pagado | N109: Pendiente
B110: =+$E$3 -> JULIETA SANTIAGO - IVAN PETRINI | C110: 46134 | D110: Fact-A-0001087 | E110: PETRINI IVAN | F110: 26 m3 de H25 de hormigones que se tiraron hasta la fecha | G110: Pilca | H110: Hormigon | I110: 5854088.7 | K110: A proveedor | L110: Pagado | N110: Recibido en obra
B111: =+$E$3 -> JULIETA SANTIAGO - IVAN PETRINI | C111: 46136 | E111: PETRINI IVAN | F111: 100 kg de alambron del 6 | G111: Hierros Industriales | H111: Alambre | I111: 310405.25 | K111: A proveedor | L111: Pagado | N111: Pendiente
B112: =+$E$3 -> JULIETA SANTIAGO - IVAN PETRINI | C112: 46136 | E112: PETRINI IVAN | F112: 6 cajas de preinstalación para aires | G112: Saniplast | H112: Plomería | I112: 53450.25 | K112: A proveedor | L112: Pagado | N112: Pendiente
B113: =+$E$3 -> JULIETA SANTIAGO - IVAN PETRINI | C113: 46141 | D113: S/N | E113: Sin factura | F113: Traslado de molones para vigas huecas galeria living | G113: Flete Gonza Moreno | H113: Fletes | I113: 170000 | K113: A bauvek | L113: Pagado | M113: Pagado | N113: Pendiente
B114: =+$E$3 -> JULIETA SANTIAGO - IVAN PETRINI | C114: 46079 | D114: Fact-B-0003138 | E114: PETRINI IVAN | F114: Alquiler Enas Contrato 6558 A1 | G114: Enas | H114: Apuntalamiento | I114: 1007683.3 | K114: A proveedor | L114: Pagado | N114: Recibido en obra
B115: =+$E$3 -> JULIETA SANTIAGO - IVAN PETRINI | C115: 46093 | D115: Fact-B-0003150 | E115: PETRINI IVAN | F115: Alquiler Enas Contrato 6558 A0 | G115: Enas | H115: Apuntalamiento | I115: 2359001 | K115: A proveedor | L115: Pagado | N115: Recibido en obra
B116: =+$E$3 -> JULIETA SANTIAGO - IVAN PETRINI | C116: 46111 | D116: Fact-B-0003168 | E116: PETRINI IVAN | F116: Alquiler Enas Contrato 6558 A1 | G116: Enas | H116: Apuntalamiento | I116: 1018767.8 | K116: A proveedor | L116: Pagado | N116: Recibido en obra
B117: =+$E$3 -> JULIETA SANTIAGO - IVAN PETRINI | C117: 46142 | D117: S/N | E117: Sin factura | F117: Traslado de alambrón y materiales eléctricos, cajas, etc | G117: Flete Hugo Godoy | H117: Fletes | I117: 176000 | K117: A bauvek | L117: Pagado | M117: Pagado | N117: Recibido en obra
B118: =+$E$3 -> JULIETA SANTIAGO - IVAN PETRINI | C118: 46140 | D118: Fact-B-0000007 | E118: PETRINI IVAN | F118: Materiales de preinstalación para los 6 aires | G118: Generación Clima S.R.L. | H118: Instalaciones | I118: 923351 | K118: A proveedor | L118: Pagado | N118: Pendiente
B119: =+$E$3 -> JULIETA SANTIAGO - IVAN PETRINI | C119: 46148 | D119: S/N | E119: Sin factura | F119: 100 m2 de Piedra Pirca | G119: Rafael Calvo | H119: Revestimiento | I119: 3600000 | K119: A bauvek | L119: Pagado | N119: Pendiente
A120: Pasado quincena | B120: =+$E$3 -> JULIETA SANTIAGO - IVAN PETRINI | C120: 46149
B121: =+$E$3 -> JULIETA SANTIAGO - IVAN PETRINI | C121: 46150 | D121: Fact-B-00299485 | E121: PETRINI IVAN | F121: Perfiles W460 y 3 barras del 20 | G121: Serin | H121: Hierros | I121: 9095997.4 | K121: A proveedor | L121: Pagado | N121: Recibido en obra
B122: =+$E$3 -> JULIETA SANTIAGO - IVAN PETRINI | C122: 46150 | D122: Fact-B-000174376 | E122: PETRINI IVAN | F122: Perfiles C120 y C140 | G122: Serin | H122: Hierros | I122: 2256770.7 | K122: A proveedor | L122: Pagado | N122: Recibido en obra
B123: =+$E$3 -> JULIETA SANTIAGO - IVAN PETRINI | C123: 46153 | D123: Fact-B-00016312 | E123: PETRINI IVAN | F123: Rollo de media sombra de 2 mts de ancho | G123: Cerroplast | H123: Obra Gruesa | I123: 162660 | K123: A proveedor | L123: Pagado | N123: Recibido en obra
B124: =+$E$3 -> JULIETA SANTIAGO - IVAN PETRINI | C124: 46154 | D124: Fact-A-00075213 | E124: PETRINI IVAN | F124: Materiales de agua | G124: Saniplast | H124: Plomería | I124: 3822328.4 | K124: A proveedor | L124: Pagado | N124: Recibido en obra
B125: =+$E$3 -> JULIETA SANTIAGO - IVAN PETRINI | C125: 46154 | D125: Fact-A-00075212 | E125: PETRINI IVAN | F125: Materiales de cloaca y pluvial, embudos de hierro fund. | G125: Saniplast | H125: Plomería | I125: 1650601.4 | K125: A proveedor | L125: Pagado | N125: Recibido en obra
B126: =+$E$3 -> JULIETA SANTIAGO - IVAN PETRINI | C126: 46128 | D126: S/N | E126: Sin factura | F126: Placas para las vigas metalicas y tabiques. | G126: Maxi Herrero | H126: Herrería | I126: 1156320.5 | K126: A bauvek | L126: Pagado | N126: Recibido en obra
B127: =+$E$3 -> JULIETA SANTIAGO - IVAN PETRINI | C127: 46150 | D127: S/N | E127: Sin factura | F127: 78 housing | G127: Zingueria Villa Allende | H127: Herrería | I127: 234000 | K127: A bauvek | L127: Pagado | N127: Recibido en obra
B128: =+$E$3 -> JULIETA SANTIAGO - IVAN PETRINI | C128: 46149 | D128: Fact-B-00003172 | E128: PETRINI IVAN | F128: Alquiler Enas Contrato 6558 A0 | G128: Enas | H128: Apuntalamiento | I128: 2384950 | K128: A proveedor | L128: Pagado | N128: Recibido en obra
B129: =+$E$3 -> JULIETA SANTIAGO - IVAN PETRINI | C129: 46156 | D129: S/N | E129: Sin factura | F129: Traslado de puntales de madera, saniplast y mediasombra | G129: Flete Hugo Godoy | H129: Fletes | I129: 124000 | K129: A bauvek | L129: Pagado | N129: Recibido en obra
...

Sheet Obra Cañuelas
D2: GASTOS MATERIAL OBRA
D3: Cliente: | E3: OBRA GIAVENNO
D4: Domicilio: | E4: LOTE 5, MZA 17 | F4: Localidad: Zona Sur Cordoba
F5: Barrio: Cañuelas Country Golf
B9: OBRA | C9: Fecha de FC | D9: Condición | E9: Razón social | F9: Descripción | G9: Proveedor | H9: Rubro | I9: Importe final Pesos (Iva incluido) | J9: Importe final USD (Iva incluido) | K9: Observaciones | L9: Estado Factura Cliente | M9: Estado Factura Bauvek | N9: Estado material | O9: Resarcimiento Bauvek | P9: Nº Remito | Q9: Encargado
B10: =+$E$3 -> OBRA GIAVENNO | C10: 45966 | D10: FACT -A 00123 | E10: A cuenta de Bauvek | F10: Modulos ciegos Bauhaus | G10: Feyro | H10: Electricidad | I10: 5295.3 | K10: Retiro Julian por la sucursal de o´higgins | L10: Pagado | N10: Recibido en obra | O10: No Pagado
B11: =+$E$3 -> OBRA GIAVENNO | C11: 45968 | D11: FACT -A 00138 | E11: A cuenta de Bauvek | F11: Cable utp | G11: Feyro | H11: Electricidad | I11: 67820.75 | K11: Retiro Julian por la sucursal de o´higgins | L11: Pagado | N11: Recibido en obra | O11: No Pagado
B12: =+$E$3 -> OBRA GIAVENNO | C12: 45971 | D12: FACT -A 00142 | E12: A cuenta de Bauvek | F12: Tapas, bastidores, Bauhaus | G12: Feyro | H12: Electricidad | I12: 15476.44 | K12: Retiro Julian por la sucursal de o´higgins | L12: Pagado | N12: Recibido en obra | O12: No Pagado
B13: =+$E$3 -> OBRA GIAVENNO | C13: 45975 | D13: FACT -A 00161 | E13: A cuenta de Bauvek | F13: Tapas y distanciadores bauhaus | G13: Feyro | H13: Electricidad | I13: 9900 | K13: Retiro Julian por la sucursal de o´higgins | L13: Pagado | N13: Recibido en obra | O13: No Pagado
A14: Pasado quincena | C14: =+$F$3 -> 0 | D14: 45996
B15: =+$E$3 -> OBRA GIAVENNO | C15: 46006 | D15: Efectivo | E15: A cuenta de Bauvek | F15: Alquiler x 1 día de bomba sumergible | G15: Alquilo Todo | H15: Alquiler | I15: 20000 | K15: Retiró Julian por Alquilo Todo | L15: Pagado | N15: Recibido en obra
B16: =+$E$3 -> OBRA GIAVENNO | C16: 46010 | E16: A cuenta de Bauvek | F16: Pintura para retocar un problema de filtracion | G16: Pintecord | H16: Pintura | I16: 23639.46 | K16: Retiró Julian por la sucursal de la oñhiggins | L16: Pagado | N16: Recibido en obra | O16: No Pagado
A17: Pasado quincena | D17: 46022
B18: =+$E$3 -> OBRA GIAVENNO | C18: 46027 | D18: FACT -A 001503 | E18: A cuenta de Bauvek | F18: Pintura para retocar un problema de filtracion | G18: Pintecord | H18: Pintura | I18: 11436.26 | K18: Retiró Julian por la sucursal de la o´higgins camino san carlos | L18: Pagado | N18: Recibido en obra | O18: No Pagado
A19: Pasado quincena | D19: 46037
A20: Pasado quincena | C20: 46065
B21: =+$E$3 -> OBRA GIAVENNO | C21: 46051 | D21: FACT-A67132 | E21: A cuenta de Bauvek | F21: mat de electricidad | G21: Feyro | H21: Electricidad | I21: 55000.05 | L21: Pagado | N21: Recibido en obra | O21: No Pagado
A22: Pasado quincena | C22: 46079
B23: =+$E$3 -> OBRA GIAVENNO
A24: Pasado quincena | C24: 46093
B25: =+$E$3 -> OBRA GIAVENNO | C25: 46100 | D25: FACT-A 10331 | E25: Bauvek | F25: Mat pintura impermeabilizacion | G25: Garin | H25: Pintura | I25: 34483.72 | K25: Retiro Mari en gauss | L25: No Pagado | N25: Recibido en obra | O25: No Pagado
A26: Pasado quincena | C26: 46107
A27: Pasado quincena | B27: =+$E$3 -> OBRA GIAVENNO | C27: 46149
A28: Prox cierre | B28: =+$E$3 -> OBRA GIAVENNO | C28: 46163
B29: =+$E$3 -> OBRA GIAVENNO
B30: =+$E$3 -> OBRA GIAVENNO
B31: =+$E$3 -> OBRA GIAVENNO
B32: =+$E$3 -> OBRA GIAVENNO
B33: =+$E$3 -> OBRA GIAVENNO
B34: =+$E$3 -> OBRA GIAVENNO
B35: =+$E$3 -> OBRA GIAVENNO
B36: =+$E$3 -> OBRA GIAVENNO
B37: =+$E$3 -> OBRA GIAVENNO
B38: =+$E$3 -> OBRA GIAVENNO
B39: =+$E$3 -> OBRA GIAVENNO
B40: =+$E$3 -> OBRA GIAVENNO
... B51: =+$E$3 -> OBRA GIAVENNO
G53: TOTAL | H53: =SUM(I10:I51) -> 243051.98

Sheet Obra EC
D2: GASTOS MATERIAL OBRA
D3: Cliente: | E3: EMILIO CONTIGIANI
D4: Domicilio: | E4: Lote 182 | F4: Localidad: | H4: El Terron
B9: OBRA | C9: Fecha de FC | D9: Condición | E9: Razón social | F9: Descripción | G9: Proveedor | H9: Rubro | I9: Importe final Pesos (Iva incluido) | J9: Importe final USD (Iva incluido) | K9: Observaciones | L9: Estado Factura Cliente | M9: Estado Factura Bauvek | N9: Estado material | O9: Resarcimiento Bauvek | P9: Nº Remito | Q9: Encargado
B10: =+$E$3 -> EMILIO CONTIGIANI | C10: 45986 | D10: S/N | E10: Sin factura | F10: Material arreglo | G10: Pintecord | H10: Pintura | K10: Perdida | L10: Pagado | N10: Pendiente | O10: No Pagado
B11: =+$E$3 -> EMILIO CONTIGIANI | C11: 45988 | D11: S/N | E11: Sin factura | F11: Retiro/traslado de andamios de lote 364 a 182 del terron, Mendiolaza | G11: Flete Hugo Godoy | H11: Flete | I11: 60000 | K11: a Bauvek | L11: Pagado | N11: Recibido en obra | O11: No Pagado
A12: Pasado quincena | C12: 45996
B13: =+$E$3 -> EMILIO CONTIGIANI | C13: 46045 | D13: S/N | E13: Sin factura | F13: Traslado de tejas de Contigiani a obra del terron | G13: Flete Hugo Godoy | H13: Flete | I13: 45000 | K13: a Bauvek | L13: Pagado | N13: Recibido en obra | O13: No Pagado
A14: Pasado quincena | C14: 46051
A15: Prox cierre | B15: =+$E$3 -> EMILIO CONTIGIANI | C15: 46065
A16: Prox cierre | B16: =+$E$3 -> EMILIO CONTIGIANI | C16: 46079
A17: Prox cierre | B17: =+$E$3 -> EMILIO CONTIGIANI | C17: 46093
A18: Prox cierre | B18: =+$E$3 -> EMILIO CONTIGIANI | C18: 46107
A19: Pasado quincena | C19: 46135
A20: Prox cierre | B20: =+$E$3 -> EMILIO CONTIGIANI | C20: 46149
A21: Prox cierre | B21: =+$E$3 -> EMILIO CONTIGIANI | C21: 46163
B22: =+$E$3 -> EMILIO CONTIGIANI
B23: =+$E$3 -> EMILIO CONTIGIANI
B24: =+$E$3 -> EMILIO CONTIGIANI
B25: =+$E$3 -> EMILIO CONTIGIANI
B26: =+$E$3 -> EMILIO CONTIGIANI
B27: =+$E$3 -> EMILIO CONTIGIANI
B28: =+$E$3 -> EMILIO CONTIGIANI
B29: =+$E$3 -> EMILIO CONTIGIANI
B30: =+$E$3 -> EMILIO CONTIGIANI
B31: =+$E$3 -> EMILIO CONTIGIANI
B32: =+$E$3 -> EMILIO CONTIGIANI
B33: =+$E$3 -> EMILIO CONTIGIANI
... B49: =+$E$3 -> EMILIO CONTIGIANI
H51: TOTAL | I51: =SUM(I10:I49) -> 105000

Sheet Obra RR
D2: GASTOS MATERIAL OBRA
D3: Cliente: | E3: HNOS ROSSI
D4: Domicilio: | E4: LOTE 12 - MZA 59 | F4: Localidad: Villa Ciudad Parque
F5: Barrio: Molvento
B9: OBRA | C9: Fecha de FC | D9: Condición | E9: Razón social | F9: Descripción | G9: Proveedor | H9: Rubro | I9: Importe final Pesos (Iva incluido) | J9: Importe final USD (Iva incluido) | K9: Observaciones | L9: Estado Factura Cliente | M9: Estado Factura Bauvek | N9: Estado material | O9: Resarcimiento Bauvek | P9: Nº Remito | Q9: Encargado | R9: Columna1 | S9: Columna2
B10: =+$E$3 -> HNOS ROSSI | C10: 45894 | D10: Fact-A-005426 | E10: AGRICOLA MAGDALENA SRL | F10: Hierro para fundaciones | G10: Steel Brox | H10: Obra Gruesa | I10: 9416519.6 | L10: Pagado | M10: Pagado | N10: Recibido en obra
B11: =+$E$3 -> HNOS ROSSI | C11: 45898 | D11: Fact-A-014006 | E11: AGRICOLA MAGDALENA SRL | F11: Media sombra | G11: Cerroplast | H11: Obra Preliminar | I11: 420462.9 | L11: Pagado | M11: Pagado | N11: Recibido en obra
B12: =+$E$3 -> HNOS ROSSI | C12: 45903 | D12: Fact-A-025966 | E12: AGRICOLA MAGDALENA SRL | F12: Puntales para cerco | G12: Mendio | H12: Obra Preliminar | I12: 1028351.9 | L12: Pagado | M12: Pagado | N12: Recibido en obra
B13: =+$E$3 -> HNOS ROSSI | C13: 45904 | D13: Factura | E13: Bauvek | F13: Materiales para pilar de luz | G13: Feyro | H13: Obra Electrica | I13: 173752.87 | L13: Pagado | M13: Pagado | N13: Recibido en obra
B14: =+$E$3 -> HNOS ROSSI | C14: 45936 | D14: Cheque | E14: Sin factura | F14: Obrador y baño quimico x 12 meses | G14: Natalia Obrador | H14: Obra Preliminar | I14: 2740000 | L14: Pagado | M14: Pagado | N14: Recibido en obra
B15: =+$E$3 -> HNOS ROSSI | C15: 45961 | D15: Fact-A-050342 | E15: Bauvek | F15: Materiales para pico de agua | G15: Deplano | H15: Plomeria | I15: 43028.22 | K15: Pagar y desp recuperar | L15: Cuenta Corriente | N15: Recibido en obra
B16: =+$E$3 -> HNOS ROSSI | C16: 45972 | D16: Fact-A-039846 | E16: Bauvek | F16: Mat. de plomeria para PSS | G16: Deplano | H16: Plomeria | I16: 158243.85 | K16: Pagar y desp recuperar | L16: Cuenta Corriente | N16: Recibido en obra
B17: =+$E$3 -> HNOS ROSSI | C17: 45972 | D17: Fact-A-050048 | E17: AGRICOLA MAGDALENA SRL | F17: Bombeo de hormigon | G17: Holcim | H17: Obra Gruesa | I17: 401418 | L17: Pagado | M17: Pagado | N17: Recibido en obra
B18: =+$E$3 -> HNOS ROSSI | C18: 45972 | D18: Fact-A-050009 | E18: AGRICOLA MAGDALENA SRL | F18: Servicio de instalacion | G18: Holcim | H18: Obra Gruesa | I18: 280992.6 | L18: Pagado | M18: Pagado | N18: Recibido en obra
B19: =+$E$3 -> HNOS ROSSI | C19: 45972 | D19: Fact-A-050008 | E19: AGRICOLA MAGDALENA SRL | F19: Hormigon de fundaciones | G19: Holcim | H19: Obra Gruesa | I19: 3090918.6 | L19: Pagado | M19: Pagado | N19: Recibido en obra
B20: =+$E$3 -> HNOS ROSSI | C20: 45978 | D20: Fact-A-029096 | E20: AGRICOLA MAGDALENA SRL | F20: Bomba sumergible | G20: Dimotec | H20: Plomeria | I20: 230850 | L20: Pagado | M20: Pagado | N20: Recibido en obra
B21: =+$E$3 -> HNOS ROSSI | C21: 45978 | D21: Fact-A-029097 | E21: AGRICOLA MAGDALENA SRL | F21: 25 m3 de hormigon de contrapiso H17 | G21: Pilca | H21: Obra Gruesa | I21: 4722050.1 | L21: Pagado | M21: Pagado | N21: Recibido en obra
A22: Pasado quincena
B23: =+$E$3 -> HNOS ROSSI | C23: 45986 | D23: Fact-A-027348 | E23: AGRICOLA MAGDALENA SRL | F23: Puntales, tablas cepilladas y fenolicos | G23: Mendio | H23: Obra Gruesa | I23: 4426851.4 | K23: A proveedor | L23: Pagado | M23: Pagado | N23: Recibido en obra
B24: =+$E$3 -> HNOS ROSSI | C24: 45981 | D24: Fact-A-027349 | E24: AGRICOLA MAGDALENA SRL | F24: Mallas del 6 y hierros | G24: Acerco | H24: Obra Gruesa | I24: 4889683.5 | K24: A proveedor | L24: Pagado | M24: Pagado | N24: Recibido en obra
B25: =+$E$3 -> HNOS ROSSI | C25: 45994 | D25: Fact-A-006032 | E25: AGRICOLA MAGDALENA SRL | F25: Vigas Enas (1º cuota con flete) | G25: Enas | H25: Obra Gruesa | I25: 1387870 | K25: A proveedor | L25: Pagado | M25: Pagado | N25: Recibido en obra
B26: =+$E$3 -> HNOS ROSSI | C26: 45986 | D26: Fact-A-024190 | E26: AGRICOLA MAGDALENA SRL | F26: Materiales de obra gruesa | G26: Apromax | H26: Obra Gruesa | I26: 10830205 | K26: A proveedor | L26: Pagado | M26: Pagado | N26: Acopio
B27: =+$E$3 -> HNOS ROSSI | C27: 45996 | E27: Sin factura | F27: Acopio de aridos | G27: A definir | H27: Obra Gruesa | I27: 4360746.8 | K27: A bauvek | L27: Pagado
B28: =+$E$3 -> HNOS ROSSI | C28: 45994 | D28: Fact-A-014686 | E28: AGRICOLA MAGDALENA SRL | F28: Alambron del 6 y clavos de 2,5 pulgadas | G28: Hierros Industriales | H28: Obra Gruesa | I28: 795549.58 | K28: A proveedor | L28: Pagado | M28: Pagado | N28: Recibido en obra
B29: =+$E$3 -> HNOS ROSSI | C29: 45994 | D29: Fact-A-034143 | E29: AGRICOLA MAGDALENA SRL | F29: Separadores para tabiques | G29: Sinis | H29: Obra Gruesa | I29: 479755.32 | K29: A proveedor | L29: Pagado | M29: Pagado | N29: Recibido en obra
B30: =+$E$3 -> HNOS ROSSI | C30: 45994 | D30: Fact-A-065307 | E30: AGRICOLA MAGDALENA SRL | F30: Materiales de corrugado y cajas de electricidd | G30: Feyro | H30: Obra Gruesa | I30: 1140238.2 | K30: A proveedor | L30: Pagado | M30: Pagado | N30: Recibido en obra
B31: =+$E$3 -> HNOS ROSSI | C31: 45994 | D31: Fact-A-000929 | E31: AGRICOLA MAGDALENA SRL | F31: 26 m3 de H25 y 8 m3 del H21 | G31: Pilca | H31: Hormigones | I31: 7095091.7 | K31: A proveedor | L31: Pagado | M31: Pagado
A32: Pasado quincena | C32: 45996
B33: =+$E$3 -> HNOS ROSSI | C33: 45996 | D33: Fact-A | E33: Bauvek SAS | F33: mat. Plomeria para bomba pluvial - Pago david, abonarle para recuperar | G33: Saniplast | H33: Plomeria | I33: 169554.67 | K33: A bauvek | L33: Pagado | M33: Pagado | N33: Recibido en obra
B34: =+$E$3 -> HNOS ROSSI | C34: 46365 | D34: S/N | E34: S/N | F34: Retiro de Hierros industriales, Apromax, feyro (Zona Guiñazu) y Sinis circunvalacion, envio a Molvento | G34: Flete Hugo Godoy | H34: Flete | I34: 175000 | K34: A bauvek | L34: Pagado | M34: Pagado | N34: Recibido en obra
B35: =+$E$3 -> HNOS ROSSI | C35: 46008 | D35: Fact-A 6081 | E35: AGRICOLA MAGDALENA SRL | F35: 1 | G35: Enas | H35: Encofrado | I35: 896610 | K35: A proveedor | L35: Pagado | M35: Pagado | N35: Recibido en obra
A36: Pasado quincena | C36: 46009
A37: Pasado quincena | C37: 46022
B38: =+$E$3 -> HNOS ROSSI | C38: 46034 | D38: Fact-A-006421 | E38: AGRICOLA MAGDALENA SRL | F38: 8 placas metalicas 25x25 para columnas | G38: Roncaglia | H38: Plegados | I38: 184000 | K38: A proveedor | L38: Pagado | M38: Pagado | N38: Recibido en obra
B39: =+$E$3 -> HNOS ROSSI | C39: 46034 | D39: Fact-A-72762,72761,72765,72763,72764 | E39: AGRICOLA MAGDALENA SRL | F39: Materiales de agua, cloaca, pluvial y gas | G39: Saniplast | H39: Plomeria | I39: 7215137.5 | K39: A proveedor | L39: Pagado | M39: Pagado | N39: Recibido en obra
B40: =+$E$3 -> HNOS ROSSI | C40: 46034 | D40: Fact-A-00958 | E40: AGRICOLA MAGDALENA SRL | F40: Hormigon para pilotes y vigas PB | G40: Pilca | H40: Hormigon | I40: 4103527.6 | K40: A proveedor | L40: Pagado | M40: Pagado
B41: =+$E$3 -> HNOS ROSSI | C41: 46034 | D41: Fact-A-30187 | E41: AGRICOLA MAGDALENA SRL | F41: 50% de excavacion de pilotes PB | G41: Canteras El Alto | H41: Pilotes | I41: 509476.55 | K41: A proveedor | L41: Pagado | M41: Pagado | N41: Recibido en obra
B42: =+$E$3 -> HNOS ROSSI | C42: 46034 | D42: Fact-A-24358 | E42: AGRICOLA MAGDALENA SRL | F42: Hierros para pilotes y vigas fundacion PB | G42: Apromax | H42: Obra Gruesa | I42: 2908060 | K42: A proveedor | L42: Pagado | M42: Pagado | N42: Recibido en obra
B43: =+$E$3 -> HNOS ROSSI | C43: 46035 | D43: Fact-A | E43: Bauvek SAS | F43: Alquiler de 2 vibros bosh se uso en el hormigon del 22/12/2025 | G43: Alquilo Todo | H43: Alquiler | I43: 100000 | K43: A bauvek | L43: Pagado | M43: Pagado | N43: Recibido en obra
B44: =+$E$3 -> HNOS ROSSI | C44: 46035 | D44: Efectivo | E44: Sin factura | F44: Flete materiales de plomería | G44: Flete Hugo Godoy | H44: Fletes | I44: 95000 | K44: A bauvek | L44: Pagado | M44: Pagado | N44: Recibido en obra
A45: Pasado quincena | C45: 46037
B46: =+$E$3 -> HNOS ROSSI | C46: 46043 | D46: S/N | E46: Sin factura | F46: Placas roncaglia a oficina | G46: Flete Hugo Godoy | H46: Fletes | I46: 45000 | K46: A bauvek | L46: Pagado | M46: Pagado | N46: Recibido en obra
B47: =+$E$3 -> HNOS ROSSI | C47: 46049 | D47: S/N | E47: Sin factura | F47: Flete devolución ENAS de Molvento a centro | G47: Flete Yonatan | H47: Fletes | I47: 380000 | K47: A bauvek | L47: Pagado | M47: Pagado | N47: Recibido en obra
B48: =+$E$3 -> HNOS ROSSI | C48: 46048 | D48: Fact-A-24438 | E48: AGRICOLA MAGDALENA SRL | F48: Materiales de obra gruesa para PB | G48: Apromax | H48: Obra Gruesa | I48: 10742274 | K48: A proveedor | L48: Pagado | M48: Pagado | N48: Acopio
B49: =+$E$3 -> HNOS ROSSI | C49: 45975 | D49: Fact-A-14772 | E49: Bauvek SAS | F49: Nylon 200 micrones para contrapiso PSS | G49: Cerroplast | H49: Obra Gruesa | I49: 49059.45 | K49: A bauvek | L49: Pagado | M49: Pagado | N49: Recibido en obra
A50: Pasado quincena | C50: 46051
B51: =+$E$3 -> HNOS ROSSI | C51: 46052 | D51: Fact-A 24451 | E51: AGRICOLA MAGDALENA SRL | F51: Hierros para columnas PB y mallas contrapiso | G51: Apromax | H51: Obra Gruesa | I51: 2681848.2 | K51: A proveedor | L51: Pagado | N51: Recibido en obra
B52: =+$E$3 -> HNOS ROSSI | C52: 46034 | D52: Fact-A 6126 | E52: AGRICOLA MAGDALENA SRL | F52: Alquiler Enas Contrato 6643-A0 | G52: Enas | H52: Encofrado | I52: 802692.97 | K52: A proveedor | L52: Pagado | N52: Recibido en obra
B53: =+$E$3 -> HNOS ROSSI | C53: 46044 | D53: Fact-A 6179 | E53: AGRICOLA MAGDALENA SRL | F53: Alquiler Enas Contrato 6643-A1 | G53: Enas | H53: Encofrado | I53: 761178.33 | K53: A proveedor | L53: Pagado | N53: Recibido en obra
B54: =+$E$3 -> HNOS ROSSI | C54: 46057 | D54: S/N | E54: Sin factura | F54: Materiales de agua desde Saniplast hasta obra | G54: Flete Hugo Godoy | H54: Fletes | I54: 185000 | K54: A bauvek | L54: Pagado | N54: Recibido en obra
B55: =+$E$3 -> HNOS ROSSI | C55: 46063 | D55: Fact-A 28334 | E55: AGRICOLA MAGDALENA SRL | F55: Tablas cepilladas, fenolicos, puntales para losa PB | G55: Mendio | H55: Encofrado | I55: 2742735.2 | K55: A proveedor | L55: Pagado | N55: Recibido en obra
B56: =+$E$3 -> HNOS ROSSI | C56: 46063 | D56: Fact-A 24496 | E56: AGRICOLA MAGDALENA SRL | F56: Hierros viga y losa PB, viguetas y ladrilllos PB | G56: Apromax | H56: Obra Gruesa | I56: 13033670 | K56: A proveedor | L56: Pagado | N56: Recibido en obra
A57: Pasado quincena | C57: 46065
B58: =+$E$3 -> HNOS ROSSI
A59: Pasado quincena | C59: 46079
B60: =+$E$3 -> HNOS ROSSI | C60: 46084 | D60: Fact-A 6284 | E60: AGRICOLA MAGDALENA SRL | F60: 1º Alquiler Enas Contrato 6643-A2 | G60: Enas | H60: Encofrado | I60: 1336445 | K60: A proveedor | L60: Pagado | N60: Recibido en obra
B61: =+$E$3 -> HNOS ROSSI | C61: 46087 | D61: Fact-A 6215 | E61: AGRICOLA MAGDALENA SRL | F61: Mes Alquiler Enas Contrato 6643-A0 | G61: Enas | H61: Encofrado | I61: 813127.97 | K61: A proveedor | L61: Pagado | N61: Recibido en obra
B62: =+$E$3 -> HNOS ROSSI | C62: 46090 | D62: Fact-A 001034 | E62: AGRICOLA MAGDALENA SRL | F62: 9 m3 de Hº alivianado y 12 m3 de H21 q se adeudaba | G62: Pilca | H62: Hormigón | I62: 4179592 | K62: A proveedor | L62: Pagado | N62: Recibido en obra
B63: =+$E$3 -> HNOS ROSSI | C63: 46090 | D63: Fact-A 001032 | E63: AGRICOLA MAGDALENA SRL | F63: 19 m3 de H25 q se adeudaba | G63: Pilca | H63: Hormigón | I63: 4084060.9 | K63: A proveedor | L63: Pagado | N63: Recibido en obra
B64: =+$E$3 -> HNOS ROSSI | D64: S/N | E64: Sin factura | F64: Alquiler 2º obrador por 6 meses | G64: Natalia Marin | H64: Obra Gruesa | I64: 980000 | K64: A bauvek | L64: Pagado | N64: Recibido en obra
B65: =+$E$3 -> HNOS ROSSI | C65: 46094 | D65: S/N | E65: Sin factura | F65: Traslado alambron | G65: Flete Hugo Godoy | I65: 60000 | K65: A bauvek | L65: Pagado | M65: Pagado | N65: Recibido en obra
A66: Pasado quincena | C66: 46093
B67: =+$E$3 -> HNOS ROSSI | C67: 46094 | D67: Fact-A 00297111 | E67: AGRICOLA MAGDALENA SRL | F67: Perfiles UPN 100 y UPN 140 | G67: Serin | H67: Herrería | I67: 1770534.6 | K67: A proveedor | L67: Pagado | N67: Recibido en obra
B68: =+$E$3 -> HNOS ROSSI | C68: 46100 | D68: Fact-A 00297396 | E68: AGRICOLA MAGDALENA SRL | F68: Hierros para losa PB | G68: Serin | H68: Herrería | I68: 2283844.5 | K68: A proveedor | L68: Pagado | N68: Recibido en obra
B69: =+$E$3 -> HNOS ROSSI | C69: 46100 | D69: Fact-A 000172413 | E69: AGRICOLA MAGDALENA SRL | F69: Alambres y clavos | G69: Serin | H69: Herrería | I69: 1348409.7 | K69: A proveedor | L69: Pagado | N69: Recibido en obra
A70: Pasado quincena | C70: 46107
B71: =+$E$3 -> HNOS ROSSI | C71: 46121 | D71: Fact-A 00006266 | E71: AGRICOLA MAGDALENA SRL | F71: Alquiler Enas Contrato 6643-A1 | G71: Enas | H71: Encofrado | I71: 777163.07 | K71: A proveedor | L71: Pagado | N71: Recibido en obra
B72: =+$E$3 -> HNOS ROSSI | C72: 46121 | D72: Fact-A 00006305 | E72: AGRICOLA MAGDALENA SRL | F72: Alquiler Enas Contrato 6643-A0 | G72: Enas | H72: Encofrado | I72: 830203.66 | K72: A proveedor | L72: Pagado | N72: Recibido en obra
B73: =+$E$3 -> HNOS ROSSI | C73: 46107 | D73: Fact-A 00006354 | E73: AGRICOLA MAGDALENA SRL | F73: Alquiler Enas Contrato 6643-A1 | G73: Enas | H73: Encofrado | I73: 785711.87 | K73: A proveedor | L73: Pagado | N73: Recibido en obra
B74: =+$E$3 -> HNOS ROSSI | C74: 46119 | D74: Fact-A 00006375 | E74: AGRICOLA MAGDALENA SRL | F74: Alquiler Enas Contrato 6643-A0 | G74: Enas | H74: Encofrado | I74: 839335.91 | K74: A proveedor | L74: Pagado | N74: Recibido en obra
B75: =+$E$3 -> HNOS ROSSI | C75: 46119 | D75: Fact-A 00006378 | E75: AGRICOLA MAGDALENA SRL | F75: Alquiler Enas Contrato 6643-A2 | G75: Enas | H75: Encofrado | I75: 1192115.6 | K75: A proveedor | L75: Pagado | N75: Recibido en obra
A76: Pasado quincena | B76: =+$E$3 -> HNOS ROSSI | C76: 46121
B77: =+$E$3 -> HNOS ROSSI | C77: 46121 | D77: Fact-A 00006734 | E77: AGRICOLA MAGDALENA SRL | F77: Rolados y sombreretes para asador | G77: Roncaglia | H77: Herrería | I77: 893000 | K77: A proveedor | L77: Pagado | N77: Recibido en obra
B78: =+$E$3 -> HNOS ROSSI | C78: 46122 | D78: Fact-A 00003169 | E78: AGRICOLA MAGDALENA SRL | F78: Separadores para losa PB | G78: Hermida | H78: Separadores | I78: 31275 | K78: A proveedor | L78: Pagado | N78: Recibido en obra
B79: =+$E$3 -> HNOS ROSSI | C79: 46132 | D79: Fact-A 00074747 | E79: BAUVEK S.A.S. | F79: 6 caños de 40 duratop color negro | G79: Saniplast | H79: Plomería | I79: 54179.7 | K79: A bauvek | L79: Pagado | N79: Recibido en obra
B80: =+$E$3 -> HNOS ROSSI | C80: 46132 | D80: S/N | E80: Sin factura | F80: Traslado de 6 caños duratop y rolados | G80: Flete Hugo Godoy | H80: Fletes | I80: 176000 | K80: A bauvek | L80: Pagado | N80: Recibido en obra
B81: =+$E$3 -> HNOS ROSSI | C81: 46133 | D81: S/N | E81: Sin factura | F81: Traslado 40 puntales y 30 vigas enas | G81: Flete Gonza Moreno | H81: Fletes | I81: 190000 | K81: A bauvek | L81: Pagado | M81: Pagado | N81: Recibido en obra
A82: Pasado quincena | B82: =+$E$3 -> HNOS ROSSI | C82: 46136
B83: =+$E$3 -> HNOS ROSSI | C83: 46136 | D83: Fact-A 000298837 | E83: AGRICOLA MAGDALENA SRL | F83: Perfiles UPN 300 | G83: Serin | H83: Herrería | I83: 8098611.2 | K83: A proveedor | L83: Pagado | N83: Recibido en obra
B84: =+$E$3 -> HNOS ROSSI | C84: 46146 | D84: Fact-A 000001101 | E84: AGRICOLA MAGDALENA SRL | F84: 36 m3 de H25 para losa PB | G84: Pilca | H84: Hormigón | I84: 8452545.6 | K84: A proveedor | L84: Pagado | N84: Recibido en obra
B85: =+$E$3 -> HNOS ROSSI | C85: 46147 | D85: Fact-A 000024496 | E85: AGRICOLA MAGDALENA SRL | F85: Materiales de obra gruesa según presup. Nº 224356 | G85: Apromax | H85: Obra Gruesa | I85: 7558058.3 | K85: A proveedor | L85: Pagado | N85: Recibido en obra
A86: Pasado quincena | B86: =+$E$3 -> HNOS ROSSI | C86: 46149
B87: =+$E$3 -> HNOS ROSSI | C87: 46149 | D87: S/N | E87: Sin factura | F87: Planchuelas metalicas para vigas met en PA | G87: Maxi Herrero | H87: Herrería | I87: 640283.96 | K87: A bauvek | L87: No Pagado | N87: Recibido en obra
B88: =+$E$3 -> HNOS ROSSI | C88: 46149 | D88: Fact-A 1453 | E88: BAUVEK S.A.S. | F88: Alquiler 1 Bomba sumergible 1 750/1100W. | desde el 07/04/2026 al 16/04/2026 | G88: Alquilo Todo VGB | H88: Alquiler | I88: 77790 | K88: A bauvek | L88: No Pagado | N88: Recibido en obra
B89: =+$E$3 -> HNOS ROSSI | C89: 46150 | D89: Fact-A 0000299500 | E89: AGRICOLA MAGDALENA SRL | F89: Hierros de planta alta | G89: Serin | H89: Hierros | I89: 2820085.4 | K89: A proveedor | L89: Pagado | N89: Recibido en obra
B90: =+$E$3 -> HNOS ROSSI | C90: 46153 | D90: Fact-A 000016315 | E90: AGRICOLA MAGDALENA SRL | F90: Rollo de media sombra de 2 mts de ancho | G90: Cerroplast | H90: Obra Gruesa | I90: 162660 | K90: A proveedor | L90: Pagado | N90: Recibido en obra
B91: =+$E$3 -> HNOS ROSSI | C91: 46150 | D91: S/N | E91: Sin factura | F91: 30 housing | G91: Zingueria Villa Allende | H91: Herrería | I91: 90000 | K91: A bauvek | L91: Pagado | N91: Recibido en obra
B92: =+$E$3 -> HNOS ROSSI | C92: 46160 | D92: Fact-A 000024892 | E92: AGRICOLA MAGDALENA SRL | F92: Viguetas y ladrillos de losa 11,5 de PA | G92: Apromax | H92: Obra Gruesa | I92: 1081752.4 | K92: A proveedor | L92: Pagado | N92: Recibido en obra
B93: =+$E$3 -> HNOS ROSSI | C93: 46156 | D93: S/N | E93: Sin factura | F93: Traslado de mediasombra | G93: Flete Hugo Godoy | H93: Fletes | I93: 62000 | K93: A bauvek | L93: No Pagado | N93: Recibido en obra
B94: =+$E$3 -> HNOS ROSSI | C94: 46161 | E94: AGRICOLA MAGDALENA SRL | F94: Perfiles UPN 300 y UPN 200, mallas del 6 | G94: Serin | H94: Hierros | K94: A proveedor | L94: No Pagado | N94: Recibido en obra
B95: =+$E$3 -> HNOS ROSSI | C95: 46161 | D95: Fact-A 00075392 | E95: AGRICOLA MAGDALENA SRL | F95: Material de gas | G95: Saniplast | H95: Plomería | I95: 953421.97 | K95: A proveedor | L95: Pagado | N95: Recibido en obra
B96: =+$E$3 -> HNOS ROSSI | C96: 46161 | D96: Fact-A 00075393 | E96: AGRICOLA MAGDALENA SRL | F96: Material de cloaca | G96: Saniplast | H96: Plomería | I96: 213348.55 | K96: A proveedor | L96: Pagado | N96: Recibido en obra
B97: =+$E$3 -> HNOS ROSSI | C97: 46161 | D97: Fact-A 00075394 | E97: AGRICOLA MAGDALENA SRL | F97: Material de agua | G97: Saniplast | H97: Plomería | I97: 2708041 | K97: A proveedor | L97: Pagado | N97: Recibido en obra
B98: =+$E$3 -> HNOS ROSSI | C98: 46163 | D98: Fact-A 000029779 | E98: AGRICOLA MAGDALENA SRL | F98: Puntales, tablas, fenolicos y chanfles para PA | G98: Mendio SA | H98: Encofrado | I98: 4386077 | K98: A proveedor | L98: Pagado | N98: Recibido en obra
A99: Pasado quincena | B99: =+$E$3 -> HNOS ROSSI | C99: 46163
B100: =+$E$3 -> HNOS ROSSI | C100: 46169 | D100: S/N | E100: Sin factura | F100: Traslado de materiales de plomeria | G100: Flete Hugo Godoy | H100: Fletes | I100: 175000 | K100: A bauvek | L100: Pagado
B101: =+$E$3 -> HNOS ROSSI | C101: 46182 | D101: S/N | E101: Sin factura | F101: Devolución de viguetas 2,20 y 2,80 de obra a Apromax | G101: Flete Gonza Moreno | H101: Fletes | I101: 230000 | K101: A Bauvek | L101: No Pagado
A102: Pasado quincena | B102: =+$E$3 -> HNOS ROSSI | C102: 46177
B103: =+$E$3 -> HNOS ROSSI | C103: 46134 | D103: Fact-A 00006431 | E103: AGRICOLA MAGDALENA SRL | F103: Alquiler Enas Contrato 6643-A1 | G103: Enas | H103: Encofrado | I103: 792783.28 | K103: A proveedor | L103: Pagado | N103: Recibido en obra
B104: =+$E$3 -> HNOS ROSSI | C104: 46134 | D104: Fact-A 00006434 | E104: AGRICOLA MAGDALENA SRL | F104: Alquiler Enas Contrato 6643-A3 | G104: Enas | H104: Encofrado | I104: 416240 | K104: A proveedor | L104: Pagado | N104: Recibido en obra
...

Sheet Obra EM
D2: GASTOS MATERIAL OBRA
D3: Cliente: | E3: Esteban y Matias
D4: Domicilio: | E4: Mza 3 - lote 16 | F4: Localidad: | H4: La Calera
E5: Vistas de La Deseada
B9: OBRA | C9: Fecha de FC | D9: Condición | E9: Razón social | F9: Descripción | G9: Proveedor | H9: Rubro | I9: Importe final Pesos (Iva incluido) | J9: Importe final USD (Iva incluido) | K9: Observaciones | L9: Estado Factura Cliente | M9: Estado Factura Bauvek | N9: Estado material | O9: Resarcimiento Bauvek | P9: Nº Remito | Q9: Encargado | R9: Columna1
B10: =+$E$3 -> Esteban y Matias | C10: 46125 | D10: s/n | E10: Sin factura | F10: 50% pago anticipo de moviemiento de suelo | G10: Pellicer | H10: Mov. Suelo | I10: 19250000 | K10: A bauvek | L10: Pagado | M10: Pagado | N10: Recibido en obra
A11: Pasado quincena | B11: =+$E$3 -> Esteban y Matias | C11: 46121
B12: =+$E$3 -> Esteban y Matias | C12: 46133 | D12: s/n | E12: Sin factura | F12: media sombra, alambre galvanizado | G12: Cerroplast | H12: cerco obra | I12: 710063 | K12: A bauvek | L12: Pagado | M12: Pagado | N12: Recibido en obra
B13: =+$E$3 -> Esteban y Matias | C13: 46133 | D13: s/n | E13: Sin factura | F13: Puntales de madera y tablas para corralito | G13: Mendio SA | H13: cerco obra | I13: 914394.4 | K13: A bauvek | L13: Pagado | M13: Pagado | N13: Recibido en obra
B14: =+$E$3 -> Esteban y Matias | C14: 46133 | D14: s/n | E14: Sin factura | F14: Baño quimico y obrador por 6 meses | G14: Conte Mas | H14: Obrador | I14: 710000 | K14: A bauvek | L14: Pagado | M14: Pagado | N14: Recibido en obra
A15: Pasado quincena | B15: =+$E$3 -> Esteban y Matias
B16: =+$E$3 -> Esteban y Matias | C16: 46147 | D16: Fact | E16: consumidor final | F16: Material pilar de luz | G16: Feyro | H16: pilar luz | I16: 255983.44 | K16: a proveedor | L16: Pagado | M16: Pagado | N16: Recibido en obra
B17: =+$E$3 -> Esteban y Matias | C17: 46147 | D17: Fact | E17: consumidor final | F17: Material cerco obra | G17: Acerco | H17: cerco obra | I17: 605305.09 | K17: a proveedor | L17: Pagado | M17: Pagado | N17: Recibido en obra
B18: =+$E$3 -> Esteban y Matias | C18: 46147 | D18: Fact | E18: consumidor final | F18: Material canilla | G18: Deplano | H18: canilla | I18: 15956.44 | K18: a proveedor | L18: Pagado | M18: Pagado | N18: Recibido en obra
A19: Pasado quincena | B19: =+$E$3 -> Esteban y Matias | C19: 46149
B20: =+$E$3 -> Esteban y Matias | C20: 46162 | D20: s/n | E20: Sin factura | F20: Hierros fundacion y arena | G20: Merlino | H20: obra gruesa | I20: 3619700 | K20: a proveedor | L20: Pagado | M20: Pagado | N20: Pendiente
B21: =+$E$3 -> Esteban y Matias | C21: 46163 | D21: Fact | E21: consumidor final | F21: proyector solar ABS 800ml 5700K luz fria + panel solar | G21: Feyro | H21: iluminacion | I21: 43724.11 | K21: A bauvek | L21: Pagado | M21: Pagado | N21: Recibido en obra
B22: =+$E$3 -> Esteban y Matias | C22: 46154 | D22: s/n | E22: Sin factura | F22: Carga en Cerroplast, Deplano, Feyro, taller del herrero | G22: Flete Hugo Godoy | H22: flete | I22: 120000 | K22: A bauvek | L22: Pagado | M22: Pagado | N22: Recibido en obra
A23: Pasado quincena | B23: =+$E$3 -> Esteban y Matias | C23: 46163
A24: Pasado quincena | B24: =+$E$3 -> Esteban y Matias | C24: 46177
B25: =+$E$3 -> Esteban y Matias | C25: 46178 | D25: s/n | E25: Sin factura | F25: Acopio de H° fundaciones y tabiques hasta planta subsuelo | G25: Hormiblock | H25: Hormigon | I25: 22416250 | K25: A bauvek | L25: Pagado | M25: Pagado | N25: Recibido en obra
B26: =+$E$3 -> Esteban y Matias | C26: 46178 | D26: s/n | E26: Sin factura | F26: Materiales obra gruesa fundaciones | G26: Apromax | H26: obra gruesa | I26: 9444594.1 | K26: A bauvek | L26: Pagado | M26: Pagado | N26: Recibido en obra
B27: =+$E$3 -> Esteban y Matias
A28: Pasado quincena | B28: =+$E$3 -> Esteban y Matias | C28: 46191
B29: =+$E$3 -> Esteban y Matias | C29: 46199 | D29: s/n | E29: Sin factura | F29: Traslado de material de SINIS a vistas de la deseada | G29: Flete Jonatan | H29: flete | I29: 200000 | K29: A bauvek | L29: Pagado | M29: Pagado | N29: Recibido en obra
B30: =+$E$3 -> Esteban y Matias | C30: 46199 | D30: s/n | E30: Sin factura | F30: Traslado de material de SINIS a vistas de la deseada | G30: Flete Jonatan | H30: flete | I30: 200000 | K30: A bauvek | L30: Pagado | M30: Pagado | N30: Recibido en obra
B31: =+$E$3 -> Esteban y Matias
A32: Pasado quincena | B32: =+$E$3 -> Esteban y Matias | C32: 46205
B33: =+$E$3 -> Esteban y Matias | C33: 46211 | D33: S/N | E33: Sin factura | F33: Flete de tablas de madera de obra JS a obra | G33: Flete Gonza Moreno | H33: Fletes | I33: 200000 | K33: A Bauvek | L33: No Pagado | M33: No Pagado | N33: Recibido en obra
B34: =+$E$3 -> Esteban y Matias | C34: 46211 | D34: S/N | E34: Sin factura | F34: Flete de fenolicos a obra | G34: Flete Hugo Godoy | H34: flete | I34: 70000 | K34: A Bauvek | L34: No Pagado | M34: No Pagado | N34: Recibido en obra
B35: =+$E$3 -> Esteban y Matias | C35: 46205 | D35: Fact 29008 | E35: bauvek | F35: Cuñas y buñas a cuenta de bauvek | G35: Mendio SA | H35: material | I35: 368917.65 | K35: a proveedor | L35: No Pagado | M35: No Pagado | N35: Recibido en obra
B36: =+$E$3 -> Esteban y Matias | C36: 46210 | D36: Fact 29058 | E36: Bauvek | F36: Fenolicos a cuenta de bauvek | G36: Mendio SA | H36: material | I36: 325000.25 | K36: a proveedor | L36: No Pagado | M36: No Pagado | N36: Recibido en obra
A37: Pasado quincena | B37: =+$E$3 -> Esteban y Matias | C37: 46219
B38: =+$E$3 -> Esteban y Matias | C38: 46223 | D38: S/N | E38: Sin factura | F38: Devolucion de material en alquiler SINIS | G38: Flete Fede Castro | H38: flete | I38: 170000 | K38: A Bauvek | L38: Pagado | M38: Pagado | N38: Recibido en obra
B39: =+$E$3 -> Esteban y Matias | C39: 46224 | D39: S/N | E39: Sin factura | F39: Devolucion de material en alquiler SINIS | G39: Flete Fede Castro | H39: flete | I39: 170000 | K39: A Bauvek | L39: Pagado | M39: Pagado | N39: Recibido en obra
B40: =+$E$3 -> Esteban y Matias | C40: 46218 | D40: Fact 2004 | E40: Bauvek | F40: Perfiles metalicos | G40: Serin | H40: perfiles | I40: 2350729.1 | K40: A Bauvek | L40: Pagado | M40: No Pagado | N40: Recibido en obra
B41: =+$E$3 -> Esteban y Matias | D41: nota de credito | E41: Bauvek | F41: Perfiles metalicos | G41: Serin | H41: nota de credito | I41: -43692 | K41: A Bauvek | L41: No Pagado | M41: No Pagado | N41: Recibido en obra
B42: =+$E$3 -> Esteban y Matias | C42: 46230 | D42: S/N | E42: Sin factura | F42: Granza 1.3 | G42: Merlino | H42: aridos | I42: 319803 | K42: A Bauvek | L42: Pagado | M42: Pagado | N42: Recibido en obra
B43: =+$E$3 -> Esteban y Matias | C43: 46231 | D43: S/N | E43: Sin factura | F43: Fenolicos, buñas, | G43: Mendio SA | H43: material | K43: A Bauvek | L43: Pagado | M43: No Pagado | N43: Recibido en obra
B44: =+$E$3 -> Esteban y Matias | C44: 46231 | D44: S/N | E44: Sin factura | F44: Puntales | G44: Mendio SA | H44: material | I44: 542491.2 | K44: A Bauvek | L44: Pagado | M44: Pagado | N44: Recibido en obra
A45: Pasado quincena | B45: =+$E$3 -> Esteban y Matias | C45: 46233
B46: =+$E$3 -> Esteban y Matias | C46: 46245 | D46: S/N | E46: Sin factura | F46: Hierros industriales | G46: Hierros Industriales | H46: material | I46: 9176000 | K46: A Bauvek | L46: Pagado | M46: Pagado | N46: Recibido en obra
B47: =+$E$3 -> Esteban y Matias
A48: Pasado quincena | B48: =+$E$3 -> Esteban y Matias | C48: 46247
B49: =+$E$3 -> Esteban y Matias | E49: Bauvek | F49: 1 Martillo neumatico - dias a confirmar | G49: Alquilo Todo | H49: equipo | K49: A Bauvek | L49: No Pagado | M49: No Pagado | N49: Recibido en obra
B50: =+$E$3 -> Esteban y Matias | C50: 46253 | E50: Bauvek | F50: 1 canguro - dias a confirmar | G50: Alquilo Todo | H50: equipo | K50: A Bauvek | L50: No Pagado | M50: No Pagado | N50: Recibido en obra
B51: =+$E$3 -> Esteban y Matias | C51: 46254 | D51: S/N | E51: Sin factura | F51: Fenolicos y puntales | G51: Mendio SA | H51: material | I51: 1449690 | K51: A Bauvek | L51: No Pagado | M51: No Pagado
B52: =+$E$3 -> Esteban y Matias | C52: 46255 | D52: S/N | E52: Sin factura | F52: 10 viajes de tierra | G52: Raúl Olmedo | H52: tierra | I52: 2700000 | K52: A Bauvek | L52: No Pagado | M52: No Pagado | N52: Recibido en obra
B53: =+$E$3 -> Esteban y Matias | C53: 46255 | E53: Bauvek | F53: Losa y voladizo de subsuelo | G53: Sinis | H53: encofrados | J53: 760.66 | K53: A Bauvek | L53: No Pagado | M53: No Pagado | Q53: Esperando que facturen y transfiere cliente
B54: =+$E$3 -> Esteban y Matias | C54: 46255 | E54: Bauvek | F54: Tabiques de planta baja y planta alta | G54: Sinis | H54: encofrados | J54: 2395.8 | K54: A Bauvek | L54: No Pagado | M54: No Pagado | Q54: Esperando que facturen y transfiere cliente
B55: =+$E$3 -> Esteban y Matias | C55: 46259 | D55: S/N | E55: Sin factura | F55: Flete de SINIS a obra en vistas la deseada | G55: Flete Fede Castro | H55: flete | I55: 180000 | K55: A Bauvek | L55: No Pagado | M55: No Pagado
B56: =+$E$3 -> Esteban y Matias | C56: 46260 | D56: S/N | E56: Sin factura | F56: Flete de SINIS a obra en vistas la deseada | G56: Flete Fede Castro | H56: flete | I56: 180000 | K56: A Bauvek | L56: No Pagado | M56: No Pagado
B57: =+$E$3 -> Esteban y Matias
A58: Pasado quincena | B58: =+$E$3 -> Esteban y Matias | C58: 46261
B59: =+$E$3 -> Esteban y Matias | C59: 46266 | D59: S/N | E59: Sin factura | F59: Flete de Jonathan. Material de Sinis a la obra | G59: Flete Jonatan | H59: Flete | I59: 200000 | K59: A Bauvek | L59: No Pagado | M59: No Pagado
B60: =+$E$3 -> Esteban y Matias | C60: 46274 | D60: S/N | E60: Sin factura | F60: 2 fletes de Jonathan. Material de Sinis a la obra | G60: Flete Jonatan | H60: Flete | I60: =2*200000 -> 400000 | K60: A Bauvek | L60: No Pagado | M60: No Pagado | R60: Por hacerse
B61: =+$E$3 -> Esteban y Matias | C61: 46275 | D61: S/N | E61: Sin factura | F61: Flete de Jonathan. Material de Sinis a la obra | G61: Flete Jonatan | H61: Flete | I61: =2*200000 -> 400000 | K61: A Bauvek | L61: No Pagado | M61: No Pagado | R61: Por hacerse
B62: =+$E$3 -> Esteban y Matias
B63: =+$E$3 -> Esteban y Matias
B64: =+$E$3 -> Esteban y Matias
B65: =+$E$3 -> Esteban y Matias
A66: Prox cierre | B66: =+$E$3 -> Esteban y Matias | C66: 46275
B67: =+$E$3 -> Esteban y Matias | C67: 46288 | D67: S/N | E67: Bauvek | F67: 1 canguro x 4 dias | G67: Alquilo Todo | H67: Alquiler | I67: 168000 | K67: A Bauvek | L67: No Pagado | M67: No Pagado
B68: =+$E$3 -> Esteban y Matias | C68: 46288 | D68: S/N | E68: Sin factura | F68: Traslado de canguro desde alquilo todo a obra | G68: Flete Hugo Godoy | H68: Flete | I68: 60000 | K68: A Bauvek | L68: No Pagado
B69: =+$E$3 -> Esteban y Matias
B70: =+$E$3 -> Esteban y Matias
H72: TOTAL | I72: =SUM(I10:I70) -> 77892910

Sheet Obra LS
D2: GASTOS MATERIAL OBRA
D3: Cliente: | E3: Rodolfo Subias y Melisa Lew
D4: Domicilio: | E4: Lote 364 | F4: Localidad: | H4: El terrón, Mendiolaza
B9: OBRA | C9: Fecha de FC | D9: Condición | E9: Razón social | F9: Descripción | G9: Proveedor | H9: Rubro | I9: Importe final Pesos (Iva incluido) | J9: Importe final USD (Iva incluido) | K9: Observaciones | L9: Estado Factura Cliente | M9: Estado Factura Bauvek | N9: Estado material | O9: Resarcimiento Bauvek | P9: Nº Remito | Q9: Encargado
B10: =+$E$3 -> Rodolfo Subias y Melisa Lew | C10: 45979 | D10: Fact B | E10: Rodolfo Subias | F10: 1 caja de porcellanato baño PA para guarda | G10: Ferrocons | H10: Terminación int | I10: 47173.87 | L10: Pagado | N10: Recibido en obra
B11: =+$E$3 -> Rodolfo Subias y Melisa Lew | C11: 45979 | D11: Fact A | E11: Bauvek | F11: 1 caja de porcellanato por rotura en baño PA | G11: Ferrocons | H11: Terminación int | I11: 48343.47 | K11: Perdida | L11: Pagado | N11: Recibido en obra | O11: Pagado
B12: =+$E$3 -> Rodolfo Subias y Melisa Lew | C12: 45979 | D12: Fact B | E12: Rodolfo Subias | F12: Materiales plomeria pluvial | G12: Saniplast | H12: Ints. Pluvial | I12: 600778.52 | K12: a proveedor | L12: Pagado | N12: Recibido en obra
B13: =+$E$3 -> Rodolfo Subias y Melisa Lew | C13: 45979 | D13: Fact B | E13: Rodolfo Subias | F13: Mat. Pintura parte metalica | G13: Garin | H13: Mat. Pintura | I13: 264716.03 | K13: a proveedor | L13: Pagado | N13: Recibido en obra
B14: =+$E$3 -> Rodolfo Subias y Melisa Lew | C14: 45979 | D14: S/N | F14: Retiro de Acerco, Ferrocons,Garin, Saniplast al terrón | G14: Flete Hugo Godoy | H14: Flete | I14: 125000 | L14: Pagado | N14: Recibido en obra
A15: Pasado quincena
B16: =+$E$3 -> Rodolfo Subias y Melisa Lew | C16: 45996 | D16: Fact A | E16: Rodolfo Subias | F16: Mat. Pegamento/pastina | G16: Contigiani | H16: Mat. Obra gruesa | I16: 1680775.1 | K16: a proveedor | L16: Pagado | N16: Recibido en obra
B17: =+$E$3 -> Rodolfo Subias y Melisa Lew | C17: 45993 | D17: S/N | E17: - | F17: ACERCO-CONTIGIANI al lote 364 | G17: Flete Hugo Godoy | H17: Flete | I17: 80000 | K17: a Bauvek | L17: Pagado | N17: Recibido en obra
B18: =+$E$3 -> Rodolfo Subias y Melisa Lew | C18: 45995 | D18: S/N | E18: - | F18: 1 viaje de arena gruesa (ya pagado cliente a Bauvek) | G18: Nico Carusso | H18: Aridos | I18: 140000 | K18: a Bauvek | L18: Pagado | N18: Recibido en obra
A19: Pasado quincena | C19: 45996
B20: =+$E$3 -> Rodolfo Subias y Melisa Lew | C20: 46009 | D20: S/N | E20: - | F20: 1 viaje de arena gruesa (ya pagado cliente a Bauvek) | G20: Nico Carusso | H20: Aridos | I20: 140000 | K20: a Bauvek | L20: Pagado | N20: Recibido en obra
A21: Pasado quincena | C21: 46009
A22: Pasado quincena | C22: 46022
B23: =+$E$3 -> Rodolfo Subias y Melisa Lew | C23: 45984 | D23: S/N | F23: Retiro de jack srl al terron (material durlock) | G23: Flete Hugo Godoy | H23: Flete | I23: 68000 | K23: a Bauvek | L23: Pagado | N23: Recibido en obra
A24: Pasado quincena | C24: 46037
B25: =+$E$3 -> Rodolfo Subias y Melisa Lew | C25: 46036 | D25: S/N | F25: Retiro de ACERCO a taller de herrero en villa allende | G25: Flete Hugo Godoy | H25: Flete | I25: 35000 | K25: a Bauvek | L25: Pagado | N25: Recibido en obra
B26: =+$E$3 -> Rodolfo Subias y Melisa Lew | C26: 46048 | D26: S/N | F26: Devolucion de andamios del terron a GUATICOR | G26: Flete Hugo Godoy | H26: Flete | I26: 54000 | K26: a Bauvek | L26: Pagado | N26: Recibido en obra
B27: =+$E$3 -> Rodolfo Subias y Melisa Lew | C27: 46048 | D27: S/N | F27: 1 contenedor de obra | G27: Contenedores Fer | H27: Flete | I27: 145000 | K27: a Bauvek | L27: Pagado | N27: Recibido en obra
B28: =+$E$3 -> Rodolfo Subias y Melisa Lew | C28: 46050 | D28: S/N | F28: 1 contenedor de obra | G28: Contenedores Fer | H28: Flete | I28: 145000 | K28: a Bauvek | L28: Pagado | N28: Recibido en obra
A29: Pasado quincena | C29: 46051
B30: =+$E$3 -> Rodolfo Subias y Melisa Lew | C30: 46052 | D30: S/N | F30: 1 contenedor de obra | G30: Contenedores Fer | H30: Flete | I30: 145000 | K30: a Bauvek | L30: Pagado | N30: Recibido en obra
B31: =+$E$3 -> Rodolfo Subias y Melisa Lew | C31: 46056 | D31: S/N | F31: 1 contenedor de obra | G31: Contenedores Fer | H31: Flete | I31: 145000 | K31: a proveedor | M31: Pagado | N31: Recibido en obra
B32: =+$E$3 -> Rodolfo Subias y Melisa Lew | C32: 46063 | D32: S/N | F32: 1 contenedor de obra | G32: Contenedores Fer | H32: Flete | I32: 145000 | K32: a proveedor | M32: Pagado | N32: Recibido en obra
A33: Pasado quincena | C33: 46065
B34: =+$E$3 -> Rodolfo Subias y Melisa Lew | C34: 46071 | D34: S/N | F34: 1 contenedor de obra | G34: Contenedores Fer | H34: Flete | I34: 150000 | K34: a proveedor | M34: Pagado | N34: Recibido en obra
B35: =+$E$3 -> Rodolfo Subias y Melisa Lew | C35: 46071 | D35: S/N | F35: 7 m3 de arena gruesa | G35: Boccolini | H35: aridos | I35: 187500 | K35: a proveedor | M35: Pagado | N35: Recibido en obra
B36: =+$E$3 -> Rodolfo Subias y Melisa Lew | C36: 46073 | D36: S/N | F36: 1 contenedor de obra | G36: Contenedores Fer | H36: Flete | I36: 150000 | K36: a proveedor | M36: Pagado | N36: Recibido en obra
B37: =+$E$3 -> Rodolfo Subias y Melisa Lew | C37: 46083 | D37: S/N | F37: 1 contenedor de obra | G37: Contenedores Fer | H37: Flete | I37: 150000 | K37: a proveedor | M37: Pagado | N37: Recibido en obra
B38: =+$E$3 -> Rodolfo Subias y Melisa Lew | C38: 46078 | D38: Fact | E38: vintage sa | F38: pegamentos | G38: Contigini | H38: Mat. Obra gruesa | M38: Pagado | N38: Pendiente
B39: =+$E$3 -> Rodolfo Subias y Melisa Lew | C39: 46078 | D39: S/N | F39: Mat de agua | G39: Saniplats | H39: Mat. Plomeria | M39: Pagado | N39: Pendiente
B40: =+$E$3 -> Rodolfo Subias y Melisa Lew | C40: 46078 | E40: vintage sa | F40: Angulos borde pileta | G40: Cyplo | H40: Herreria | K40: a Bauvek | L40: Pagado | M40: Pagado | N40: Pendiente
A41: Pasado quincena | C41: 46079
B42: =+$E$3 -> Rodolfo Subias y Melisa Lew | C42: 46084 | D42: S/N | F42: 50% manos de obra y materiales | G42: Dimotec | H42: Mat. Bombas hidrau. | I42: 4773 | K42: a proveedor | M42: Pagado | N42: Recibido en obra
B43: =+$E$3 -> Rodolfo Subias y Melisa Lew | C43: 46092 | D43: S/N | F43: 1 contenedor de obra | G43: Contenedores Fer | H43: Flete | I43: 150000 | K43: a proveedor | M43: Pagado | N43: Recibido en obra
A44: Pasado quincena | C44: 46093
B45: =+$E$3 -> Rodolfo Subias y Melisa Lew | C45: 46106 | D45: S/N | F45: 1 contenedor de obra | G45: Contenedores Fer | H45: Flete | I45: 150000 | K45: a proveedor | M45: Pagado | N45: Recibido en obra
B46: =+$E$3 -> Rodolfo Subias y Melisa Lew | C46: 46106 | F46: 7 m3 de arena gruesa | G46: Boccolini | H46: Aridos | I46: 187500 | K46: a proveedor | M46: Pagado | N46: Recibido en obra
B47: =+$E$3 -> Rodolfo Subias y Melisa Lew | C47: 46106 | D47: Fact | E47: vintage sa | F47: pegamento flex, cemento, lad. Cemento | G47: Contigini | H47: Mat. Obra gruesa | I47: 2562580.5 | K47: a proveedor | M47: Pagado | N47: Pendiente
A48: Pasado quincena | C48: 46107
B49: =+$E$3 -> Rodolfo Subias y Melisa Lew | C49: 46127 | D49: S/N | F49: 1 contenedor de obra | G49: Contenedores Fer | H49: Flete | I49: 150000 | K49: a proveedor | M49: Pagado | N49: Recibido en obra
B50: =+$E$3 -> Rodolfo Subias y Melisa Lew | C50: 46136 | D50: S/N | F50: 1 contenedor de obra | G50: Contenedores Fer | H50: Flete | I50: 150000 | K50: a proveedor | M50: Pagado | N50: Recibido en obra
B51: =+$E$3 -> Rodolfo Subias y Melisa Lew | C51: 46135 | D51: S/N | F51: Traslado de adoquines del terron al malagueño corblock | G51: Flete Hugo Godoy | H51: Flete | I51: 100000 | K51: a proveedor | M51: Pagado | N51: Recibido en obra
A52: Pasado quincena | C52: 46135
B53: =+$E$3 -> Rodolfo Subias y Melisa Lew | C53: 46141 | D53: fact | E53: vintage sa | F53: 75 unid planchuela | G53: Acerco | H53: material | I53: 646502.49 | K53: a proveedor | M53: Pagado | N53: Recibido en obra
B54: =+$E$3 -> Rodolfo Subias y Melisa Lew | C54: 46142 | D54: fact | E54: vintage sa | F54: caño puertas tanque | G54: Acerco | H54: material | I54: 82550.44 | K54: a proveedor | M54: Pagado | N54: Recibido en obra
B55: =+$E$3 -> Rodolfo Subias y Melisa Lew | C55: 46147 | D55: fact | E55: Bauvek | F55: 4 cuerpos de andamios, 4 tablones metalicos, 8 ruedas fijas sin frenos | G55: Guaticor | H55: material | I55: 231120 | K55: a proveedor | M55: Pagado | N55: Recibido en obra
B56: =+$E$3 -> Rodolfo Subias y Melisa Lew | C56: 46148 | D56: S/N | F56: Traslado de Jack, acerco, a taller herrero y al terron | G56: Flete Hugo Godoy | H56: Flete | K56: a proveedor | M56: No Pagado | N56: Recibido en obra
B57: =+$E$3 -> Rodolfo Subias y Melisa Lew | C57: 46149 | D57: S/N | F57: Traslado de material del terron a Saniplast de la recta (devolucion de material) | G57: Flete Hugo Godoy | H57: Flete | K57: A bauvek | M57: No Pagado | N57: Recibido en obra
A58: Pasado quincena | B58: =+$E$3 -> Rodolfo Subias y Melisa Lew | C58: 46149
B59: =+$E$3 -> Rodolfo Subias y Melisa Lew | C59: 46160 | D59: S/N | G59: Flete Hugo Godoy | H59: Flete | I59: 62000 | K59: A bauvek | M59: No Pagado | N59: Recibido en obra
A60: Pasado quincena | B60: =+$E$3 -> Rodolfo Subias y Melisa Lew | C60: 46163
B61: =+$E$3 -> Rodolfo Subias y Melisa Lew
B62: =+$E$3 -> Rodolfo Subias y Melisa Lew | C62: 46230 | D62: S/N | F62: Traslado de macetas a obra | G62: Flete Hugo Godoy | H62: Flete | I62: 60000 | K62: a proveedor | M62: Pagado | N62: Recibido en obra
B63: =+$E$3 -> Rodolfo Subias y Melisa Lew | C63: 46230 | D63: S/N | F63: Traslado de jack a obra | G63: Flete Hugo Godoy | H63: Flete | I63: 60000 | K63: A bauvek | L63: No Pagado | M63: No Pagado | N63: Recibido en obra | O63: No Pagado
B64: =+$E$3 -> Rodolfo Subias y Melisa Lew | C64: 46231 | D64: S/N | F64: Traslado deandamios de Q2 a obra | G64: Flete Hugo Godoy | H64: Flete | I64: 60000 | K64: A bauvek | L64: No Pagado | M64: No Pagado | N64: Recibido en obra | O64: No Pagado
A65: Pasado quincena | B65: =+$E$3 -> Rodolfo Subias y Melisa Lew | C65: 46233
B66: =+$E$3 -> Rodolfo Subias y Melisa Lew | C66: 46244 | D66: S/N | F66: Andamios del terron a Q2 | G66: Flete Hugo Godoy | H66: Flete | I66: 65000 | K66: A bauvek | L66: No Pagado | M66: No Pagado | N66: Recibido en obra | O66: No Pagado
B67: =+$E$3 -> Rodolfo Subias y Melisa Lew
B68: =+$E$3 -> Rodolfo Subias y Melisa Lew
A69: Prox cierre | B69: =+$E$3 -> Rodolfo Subias y Melisa Lew | C69: 46247
B70: =+$E$3 -> Rodolfo Subias y Melisa Lew
B71: =+$E$3 -> Rodolfo Subias y Melisa Lew
B72: =+$E$3 -> Rodolfo Subias y Melisa Lew
A73: Prox cierre | B73: =+$E$3 -> Rodolfo Subias y Melisa Lew | C73: 46261
B74: =+$E$3 -> Rodolfo Subias y Melisa Lew
G76: TOTAL | H76: =SUM(I10:I74) -> 9368313.4

Sheet Obra RL
D2: GASTOS MATERIAL OBRA
D3: Cliente: | E3: RODRIGO LUGON
D4: Domicilio: | E4: Lote 426 | F4: Localidad: | H4: Estancia Q2
B9: OBRA | C9: Fecha de FC | D9: Condición | E9: Razón social | F9: Descripción | G9: Proveedor | H9: Rubro | I9: Importe final Pesos (Iva incluido) | J9: Importe final USD (Iva incluido) | K9: Observaciones | L9: Estado Factura Cliente | M9: Estado Factura Bauvek | N9: Estado material | O9: Resarcimiento Bauvek | P9: Nº Remito | Q9: Encargado
B10: =+$E$3 -> RODRIGO LUGON | C10: 46096 | D10: Fact-A | E10: Bauvek | G10: Guaticor | H10: Alquiler | I10: 250000 | K10: a Bauvek | L10: No Pagado | N10: Recibido en obra
B11: =+$E$3 -> RODRIGO LUGON | C11: 46107 | D11: Fact-A | E11: El gran Ombu | F11: 1 contenedor | G11: Conte Top | H11: Alquiler | I11: 150000 | K11: A proveedor | L11: No Pagado | N11: Recibido en obra
A12: Pasado quincena
B13: =+$E$3 -> RODRIGO LUGON | C13: 46127 | D13: Fact-A | E13: Bauvek | G13: Guaticor | H13: Alquiler | I13: 250000 | K13: a Bauvek | L13: No Pagado | N13: Recibido en obra
A14: Pasado quincena | C14: 46135
B15: =+$E$3 -> RODRIGO LUGON | C15: 46141 | D15: Fact-A | E15: Bauvek | G15: Guaticor | H15: Alquiler | I15: 105400 | K15: a Bauvek | L15: No Pagado | N15: Recibido en obra
A16: Pasado quincena | B16: =+$E$3 -> RODRIGO LUGON | C16: 46149
B17: =+$E$3 -> RODRIGO LUGON | C17: 46175 | D17: Fact-A | E17: Gran ombu | F17: 1 contenedor | G17: Conte Top | K17: A proveedor | L17: No Pagado | N17: Recibido en obra
B18: =+$E$3 -> RODRIGO LUGON | C18: 46182 | D18: Fact-A | E18: Gran ombu | F18: 1 contenedor | G18: Conte Top | K18: A proveedor | L18: No Pagado | N18: Recibido en obra
B19: =+$E$3 -> RODRIGO LUGON
B20: =+$E$3 -> RODRIGO LUGON
A21: Pasado quincena | B21: =+$E$3 -> RODRIGO LUGON | C21: 46191
B22: =+$E$3 -> RODRIGO LUGON | C22: 46196 | D22: s/n | F22: Andamios de obra a guaticor | G22: Flete Hugo Godoy | H22: flete | I22: 75000 | K22: A proveedor | L22: No Pagado | N22: Recibido en obra
B23: =+$E$3 -> RODRIGO LUGON | C23: 46197 | D23: s/n | F23: Andamios de obra a guaticor | G23: Flete Hugo Godoy | H23: flete | I23: 75000 | K23: A proveedor | L23: No Pagado | N23: Recibido en obra
B24: =+$E$3 -> RODRIGO LUGON
B25: =+$E$3 -> RODRIGO LUGON
A26: Pasado quincena | B26: =+$E$3 -> RODRIGO LUGON | C26: 46205
B27: =+$E$3 -> RODRIGO LUGON | C27: 46244 | D27: S/N | E27: Bauvek | F27: Desplazamiento de andamios del terron a Q2 | G27: Flete Hugo Godoy | H27: flete | I27: 65000 | K27: A proveedor | L27: No Pagado | N27: Recibido en obra
A28: Pasado quincena | B28: =+$E$3 -> RODRIGO LUGON | C28: 46261
B29: =+$E$3 -> RODRIGO LUGON
B30: =+$E$3 -> RODRIGO LUGON
B31: =+$E$3 -> RODRIGO LUGON
B32: =+$E$3 -> RODRIGO LUGON
B33: =+$E$3 -> RODRIGO LUGON
A34: Prox cierre | B34: =+$E$3 -> RODRIGO LUGON | C34: 46275
B35: =+$E$3 -> RODRIGO LUGON
B36: =+$E$3 -> RODRIGO LUGON
B37: =+$E$3 -> RODRIGO LUGON
B38: =+$E$3 -> RODRIGO LUGON
B39: =+$E$3 -> RODRIGO LUGON
B40: =+$E$3 -> RODRIGO LUGON
B41: =+$E$3 -> RODRIGO LUGON
B42: =+$E$3 -> RODRIGO LUGON
B43: =+$E$3 -> RODRIGO LUGON
B44: =+$E$3 -> RODRIGO LUGON
B45: =+$E$3 -> RODRIGO LUGON
B46: =+$E$3 -> RODRIGO LUGON
... B49: =+$E$3 -> RODRIGO LUGON
G51: TOTAL | H51: =SUM(I10:I49) -> 970400

Sheet Obra Bauvek(NE)
D2: GASTOS MATERIAL OBRA
D3: Cliente: | E3: NE | F3: Gastos Bauvek
D4: Domicilio: | F4: Localidad:
B9: OBRA | C9: Fecha de FC | D9: Condición | E9: Razón social | F9: Descripción | G9: Proveedor | H9: Rubro | I9: Importe final Pesos (Iva incluido) | J9: Importe final USD (Iva incluido) | K9: Observaciones | L9: Estado Factura Cliente | M9: Estado Factura Bauvek | N9: Estado material | O9: Resarcimiento Bauvek | P9: Nº Remito | Q9: Encargado | R9: Columna1
B10: =+$E$3 -> NE | C10: 45993 | D10: S/N | E10: - | F10: Retiro/traslado de tierra a chacras la villa | G10: Flete Hugo Godoy | H10: Flete | I10: 50000 | K10: a Bauvek | L10: Pagado | N10: Recibido en obra
A11: Pasado quincena
B12: =+$E$3 -> NE | C12: 46017 | D12: S/N | E12: - | F12: Retiro/traslado de sillas Lucho a chacras la villa | G12: Flete Hugo Godoy | H12: Flete | I12: 80000 | K12: a Bauvek | L12: Pagado | N12: Recibido en obra
A13: Pasado quincena | C13: 46022
A14: Pasado quincena | C14: 46037
B15: =+$E$3 -> NE | C15: 46043 | D15: FACT A28027 | E15: Bauvek | F15: Material madera | G15: Mendio SA | H15: materiales | I15: 101642.26 | K15: A Bauvek | L15: Pagado | R15: Echeq a 30 días, ver cuando se emite
A16: Pasado quincena | C16: 46051
A17: Pasado quincena | C17: 46065
B18: =+$E$3 -> NE
A19: Pasado quincena | C19: 46079
B20: =+$E$3 -> NE | C20: 46079 | D20: S/N | E20: - | F20: Perfiles y tornillos | G20: Jack SRL | H20: Materiales | I20: 116099.45 | K20: A Bauvek | L20: Pagado | N20: Recibido en obra
A21: Pasado quincena | C21: 46093
A22: Pasado quincena | C22: 46107
A23: Pasado quincena | C23: 46121
B24: =+$E$3 -> NE
A25: Pasado quincena | C25: 46135
B26: =+$E$3 -> NE | C26: 46136 | D26: S/N | F26: ROLLO FILM NEGRO 3 X 50 MTS 200 MIC | G26: Jack SRL | I26: 73239.49 | K26: A Bauvek | L26: No Pagado | M26: No Pagado | N26: Recibido en obra | O26: Cuenta Corriente | R26: Para obra Emilio contigiani
B27: =+$E$3 -> NE | C27: 46142 | D27: S/N | F27: 6 soleras | G27: Jack SRL | I27: 17011.05 | K27: A Bauvek | L27: No Pagado | M27: No Pagado | N27: Recibido en obra | O27: Cuenta Corriente | R27: casa Nico
B28: =+$E$3 -> NE | C28: 46140 | D28: Fact A69918 | E28: Bauvek | F28: Mat electricidad | G28: Feyro | I28: 89000.01 | K28: A Bauvek | L28: No Pagado | M28: No Pagado | N28: Recibido en obra | O28: Cuenta Corriente | R28: Casa Nico
A29: Pasado quincena | B29: =+$E$3 -> NE | C29: 46149
B30: =+$E$3 -> NE | C30: 46154 | D30: Fact A69918 | E30: Bauvek | F30: Mat electricidad para casa de las sierras | G30: Feyro | I30: 116243.41 | K30: A Bauvek | L30: No Pagado | M30: No Pagado | N30: Recibido en obra | O30: Cuenta Corriente | R30: Casa Rio Cuarto
B31: =+$E$3 -> NE
A32: Pasado quincena | B32: =+$E$3 -> NE | C32: 46163
A33: Pasado quincena | B33: =+$E$3 -> NE | C33: 46177
B34: =+$E$3 -> NE | C34: 46113 | D34: Fact A10398 | E34: Bauvek | F34: Tersitech y venda | G34: Garin | I34: 153703.26 | K34: A Bauvek | L34: No Pagado | M34: No Pagado | N34: Recibido en obra | O34: Cuenta Corriente
B35: =+$E$3 -> NE | C35: 46125 | D35: Fact A10461 | E35: Bauvek | G35: Garin | I35: 11721.4 | K35: A Bauvek | L35: No Pagado | M35: No Pagado | N35: Recibido en obra | O35: Cuenta Corriente
B36: =+$E$3 -> NE | C36: 46168 | D36: S/N | F36: 1 contenedor casa Nico | G36: Conte Top | I36: 145000 | K36: A Bauvek | L36: No Pagado | M36: No Pagado | N36: Recibido en obra | O36: Cuenta Corriente
B37: =+$E$3 -> NE
A38: Pasado quincena | B38: =+$E$3 -> NE | C38: 46191
B39: =+$E$3 -> NE | C39: 46227 | D39: Fact A11044 | E39: Bauvek | F39: Tersinol, venda, latex profesional - obra LOCAL | G39: Garin | I39: 293515.55 | K39: A Bauvek | L39: No Pagado | M39: No Pagado | N39: Recibido en obra | O39: Cuenta Corriente
B40: =+$E$3 -> NE | C40: 46227 | D40: Fact A11045 | E40: Bauvek | F40: Yeso, esmalte sintetico blanco - obra LOCAL | G40: Garin | I40: 17275.27 | K40: A Bauvek | L40: No Pagado | M40: No Pagado | N40: Recibido en obra | O40: Cuenta Corriente
B41: =+$E$3 -> NE | C41: 46231 | D41: Fact A11069 | E41: Bauvek | F41: Latex profesional int - obra LOCAL | G41: Garin | I41: 106279.61 | K41: A Bauvek | L41: No Pagado | M41: No Pagado | N41: Recibido en obra | O41: Cuenta Corriente
B42: =+$E$3 -> NE | C42: 46216 | D42: S/N | F42: 1 contenedor casa Nico | G42: Conte Top | I42: 145000 | K42: A Bauvek | L42: No Pagado | M42: No Pagado | N42: Recibido en obra | O42: Cuenta Corriente
A43: Pasado quincena | B43: =+$E$3 -> NE | C43: 46232
B44: =+$E$3 -> NE
B45: =+$E$3 -> NE
A46: Pasado quincena | B46: =+$E$3 -> NE | C46: 46247
B47: =+$E$3 -> NE | C47: 46258 | D47: S/N | E47: Bauvek | F47: 4m3 de tierra de relleno | G47: Nicolas Carusso | I47: 180000 | K47: a Bauvek | L47: No Pagado | M47: No Pagado | N47: Recibido en obra | O47: Cuenta Corriente
B48: =+$E$3 -> NE
A49: Pasado quincena | B49: =+$E$3 -> NE | C49: 46261
B50: =+$E$3 -> NE
B51: =+$E$3 -> NE
B52: =+$E$3 -> NE
B53: =+$E$3 -> NE
A54: Prox cierre | B54: =+$E$3 -> NE | C54: 46275
B55: =+$E$3 -> NE
B56: =+$E$3 -> NE
B57: =+$E$3 -> NE
H59: TOTAL | I59: =SUM(I10:I57) -> 1695730.8

Sheet Obra AV
D2: GASTOS MATERIAL OBRA
D3: Cliente: | E3: Alma Viva
D4: Domicilio: | E4: Lote 9 - mza H | F4: Localidad: | H4: Estancia San Miguel
E5: Río ceballos
B9: OBRA | C9: Fecha de FC | D9: Condición | E9: Razón social | F9: Descripción | G9: Proveedor | H9: Rubro | I9: Importe final Pesos (Iva incluido) | J9: Importe final USD (Iva incluido) | K9: Observaciones | L9: Estado Factura Cliente | M9: Estado Factura Bauvek | N9: Estado material | O9: Resarcimiento Bauvek | P9: Nº Remito | Q9: Encargado
B10: =+$E$3 -> Alma Viva | C10: 45975 | D10: S/N | E10: - | F10: Retiro/traslado de material de Enas a obra Río ceballos, alma vida - turno mañana | G10: Flete Hugo Godoy | H10: Flete | I10: 100000 | L10: Pagado | N10: Recibido en obra
B11: =+$E$3 -> Alma Viva | C11: 45975 | D11: S/N | E11: - | F11: Retiro/traslado de material de Enas a obra Río ceballos, alma vida - turno Tarde | G11: Flete Hugo Godoy | H11: Flete | I11: 100000 | L11: Pagado | N11: Recibido en obra
B12: =+$E$3 -> Alma Viva | C12: 45986 | D12: S/N | E12: - | F12: Retiro/traslado de material de SINIS de obra Río Ceballos a Sinis | G12: Flete Jonatan | H12: Flete | I12: 240000 | K12: Realizado | L12: Pagado | N12: Recibido en obra
B13: =+$E$3 -> Alma Viva | C13: 45988 | D13: S/N | E13: - | F13: Retiro/traslado de material de SINIS de obra Río Ceballos a Sinis | G13: Flete Jonatan | H13: Flete | I13: 240000 | K13: Realizado | L13: Pagado | N13: Recibido en obra
B14: =+$E$3 -> Alma Viva | C14: 45989 | D14: S/N | E14: - | F14: Retiro/traslado de material de SINIS de obra Río Ceballos a Sinis | G14: Flete Jonatan | H14: Flete | I14: 240000 | K14: Realizado | L14: Pagado | N14: Recibido en obra
A15: Pasado quincena | C15: 45989
B16: =+$E$3 -> Alma Viva | C16: 45982 | D16: S/N | E16: - | F16: Retiro/traslado de material de Enas a obra Río ceballos, alma vida - turno mañana | G16: Flete Hugo Godoy | H16: Flete | I16: 100000 | K16: Realizado | L16: Pagado | N16: Recibido en obra
B17: =+$E$3 -> Alma Viva | C17: 45982 | D17: S/N | E17: - | F17: Retiro/traslado de material de Enas a obra Río ceballos, alma vida - turno Tarde | G17: Flete Hugo Godoy | H17: Flete | I17: 100000 | K17: Realizado | L17: Pagado | N17: Recibido en obra
B18: =+$E$3 -> Alma Viva | C18: 45993 | D18: S/N | E18: - | F18: Retiro/traslado de material de SINIS de obra Río Ceballos a Sinis | G18: Flete Jonatan | H18: Flete | I18: 240000 | K18: Realizado | L18: Pagado | N18: Recibido en obra
B19: =+$E$3 -> Alma Viva | C19: 45994 | D19: S/N | E19: - | F19: Retiro/traslado de material de SINIS de obra Río Ceballos a Sinis | G19: Flete Jonatan | H19: Flete | I19: 240000 | K19: Realizado | L19: Pagado | N19: Recibido en obra
B20: =+$E$3 -> Alma Viva | C20: 46000 | D20: S/N | E20: - | F20: Retiro/traslado de material de ENAS de obra Río Ceballos a ENAS centro | G20: Flete Jonatan | H20: Flete | I20: 240000 | K20: Realizado | L20: Pagado | N20: Recibido en obra
A21: Pasado quincena | C21: 45996
B22: =+$E$3 -> Alma Viva | C22: 46010 | D22: S/N | E22: - | F22: 20 puntales acrow E-3L | G22: Flete Hugo Godoy | H22: Flete | I22: 110000 | K22: Realizado | L22: Pagado | N22: Recibido en obra
A23: Pasado quincena | C23: 46009
A24: Pasado quincena | C24: 46022
B25: =+$E$3 -> Alma Viva | C25: 46035 | D25: Fact-A | E25: Bauvek SAS | F25: Alquiler de 1 vibro bosh se uso en el hormigon del 22/12/2025 | G25: Alquilo Todo | H25: Alquiler | I25: 50000 | K25: A bauvek | L25: Pagado | N25: Recibido en obra
A26: Pasado quincena | C26: 46037
B27: =+$E$3 -> Alma Viva | C27: 46050 | D27: Fact-A | E27: Bauvek SAS | F27: Devolucion material de Enas | G27: Flete de ENAS | H27: Flete | I27: =145200*1.21 -> 175692 | K27: A bauvek | L27: Pagado | M27: Pagado
B28: =+$E$3 -> Alma Viva | C28: 46051 | D28: Fact-A | E28: Bauvek SAS | F28: Devolucion material de Enas | G28: Flete de ENAS | H28: Flete | I28: =145200*1.21 -> 175692 | K28: A bauvek | L28: Pagado | M28: Pagado
A29: Pasado quincena | C29: 46051
A30: Pasado quincena | C30: 46065
B31: =+$E$3 -> Alma Viva
A32: Pasado quincena | C32: 46079
B33: =+$E$3 -> Alma Viva | C33: 46083 | D33: S/N | E33: - | F33: Devolución de material de ENAS de obra Río Ceballos a ENAS centro | G33: Flete Jonatan | H33: Flete | I33: 220000 | K33: A proveedor | L33: Pagado | N33: Recibido en obra | T33: ver que pague blussand por transferencia
B34: =+$E$3 -> Alma Viva | C34: 46080 | D34: Fact-A-6106 | E34: Bauvek SAS | F34: Alquiler material contra 6483A5 | G34: Enas | H34: Alquiler material | I34: 389323.55 | K34: A bauvek | L34: Pagado | M34: Pagado | N34: Recibido en obra
B35: =+$E$3 -> Alma Viva | C35: 46080 | D35: Fact-A-6110 | E35: Bauvek SAS | F35: Alquiler material contra 6483A4 | G35: Enas | H35: Alquiler material | I35: 44704.66 | K35: A bauvek | L35: Pagado | M35: Pagado | N35: Recibido en obra
B36: =+$E$3 -> Alma Viva | C36: 46080 | D36: Fact-A-6155 | E36: Bauvek SAS | F36: Alquiler material contra 6483A2 | G36: Enas | H36: Alquiler material | I36: 230045.12 | K36: A bauvek | L36: Pagado | M36: Pagado | N36: Recibido en obra
B37: =+$E$3 -> Alma Viva | C37: 46080 | D37: Fact-A-6156 | E37: Bauvek SAS | F37: Alquiler material contra 6483A2 | G37: Enas | H37: Alquiler material | I37: 2361540.1 | K37: A bauvek | L37: Pagado | M37: Pagado | N37: Recibido en obra
B38: =+$E$3 -> Alma Viva | C38: 46080 | D38: Fact-A-6157 | E38: Bauvek SAS | F38: Alquiler material contra 6483A2 | G38: Enas | H38: Alquiler material | I38: 395163.41 | K38: A bauvek | L38: Pagado | M38: Pagado | N38: Recibido en obra
B39: =+$E$3 -> Alma Viva | C39: 46080 | D39: Fact-A-6206 | E39: Bauvek SAS | F39: Alquiler material contra 6483 | G39: Enas | H39: Alquiler material | I39: 435600 | K39: A bauvek | L39: Pagado | M39: Pagado | N39: Recibido en obra
B40: =+$E$3 -> Alma Viva | C40: 46080 | D40: Fact-A-6237 | E40: Bauvek SAS | F40: Alquiler material contra 6483A6 | G40: Enas | H40: Alquiler material | I40: 10001.96 | K40: A bauvek | L40: Pagado | M40: Pagado | N40: Recibido en obra
B41: =+$E$3 -> Alma Viva | C41: 46080 | D41: Fact-A-6238 | E41: Bauvek SAS | F41: Alquiler material contra 6483A4 | G41: Enas | H41: Alquiler material | I41: 241727.75 | K41: A bauvek | L41: Pagado | M41: Pagado | N41: Recibido en obra
B42: =+$E$3 -> Alma Viva | C42: 46080 | D42: Fact-A-6244 | E42: Bauvek SAS | F42: Alquiler material contra 6483A5 | G42: Enas | H42: Alquiler material | I42: 228291.55 | K42: A bauvek | L42: Pagado | M42: Pagado | N42: Recibido en obra
B43: =+$E$3 -> Alma Viva | C43: 46080 | D43: Fact-A-6281 | E43: Bauvek SAS | F43: Alquiler material contra 6483A6 | G43: Enas | H43: Alquiler material | I43: 10212 | K43: A bauvek | L43: Pagado | M43: Pagado | N43: Recibido en obra
B44: =+$E$3 -> Alma Viva | C44: 46086 | D44: S/N | E44: - | F44: Material roto | G44: Enas | H44: material roto | I44: 3000000 | K44: A bauvek | L44: Pagado | M44: Pagado | N44: Recibido en obra | T44: Se paga en dos veces
A45: Pasado quincena | C45: 46093
A46: Pasado quincena | C46: 46107
A47: Prox cierre | B47: =+$E$3 -> Alma Viva | C47: 46149
A48: Prox cierre | B48: =+$E$3 -> Alma Viva | C48: 46163
B49: =+$E$3 -> Alma Viva
B50: =+$E$3 -> Alma Viva
B51: =+$E$3 -> Alma Viva
B52: =+$E$3 -> Alma Viva
B53: =+$E$3 -> Alma Viva
B54: =+$E$3 -> Alma Viva
B55: =+$E$3 -> Alma Viva
H57: TOTAL | I57: =SUM(I10:I55) -> 9917994.1

Sheet Obra LH
D2: GASTOS MATERIAL OBRA
D3: Cliente: | E3: LOSA HERRERA
D4: Domicilio: | E4: Lote 346 | F4: Localidad: | H4: El Terrón
B9: OBRA | C9: Fecha de FC | D9: Condición | E9: Razón social | F9: Descripción | G9: Proveedor | H9: Rubro | I9: Importe final Pesos (Iva incluido) | J9: Importe final USD (Iva incluido) | K9: Observaciones | L9: Estado Factura Cliente | M9: Estado Factura Bauvek | N9: Estado material | O9: Resarcimiento Bauvek | P9: Nº Remito | Q9: Encargado
B10: =+$E$3 -> LOSA HERRERA | C10: 46035 | D10: Fact-A | E10: Bauvek SAS | F10: Alquiler de 1 vibro bosh se uso en el hormigon del 17/12/2025 | G10: Alquilo Todo | H10: Alquiler | I10: 50000 | K10: A bauvek | L10: Pagado | N10: Recibido en obra
A11: Pasado quincena | D11: 46037
B12: =+$E$3 -> LOSA HERRERA | C12: 46038 | D12: S/N | E12: contrato 6551 | F12: Devolucion material de Enas | G12: Flete Jonatan | H12: Flete | I12: 200000 | K12: A bauvek | L12: Pagado | N12: Recibido en obra | P12: 3220
B13: =+$E$3 -> LOSA HERRERA | C13: 46043 | D13: S/N | E13: contrato 6551 | F13: Devolucion Material de Enas | G13: Flete Jonatan | H13: Flete | I13: 200000 | K13: A bauvek | L13: Pagado | N13: Recibido en obra | P13: 3229
B14: =+$E$3 -> LOSA HERRERA | C14: 46048 | D14: S/N | E14: contrato 6551 | F14: Devolucion Material de Enas | G14: Flete Jonatan | H14: Flete | I14: 200000 | K14: A bauvek | L14: Pagado | N14: Recibido en obra
A15: Pasado quincena | C15: 46051
A16: Pasado quincena | C16: 46065
A17: Pasado quincena | C17: 46079
B18: =+$E$3 -> LOSA HERRERA | D18: Fact-A - 505422 | E18: Bauvek | F18: Caución | G18: afianciadora de compañía de seguros | H18: Aseguradora | I18: 82.65 | L18: No Pagado | M18: No Pagado
B19: =+$E$3 -> LOSA HERRERA | C19: 46078 | D19: Fact-A -527930 | E19: Bauvek | F19: Caución | G19: afianciadora de compañía de seguros | H19: Aseguradora | I19: 81.17 | K19: Factura restado por nota de credito | L19: Pagado
B20: =+$E$3 -> LOSA HERRERA | C20: 46078 | D20: NT-Cred.104773 | E20: Bauvek | F20: Caución | G20: afianciadora de compañía de seguros | H20: Aseguradora | I20: -81.17 | K20: Nota de credito corresponde a FactA-527930 | L20: Pagado
B21: =+$E$3 -> LOSA HERRERA | D21: Bauvek | E21: contrato 6551 | F21: Devolucion Material de Enas | G21: Flete de ENAS | H21: Flete | I21: 145200 | K21: A bauvek | L21: Pagado | N21: Recibido en obra
B22: =+$E$3 -> LOSA HERRERA | D22: Bauvek | E22: contrato 6551 | F22: Devolucion Material de Enas | G22: Flete de ENAS | H22: Flete | I22: 145200 | K22: A bauvek | L22: Pagado | N22: Recibido en obra
B23: =+$E$3 -> LOSA HERRERA | D23: Bauvek | E23: contrato 6551 | F23: Material roto contrato A0/A1/A2 | G23: Enas | H23: Material alquile | I23: 2218438.2 | K23: A bauvek | L23: Pagado | N23: Recibido en obra
A24: Pasado quincena | B24: =+$E$3 -> LOSA HERRERA | C24: 46093
A25: Prox cierre | B25: =+$E$3 -> LOSA HERRERA | C25: 46107
A26: Prox cierre | B26: =+$E$3 -> LOSA HERRERA | C26: 46121
A27: Prox cierre | B27: =+$E$3 -> LOSA HERRERA | C27: 46149
A28: Prox cierre | B28: =+$E$3 -> LOSA HERRERA | C28: 46163
B29: =+$E$3 -> LOSA HERRERA
B30: =+$E$3 -> LOSA HERRERA
B31: =+$E$3 -> LOSA HERRERA
B32: =+$E$3 -> LOSA HERRERA
B33: =+$E$3 -> LOSA HERRERA
B34: =+$E$3 -> LOSA HERRERA
B35: =+$E$3 -> LOSA HERRERA
B36: =+$E$3 -> LOSA HERRERA
B37: =+$E$3 -> LOSA HERRERA
B38: =+$E$3 -> LOSA HERRERA
B39: =+$E$3 -> LOSA HERRERA
B40: =+$E$3 -> LOSA HERRERA
... B50: =+$E$3 -> LOSA HERRERA
G52: TOTAL | H52: =SUM(I10:I50) -> 3158920.9

Sheet Obra colegio
D2: GASTOS MATERIAL OBRA
D3: Cliente: | E3: Colegio Malageño
D4: Domicilio: | E4: Peaje VCP | F4: Localidad: | H4: Malagueño
B9: OBRA | C9: Fecha de FC | D9: Condición | E9: Razón social | F9: Descripción | G9: Proveedor | H9: Rubro | I9: Importe final Pesos (Iva incluido) | J9: Importe final USD (Iva incluido) | K9: Observaciones | L9: Estado Factura Cliente | M9: Estado Factura Bauvek | N9: Estado material | O9: Resarcimiento Bauvek | P9: Nº Remito | Q9: Encargado
B10: =+$E$3 -> Colegio Malageño | C10: 46042 | D10: S/N | F10: Retiro de anadamio Guaticor a peaje VCP- colegio Malagueño | G10: Flete Hugo Godoy | H10: Flete | I10: 58000 | K10: a Bauvek | L10: Pagado | N10: Recibido en obra
B11: =+$E$3 -> Colegio Malageño | C11: 46042 | F11: 1 cuerpo y medio de andamios. 1 cuerpo de barandas y 1 tablon | G11: Guaticor | H11: Alquiler | I11: 60400 | K11: a Bauvek | L11: Pagado | N11: Recibido en obra
A12: Pasado quincena | C12: 46051
A13: Pasado quincena | C13: 46065
B14: =+$E$3 -> Colegio Malageño | C14: 46073 | F14: 1 cuerpo y medio de andamios. 1 cuerpo de barandas y 1 tablon | G14: Guaticor | H14: Alquiler | I14: 60400 | K14: a Bauvek | L14: Pagado | N14: Recibido en obra
B15: =+$E$3 -> Colegio Malageño | C15: 46079 | D15: S/N | F15: Traslado de andamios a obra en Arguello | G15: Flete Hugo Godoy | H15: Flete | I15: 52000 | K15: a Bauvek | L15: Pagado | M15: No Pagado | N15: Recibido en obra
A16: Pasado quincena | C16: 46079
A17: Pasado quincena | C17: 46093
B18: =+$E$3 -> Colegio Malageño | D18: S/N | E18: Sin factura | F18: devolucion de andamios a Guaticor | G18: Flete Hugo Godoy | H18: Fletes | I18: 40000 | K18: A bauvek | L18: Pagado | N18: Recibido en obra
B19: =+$E$3 -> Colegio Malageño
B20: =+$E$3 -> Colegio Malageño
A21: Prox cierre | C21: 46107
A22: Prox cierre | B22: =+$E$3 -> Colegio Malageño | C22: 46149
A23: Prox cierre | B23: =+$E$3 -> Colegio Malageño | C23: 46163
B24: =+$E$3 -> Colegio Malageño
B25: =+$E$3 -> Colegio Malageño
B26: =+$E$3 -> Colegio Malageño
B27: =+$E$3 -> Colegio Malageño
B28: =+$E$3 -> Colegio Malageño
B29: =+$E$3 -> Colegio Malageño
B30: =+$E$3 -> Colegio Malageño
B31: =+$E$3 -> Colegio Malageño
B32: =+$E$3 -> Colegio Malageño
B33: =+$E$3 -> Colegio Malageño
B34: =+$E$3 -> Colegio Malageño
B35: =+$E$3 -> Colegio Malageño
... B41: =+$E$3 -> Colegio Malageño
G43: TOTAL | H43: =SUM(I10:I41) -> 270800

Sheet Casa sietes soles
D2: GASTOS MATERIAL OBRA
D3: Cliente: | E3: Casa siete soles
D4: Domicilio: | E4: Sieste soles | F4: Localidad: | H4: Malagueño
B9: OBRA | C9: Fecha de FC | D9: Condición | E9: Razón social | F9: Descripción | G9: Proveedor | H9: Rubro | I9: Importe final Pesos (Iva incluido) | J9: Importe final USD (Iva incluido) | K9: Observaciones | L9: Estado Factura Cliente | M9: Estado Factura Bauvek | N9: Estado material | O9: Resarcimiento Bauvek | P9: Nº Remito | Q9: Encargado
B10: =+$E$3 -> Casa siete soles | C10: 46036 | D10: S/N | F10: Retiro de andamios alquilo todo a 7 soles | G10: Flete Hugo Godoy | H10: Flete | I10: 60000 | K10: a Bauvek | L10: Pagado | N10: Recibido en obra
B11: =+$E$3 -> Casa siete soles | C11: 46036 | D11: S/N | F11: 1 cuerpo de andamios y 1 tablon | G11: alquiloTodo | H11: Alquiler | I11: 0 | K11: a Bauvek | L11: Pagado | N11: Recibido en obra
A12: Pasado quincena | C12: 46051
A13: Pasado quincena | C13: 46065
B14: =+$E$3 -> Casa siete soles | C14: 46074 | D14: S/N | F14: 1 cuerpo de andamios y 1 tablon | G14: alquiloTodo | H14: Alquiler | I14: 0 | K14: a Bauvek | L14: Pagado | N14: Recibido en obra
A15: Pasado quincena | C15: 46079
A16: Pasado quincena | C16: 46093
A17: Pasado quincena | C17: 46107
B18: =+$E$3 -> Casa siete soles | C18: 46113 | D18: S/N | F18: Retiro de acerco material a obra | G18: Flete Hugo Godoy | H18: Flete | I18: 47000 | K18: a Bauvek | L18: Pagado | N18: Recibido en obra
A19: Pasado quincena | C19: 46121
A21: Pasado quincena | B21: =+$E$3 -> Casa siete soles
B22: =+$E$3 -> Casa siete soles | C22: 46140 | D22: Fact | E22: Bauvek | F22: 4 cuerpos de andamio y 2 tablones | G22: Guaticor | I22: 120800 | L22: Pagado | N22: Recibido en obra | Q22: Julian
A23: Pasado quincena | B23: =+$E$3 -> Casa siete soles | C23: 46149
B24: =+$E$3 -> Casa siete soles
A25: Pasado quincena | B25: =+$E$3 -> Casa siete soles | C25: 46163
B26: =+$E$3 -> Casa siete soles
B27: =+$E$3 -> Casa siete soles
A28: Pasado quincena | B28: =+$E$3 -> Casa siete soles | C28: 46177
B29: =+$E$3 -> Casa siete soles | D29: Fact | E29: Bauvek | F29: 4 cuerpos de andamio y 2 tablones RENOVACIÓN | G29: Guaticor | L29: No Pagado | N29: Recibido en obra | Q29: Julian
B30: =+$E$3 -> Casa siete soles
A31: Prox cierre | B31: =+$E$3 -> Casa siete soles | C31: 46191
B32: =+$E$3 -> Casa siete soles
B33: =+$E$3 -> Casa siete soles
B34: =+$E$3 -> Casa siete soles
B35: =+$E$3 -> Casa siete soles
B36: =+$E$3 -> Casa siete soles
B37: =+$E$3 -> Casa siete soles
B38: =+$E$3 -> Casa siete soles
B39: =+$E$3 -> Casa siete soles
G41: TOTAL | H41: =SUM(I10:I39) -> 227800

Sheet Proyecto AZ
D2: GASTOS MATERIAL OBRA
D3: Cliente: | E3: Agustin Zampol
D4: Domicilio: | E4: Mza 7 - lote 4 | F4: Localidad: | H4: Vistas de La Deseada
B9: OBRA | C9: Fecha de FC | D9: Condición | E9: Razón social | F9: Descripción | G9: Proveedor | H9: Rubro | I9: Importe final Pesos (Iva incluido) | J9: Importe final USD (Iva incluido) | K9: Observaciones | L9: Estado Factura Cliente | M9: Estado Factura Bauvek | N9: Estado material | O9: Resarcimiento Bauvek | P9: Nº Remito | Q9: Encargado
B10: =+$E$3 -> Agustin Zampol | C10: 46064 | E10: Tatagua SA | F10: Estudio de suelo, altimetria, vegetación y vegetación autoctona | G10: Geotecnia | I10: 1936000 | L10: Pagado | N10: Recibido en obra
B11: =+$E$3 -> Agustin Zampol | C11: 46064 | F11: Amojonamiento - ver cantidad de puntos | G11: Agrimensor | I11: 320000 | L11: Pagado | N11: Recibido en obra
B12: =+$E$3 -> Agustin Zampol | C12: 46064 | F12: Amojonamiento -colegiado | G12: Agrimensor | I12: 89000 | L12: Pagado | N12: Recibido en obra
A13: Pasado quincena | C13: 46065
A14: Pasado quincena | C14: 46079
A15: Pasado quincena | C15: 46093
A16: Pasado quincena | C16: 46107
A17: Pasado quincena | B17: =+$E$3 -> Agustin Zampol | C17: 46149
A18: Pasado quincena | B18: =+$E$3 -> Agustin Zampol | C18: 46163
A19: Pasado quincena | B19: =+$E$3 -> Agustin Zampol | C19: 46177
B20: =+$E$3 -> Agustin Zampol
B21: =+$E$3 -> Agustin Zampol
B22: =+$E$3 -> Agustin Zampol
A23: Prox cierre | B23: =+$E$3 -> Agustin Zampol | C23: 46191
B24: =+$E$3 -> Agustin Zampol
B25: =+$E$3 -> Agustin Zampol
B26: =+$E$3 -> Agustin Zampol
B27: =+$E$3 -> Agustin Zampol
B28: =+$E$3 -> Agustin Zampol
B29: =+$E$3 -> Agustin Zampol
B30: =+$E$3 -> Agustin Zampol
B31: =+$E$3 -> Agustin Zampol
B32: =+$E$3 -> Agustin Zampol
B33: =+$E$3 -> Agustin Zampol
B34: =+$E$3 -> Agustin Zampol
B35: =+$E$3 -> Agustin Zampol
B36: =+$E$3 -> Agustin Zampol
G38: TOTAL | H38: =SUM(I10:I36) -> 2345000

Sheet Obra Mogetta
D2: GASTOS MATERIAL OBRA
D3: Cliente: | E3: Losa Mogetta
D4: Domicilio: | E4: Villa allende | F4: Localidad: | H4: La Calera
B9: OBRA | C9: Fecha de FC | D9: Condición | E9: Razón social | F9: Descripción | G9: Proveedor | H9: Rubro | I9: Importe final Pesos (Iva incluido) | J9: Importe final USD (Iva incluido) | K9: Observaciones | L9: Estado Factura Cliente | M9: Estado Factura Bauvek | N9: Estado material | O9: Resarcimiento Bauvek | P9: Nº Remito | Q9: Encargado
B10: =+$E$3 -> Losa Mogetta | E10: Bauvek | F10: Caución | G10: afianciadora de compañía de seguros | H10: Aseguradora | J10: 74 | L10: Pagado
B11: =+$E$3 -> Losa Mogetta | C11: 46063 | D11: Fact-A | E11: Bauvek | F11: Alquiler encofrado losa vista | G11: Sinis | H11: Alquilar encofrado | J11: 1497.06 | K11: Costo mensual | L11: Pagado | R11: Factura por mes 28 días
B12: =+$E$3 -> Losa Mogetta | C12: 46063 | D12: Fact-A | E12: Bauvek | F12: Alquiler encofrado losa NO vista | G12: Sinis | H12: Alquilar encofrado | J12: 1839.3 | K12: Costo mensual | L12: Pagado | R12: Factura por mes 28 días
B13: =+$E$3 -> Losa Mogetta | C13: 46072 | D13: Fact-A | E13: Bauvek | F13: Alquiler encofrado losa NO vista | G13: Sinis | H13: Alquilar encofrado | J13: 332.02 | K13: Costo mensual | L13: Pagado | R13: Factura por mes 28 días
B14: =+$E$3 -> Losa Mogetta | C14: 46072 | D14: Nota de credito | E14: Bauvek | F14: Alquiler encofrado losa NO vista | G14: Sinis | H14: Alquilar encofrado | J14: -474.32 | K14: Costo mensual | L14: Pagado | R14: Factura por mes 28 días
B15: =+$E$3 -> Losa Mogetta | C15: 46072 | D15: Nota de credito | E15: Bauvek | F15: Alquiler encofrado losa NO vista | G15: Sinis | H15: Alquilar encofrado | J15: -155.85 | K15: Costo mensual | L15: Pagado | R15: Factura por mes 28 días
B16: =+$E$3 -> Losa Mogetta | C16: 46065 | D16: S/N | E16: Sin factura | F16: Flete de SINIS a obra | G16: Flete Yonatan | H16: Fletes | I16: 200000 | K16: A bauvek | L16: Pagado | N16: Recibido en obra
B17: =+$E$3 -> Losa Mogetta | C17: 46065 | D17: S/N | E17: Sin factura | F17: Flete de SINIS a obra | G17: Flete Yonatan | H17: Fletes | I17: 200000 | K17: A bauvek | L17: Pagado | N17: Recibido en obra
B18: =+$E$3 -> Losa Mogetta | C18: 46071 | D18: S/N | E18: Sin factura | F18: Flete de SINIS a obra | G18: Flete Yonatan | H18: Fletes | I18: 200000 | K18: A bauvek | L18: Pagado | N18: Recibido en obra
B19: =+$E$3 -> Losa Mogetta | C19: 46071 | D19: S/N | E19: Sin factura | F19: Flete de SINIS a obra | G19: Flete Yonatan | H19: Fletes | I19: 200000 | K19: A bauvek | L19: Pagado | N19: Recibido en obra
A20: Pasado quincena | C20: 46065
B21: =+$E$3 -> Losa Mogetta
A22: Pasado quincena | C22: 46079
B23: =+$E$3 -> Losa Mogetta | C23: 46083 | D23: Fact-A | E23: Bauvek | F23: Molones | G23: Enpolex | I23: 1558995 | K23: A proveedor | L23: Pagado | N23: Recibido en obra
B24: =+$E$3 -> Losa Mogetta | C24: 46084 | D24: S/N | E24: Sin factura | G24: Mendio SA | I24: 125946.8 | K24: A proveedor | L24: Pagado | N24: Recibido en obra
B25: =+$E$3 -> Losa Mogetta | C25: 46084 | D25: Fact-A | E25: Bauvek | F25: Puntales y vigas - losa no vista | G25: Sinis | J25: 263.49 | K25: A proveedor | L25: Pagado | N25: Recibido en obra | R25: Factura por mes 28 días
B26: =+$E$3 -> Losa Mogetta | C26: 46084 | D26: S/N | E26: Sin factura | G26: Mendio SA | I26: 125946.8 | K26: A proveedor | L26: Pagado | N26: Recibido en obra
B27: =+$E$3 -> Losa Mogetta | C27: 46090 | D27: S/N | E27: Sin factura | F27: Flete de SINIS a obra | G27: Flete Yonatan | H27: Fletes | I27: 200000 | K27: A bauvek | L27: Pagado | N27: Recibido en obra
A28: Pasado quincena | C28: 46093
B29: =+$E$3 -> Losa Mogetta | C29: 46093 | D29: Fact-A | E29: Bauvek | F29: Puntales y vigas - losa vista | G29: Sinis | J29: 1497.06 | K29: A proveedor | L29: Pagado | N29: Recibido en obra
B30: =+$E$3 -> Losa Mogetta | C30: 46094 | D30: Fact-A | E30: Bauvek | F30: Molones | G30: Enpolex | I30: 423646.93 | K30: A proveedor | L30: Pagado | N30: Recibido en obra
B31: =+$E$3 -> Losa Mogetta | C31: 46097 | D31: S/N | E31: Sin factura | F31: Traslado de 50 unid molones de 20cm | G31: Flete Hugo Godoy | H31: Fletes | I31: 56000 | K31: A bauvek | L31: Pagado | N31: Recibido en obra
B32: =+$E$3 -> Losa Mogetta | C32: 46101 | D32: Fact-A | E32: Bauvek | F32: Puntales y vigas - losa NO vista | G32: Sinis | J32: 1541.15 | K32: A proveedor | L32: Pagado | N32: Recibido en obra
A33: Pasado quincena | C33: 46107
B34: =+$E$3 -> Losa Mogetta | C34: 46119 | D34: Fact-A | E34: Bauvek | F34: Puntales y vigas - losa NO vista | G34: Sinis | J34: 263.49 | K34: A proveedor | L34: Pagado | N34: Recibido en obra
B35: =+$E$3 -> Losa Mogetta | C35: 46122 | D35: Fact-A | E35: Bauvek | F35: Puntales y vigas - losa vista | G35: Sinis | J35: 1497.06 | K35: A proveedor | L35: Pagado | N35: Recibido en obra
B36: =+$E$3 -> Losa Mogetta | C36: 46129 | D36: Fact-A | E36: Bauvek | F36: Puntales y vigas - losa NO vista | G36: Sinis | J36: 1541.15 | K36: A proveedor | L36: Pagado | N36: Recibido en obra
A37: Pasado quincena | C37: 46141
B38: =+$E$3 -> Losa Mogetta
B39: =+$E$3 -> Losa Mogetta
A40: Pasado quincena | B40: =+$E$3 -> Losa Mogetta | C40: 46149
B41: =+$E$3 -> Losa Mogetta
B42: =+$E$3 -> Losa Mogetta
A43: Pasado quincena | B43: =+$E$3 -> Losa Mogetta | C43: 46163
B44: =+$E$3 -> Losa Mogetta | C44: 46168 | D44: Fact-A36270 | E44: bauvek | F44: Puntales y vigas - losa PA | G44: Sinis | J44: 653.64 | K44: A proveedor | L44: Pagado | N44: Recibido en obra
B45: =+$E$3 -> Losa Mogetta
A46: Pasado quincena | B46: =+$E$3 -> Losa Mogetta | C46: 46177
B47: =+$E$3 -> Losa Mogetta
B48: =+$E$3 -> Losa Mogetta
A49: Pasado quincena | B49: =+$E$3 -> Losa Mogetta | C49: 46191
B50: =+$E$3 -> Losa Mogetta | C50: 46191 | D50: S/N | E50: Sin factura | F50: Traslado vigas encofrado de villa allende a Sinis | G50: Flete Hugo Godoy | H50: Flete tiene que pagarlo SINIS, realiza nota de credito | I50: 80000 | K50: A bauvek | L50: No Pagado | N50: Recibido en obra
B51: =+$E$3 -> Losa Mogetta | C51: 46191 | D51: S/N | E51: Sin factura | F51: Traslado vigas encofrado SINIS a villa allende | G51: Flete Hugo Godoy | H51: Flete tiene que pagarlo SINIS, realiza nota de credito | I51: 80000 | K51: A bauvek | L51: No Pagado | N51: Recibido en obra
B52: =+$E$3 -> Losa Mogetta
A53: Pasado quincena | B53: =+$E$3 -> Losa Mogetta | C53: 46205
B54: =+$E$3 -> Losa Mogetta
A55: Pasado quincena | B55: =+$E$3 -> Losa Mogetta | C55: 46219
B56: =+$E$3 -> Losa Mogetta
A57: Pasado quincena | B57: =+$E$3 -> Losa Mogetta | C57: 46233
B58: =+$E$3 -> Losa Mogetta | C58: 46245 | D58: S/N | E58: Sin factura | F58: Flete de SINIS a obra | G58: Flete Yonatan | H58: Fletes | I58: 230000 | K58: A bauvek | L58: Pagado | N58: Recibido en obra
B59: =+$E$3 -> Losa Mogetta | C59: 46246 | D59: S/N | E59: Sin factura | F59: Flete de SINIS a obra | G59: Flete Yonatan | H59: Fletes | I59: 230000 | K59: A bauvek | L59: Pagado | N59: Recibido en obra
B60: =+$E$3 -> Losa Mogetta | C60: 46246 | D60: S/N | E60: Sin factura | F60: Flete de SINIS a obra | G60: Flete Yonatan | H60: Fletes | I60: 230000 | K60: A bauvek | L60: Pagado | N60: Recibido en obra
B61: =+$E$3 -> Losa Mogetta | C61: 46247 | D61: S/N | E61: Sin factura | F61: Flete de SINIS a obra | G61: Flete Yonatan | H61: Fletes | I61: 230000 | K61: A bauvek | L61: Pagado | N61: Recibido en obra
B62: =+$E$3 -> Losa Mogetta | C62: 46247 | D62: S/N | E62: Sin factura | F62: Flete de SINIS a obra | G62: Flete Yonatan | H62: Fletes | I62: 230000 | K62: A bauvek | L62: Pagado | N62: Recibido en obra
B63: =+$E$3 -> Losa Mogetta | C63: 46253 | E63: Bauvek | F63: 1 matafuego - recarga | G63: Pastorino | H63: equipo | K63: A Bauvek | L63: No Pagado | M63: No Pagado
B64: =+$E$3 -> Losa Mogetta
A65: Pasado quincena | B65: =+$E$3 -> Losa Mogetta | C65: 46247
B66: =+$E$3 -> Losa Mogetta
B67: =+$E$3 -> Losa Mogetta
B68: =+$E$3 -> Losa Mogetta
B69: =+$E$3 -> Losa Mogetta
H71: TOTAL | I71: =SUM(I10:I69) -> 4600535.5

Sheet Obra DC
D2: GASTOS MATERIAL OBRA
D3: Cliente: | E3: Diego Casalis
D4: Domicilio: | E4: Lote 494 | F4: Localidad: | H4: Mendiolaza
E5: El terron
B9: OBRA | C9: Fecha de FC | D9: Condición | E9: Razón social | F9: Descripción | G9: Proveedor | H9: Rubro | I9: Importe final Pesos (Iva incluido) | J9: Importe final USD (Iva incluido) | K9: Observaciones | L9: Estado Factura Cliente | M9: Estado Factura Bauvek | N9: Estado material | O9: Resarcimiento Bauvek | P9: Nº Remito | Q9: Encargado | R9: Columna1
B10: =+$E$3 -> Diego Casalis | C10: 46182 | D10: Fact-71396 | E10: Bauvek Sas | F10: Materiales de electricidad | G10: Feyro | H10: Pilar de luz | I10: 176650.04 | K10: A bauvek | L10: No Pagado | M10: Pagado | N10: Recibido en obra
B11: =+$E$3 -> Diego Casalis | C11: 46178 | D11: Fact | E11: Bauvek Sas | F11: Materiales de electricidad (fusuibles que faltaban) | G11: Feyro | H11: Pilar de luz | I11: 43260.86 | K11: A bauvek | L11: No Pagado | M11: Pagado | N11: Recibido en obra
B12: =+$E$3 -> Diego Casalis
A13: Pasado quincena | B13: =+$E$3 -> Diego Casalis | C13: 46191
B14: =+$E$3 -> Diego Casalis | C14: 46195 | D14: Fact A-16680 | E14: Bauvek Sas | F14: Materiales media sombra, alambre | G14: Cerroplast | H14: cerco obra | I14: 837228 | K14: A bauvek | L14: No Pagado | M14: Pagado | N14: Recibido en obra | R14: Echeq 30 dias
B15: =+$E$3 -> Diego Casalis | C15: 46195 | D15: Fact A-30214 | E15: Bauvek Sas | F15: puntales de madera + tablas de corralito | G15: Mendio SA | H15: cerco obra | I15: 1228221.1 | K15: A bauvek | L15: No Pagado | M15: Pagado | N15: Recibido en obra | R15: Echeq 30 dias
B16: =+$E$3 -> Diego Casalis | C16: 46199 | D16: Fact-A-72240 | E16: Bauvek Sas | F16: Materiales comienzo cerco | G16: Ferrocons | H16: obra gruesa | I16: 626508.57 | K16: A bauvek | L16: No Pagado | M16: Pagado | N16: Recibido en obra
A17: Pasado quincena | B17: =+$E$3 -> Diego Casalis | C17: 46205
B18: =+$E$3 -> Diego Casalis | C18: 46216 | D18: Fact-A-53258 | E18: Bauvek Sas | F18: Caños estructurales | G18: Acerco | H18: porton obra | I18: 711187.72 | K18: A bauvek | L18: No Pagado | M18: Pagado | N18: Recibido en obra
A19: Pasado quincena | B19: =+$E$3 -> Diego Casalis | C19: 46219
B20: =+$E$3 -> Diego Casalis | C20: 46220 | D20: S/N | E20: sin factura | F20: Acerco a herreria Maxi | G20: Flete Hugo Godoy | H20: porton obra | I20: 32500 | K20: A bauvek | L20: No Pagado | M20: No Pagado | N20: Recibido en obra
B21: =+$E$3 -> Diego Casalis | C21: 46230 | D21: S/N | E21: sin factura | F21: Herreria maxi a obra | G21: Flete Hugo Godoy | H21: porton obra | I21: 60000 | K21: A bauvek | L21: No Pagado | M21: No Pagado | N21: Recibido en obra
B22: =+$E$3 -> Diego Casalis
A23: Pasado quincena | B23: =+$E$3 -> Diego Casalis | C23: 46233
B24: =+$E$3 -> Diego Casalis
B25: =+$E$3 -> Diego Casalis
B26: =+$E$3 -> Diego Casalis
A27: Pasado quincena | B27: =+$E$3 -> Diego Casalis | C27: 46247
B28: =+$E$3 -> Diego Casalis | C28: 46253 | E28: Bauvek | F28: 1 canguro - dias a confirmar | G28: Alquilo Todo | H28: equipo | K28: A Bauvek | L28: No Pagado | M28: No Pagado | N28: Recibido en obra
B29: =+$E$3 -> Diego Casalis | C29: 46253 | E29: Bauvek | F29: 1 matafuego - recarga | G29: Pastorino | H29: equipo | K29: A Bauvek | L29: No Pagado | M29: No Pagado | N29: Recibido en obra
B30: =+$E$3 -> Diego Casalis | C30: 46254 | E30: Bauvek | F30: Traslado de 1 canguro de alquilo todo al terrón | G30: Flete Hugo Godoy | H30: flete | I30: 60000 | K30: A Bauvek | L30: No Pagado | M30: No Pagado | N30: Recibido en obra
B31: =+$E$3 -> Diego Casalis
B32: =+$E$3 -> Diego Casalis
B33: =+$E$3 -> Diego Casalis
A34: Pasado quincena | B34: =+$E$3 -> Diego Casalis | C34: 46261
B35: =+$E$3 -> Diego Casalis | C35: 46273 | D35: S/N | E35: sin factura | F35: Traslado de 1 martillo 30kg de alquilo todo al terrón | G35: Flete Hugo Godoy | H35: flete | I35: 65000 | K35: A Bauvek | L35: No Pagado | M35: No Pagado | N35: Recibido en obra
B36: =+$E$3 -> Diego Casalis | C36: 46273 | E36: Bauvek Sas | F36: Alquiler de martillo 30kg | G36: Alquilo Todo | H36: equipo | K36: A Bauvek | L36: No Pagado | M36: No Pagado | N36: Recibido en obra
B37: =+$E$3 -> Diego Casalis
B38: =+$E$3 -> Diego Casalis
B39: =+$E$3 -> Diego Casalis
A40: Prox cierre | B40: =+$E$3 -> Diego Casalis | C40: 46275
B41: =+$E$3 -> Diego Casalis
B42: =+$E$3 -> Diego Casalis
B43: =+$E$3 -> Diego Casalis
H45: TOTAL | I45: =SUM(I10:I43) -> 3840556.3

Sheet Obra CR
D2: GASTOS MATERIAL OBRA
D3: Cliente: | E3: Carola Ruda
D4: Domicilio: | E4: Mza 29 - lote 10 | F4: Localidad: | H4: Córdoba
E5: Las Delicias
B9: OBRA | C9: Fecha de FC | D9: Condición | E9: Razón social | F9: Descripción | G9: Proveedor | H9: Rubro | I9: Importe final Pesos (Iva incluido) | J9: Importe final USD (Iva incluido) | K9: Observaciones | L9: Estado Factura Cliente | M9: Estado Factura Bauvek | N9: Estado material | O9: Resarcimiento Bauvek | P9: Nº Remito | Q9: Encargado
B10: =+$E$3 -> Carola Ruda
B11: =+$E$3 -> Carola Ruda | C11: 46216 | D11: Fact-A-53258 | E11: Bauvek Sas | F11: Caños estructurales | G11: Acerco | H11: porton obra | I11: 711187.72 | K11: A bauvek | L11: No Pagado | M11: Pagado
B12: =+$E$3 -> Carola Ruda | C12: 46216 | D12: Fact A-16680 | E12: Bauvek Sas | F12: Materiales media sombra, alambre | G12: Cerroplast | H12: cerco obra | I12: 837228 | K12: A bauvek | L12: No Pagado | M12: Pagado | R12: Echeq 30 dias
B13: =+$E$3 -> Carola Ruda | C13: 46216 | D13: Fact A-30214 | E13: Bauvek Sas | F13: puntales de madera + tablas de corralito | G13: Mendio SA | H13: cerco obra | I13: 1228221.1 | K13: A bauvek | L13: No Pagado | M13: Pagado | R13: Echeq 30 dias
A14: Pasado quincena | B14: =+$E$3 -> Carola Ruda | C14: 46219
B15: =+$E$3 -> Carola Ruda | C15: 46220 | D15: S/N | E15: sin factura | F15: Acerco a herreria Maxi | G15: Flete Hugo Godoy | H15: porton obra | I15: 32500 | K15: A bauvek | L15: No Pagado | M15: No Pagado
B16: =+$E$3 -> Carola Ruda | C16: 46217 | D16: S/N | E16: sin factura | F16: Material, acerco - cerroplas a obra | G16: Flete Hugo Godoy | H16: porton obra | I16: 75000
B17: =+$E$3 -> Carola Ruda | C17: 46230 | D17: S/N | E17: sin factura | F17: Herreria maxi a obra | G17: Flete Hugo Godoy | H17: porton obra | I17: 60000 | K17: A bauvek | L17: No Pagado | M17: No Pagado
B18: =+$E$3 -> Carola Ruda
A19: Pasado quincena | B19: =+$E$3 -> Carola Ruda | C19: 46233
B20: =+$E$3 -> Carola Ruda
B21: =+$E$3 -> Carola Ruda
A22: Pasado quincena | B22: =+$E$3 -> Carola Ruda | C22: 46247
B23: =+$E$3 -> Carola Ruda | C23: 46253 | E23: Bauvek | F23: 1 matafuego - recarga | G23: Pastorino | H23: equipo | K23: A Bauvek | L23: No Pagado | M23: No Pagado
B24: =+$E$3 -> Carola Ruda | C24: 46255 | D24: S/N | E24: Bauvek | F24: Traslado de 10 fenolicos de Molvento a las delicias | G24: Flete Hugo Godoy | H24: flete | I24: 120000 | K24: A Bauvek | L24: No Pagado | M24: No Pagado
A25: Pasado quincena | B25: =+$E$3 -> Carola Ruda | C25: 46261
B26: =+$E$3 -> Carola Ruda | C26: 46267 | E26: Bauvek Sas | F26: Alquiler de martillo 15kg- 3dias | G26: Alquilo Todo | H26: equipo | K26: A Bauvek | L26: No Pagado | M26: No Pagado | N26: Recibido en obra
B27: =+$E$3 -> Carola Ruda | C27: 46272 | E27: Bauvek Sas | F27: Alquiler de martillo 30kg | G27: Alquilo Todo | H27: equipo | K27: A Bauvek | L27: No Pagado | M27: No Pagado | N27: Recibido en obra
B28: =+$E$3 -> Carola Ruda
A29: Prox cierre | B29: =+$E$3 -> Carola Ruda | C29: 46275
B30: =+$E$3 -> Carola Ruda | C30: 46287 | E30: Bauvek Sas | F30: Alquiler de martillo 34kg | G30: Alquilo Todo | H30: equipo | I30: 208000 | K30: A Bauvek | L30: No Pagado
B31: =+$E$3 -> Carola Ruda
B32: =+$E$3 -> Carola Ruda
B33: =+$E$3 -> Carola Ruda
H35: TOTAL | I35: =SUM(I10:I33) -> 3272136.8

Sheet Obra VB
D2: GASTOS MATERIAL OBRA
D3: Cliente: | E3: Venturelli-Bernal
D4: Domicilio: | E4: Mza 49 lote 8 | F4: Localidad: | H4: Córdoba
E5: Las Cañitas, Malagueño
B9: OBRA | C9: Fecha de FC | D9: Condición | E9: Razón social | F9: Descripción | G9: Proveedor | H9: Rubro | I9: Importe final Pesos (Iva incluido) | J9: Importe final USD (Iva incluido) | K9: Observaciones | L9: Estado Factura Cliente | M9: Estado Factura Bauvek | N9: Estado material | O9: Resarcimiento Bauvek | P9: Nº Remito | Q9: Encargado
B10: =+$E$3 -> Venturelli-Bernal
B11: =+$E$3 -> Venturelli-Bernal | R11: Echeq 30 dias
B12: =+$E$3 -> Venturelli-Bernal
B13: =+$E$3 -> Venturelli-Bernal
B14: =+$E$3 -> Venturelli-Bernal
B15: =+$E$3 -> Venturelli-Bernal
A16: Pasado quincena | B16: =+$E$3 -> Venturelli-Bernal | C16: 46219
B17: =+$E$3 -> Venturelli-Bernal | C17: 46253 | E17: Bauvek | F17: 1 matafuego - recarga | G17: Pastorino | H17: equipo | K17: A Bauvek | L17: No Pagado | M17: No Pagado
A18: Pasado quincena | B18: =+$E$3 -> Venturelli-Bernal | C18: 46261
B19: =+$E$3 -> Venturelli-Bernal | C19: 46268 | E19: Bauvek Sas | F19: Alquiler de martillo canguro - 2 dias | G19: Alquilo Todo | H19: equipo | K19: A Bauvek | L19: No Pagado | M19: No Pagado | N19: Recibido en obra
B20: =+$E$3 -> Venturelli-Bernal | C20: 46272 | E20: Bauvek Sas | F20: Alquiler de martillo canguro - controlar dias | G20: Alquilo Todo | H20: equipo | K20: A Bauvek | L20: No Pagado | M20: No Pagado | N20: Recibido en obra
B21: =+$E$3 -> Venturelli-Bernal
A22: Prox cierre | B22: =+$E$3 -> Venturelli-Bernal | C22: 46275
B23: =+$E$3 -> Venturelli-Bernal
B24: =+$E$3 -> Venturelli-Bernal
B25: =+$E$3 -> Venturelli-Bernal
B26: =+$E$3 -> Venturelli-Bernal
H28: TOTAL | I28: =SUM(I10:I26) -> 0

Sheet Resumens
A1: Obra | B1: Proveedor | C1: Importe final (Iva incluido) | D1: Estado Factura Cliente | E1: Estado Factura Bauvek | F1: Estado material
A2: =IF('Obra SG'!F10="","","Obra SG") | B2: =IF('Obra SG'!F10="","",'Obra SG'!F10) | C2: =IF('Obra SG'!F10="","",'Obra SG'!H10) | D2: =IF('Obra SG'!F10="","",'Obra SG'!K10) | E2: =IF('Obra SG'!F10="","",'Obra SG'!L10) | F2: =IF('Obra SG'!F10="","",'Obra SG'!M10)
A3: =IF('Obra SG'!F11="","","Obra SG") | B3: =IF('Obra SG'!F11="","",'Obra SG'!F11) | C3: =IF('Obra SG'!F11="","",'Obra SG'!H11) | D3: =IF('Obra SG'!F11="","",'Obra SG'!K11) | E3: =IF('Obra SG'!F11="","",'Obra SG'!L11) | F3: =IF('Obra SG'!F11="","",'Obra SG'!M11)
A4: =IF('Obra SG'!F12="","","Obra SG") | B4: =IF('Obra SG'!F12="","",'Obra SG'!F12) | C4: =IF('Obra SG'!F12="","",'Obra SG'!H12) | D4: =IF('Obra SG'!F12="","",'Obra SG'!K12) | E4: =IF('Obra SG'!F12="","",'Obra SG'!L12) | F4: =IF('Obra SG'!F12="","",'Obra SG'!M12)
A5: =IF('Obra SG'!F13="","","Obra SG") -> Obra SG | B5: =IF('Obra SG'!F13="","",'Obra SG'!F13) -> 2 placas antihumedad y perfiles z | C5: =IF('Obra SG'!I13="","",'Obra SG'!I13) -> 91470.24 | D5: =IF('Obra SG'!F13="","",'Obra SG'!K13) -> A bauvek | E5: =IF('Obra SG'!F13="","",'Obra SG'!L13) -> Cuenta Corriente | F5: =IF('Obra SG'!F13="","",'Obra SG'!M13) -> 0
A6: =IF('Obra SG'!F14="","","Obra SG") -> Obra SG | B6: =IF('Obra SG'!F14="","",'Obra SG'!F14) -> 4 placas comunes y 2 puntas atorn. | C6: =IF('Obra SG'!I14="","",'Obra SG'!I14) -> 58182.63 | D6: =IF('Obra SG'!F14="","",'Obra SG'!K14) -> A bauvek | E6: =IF('Obra SG'!F14="","",'Obra SG'!L14) -> Cuenta Corriente | F6: =IF('Obra SG'!F14="","",'Obra SG'!M14) -> 0
A7: =IF('Obra SG'!F15="","","Obra SG") -> Obra SG | B7: =IF('Obra SG'!F15="","",'Obra SG'!F15) -> Materiales de pintura, rodillos y lijas | C7: =IF('Obra SG'!I15="","",'Obra SG'!I15) | D7: =IF('Obra SG'!F15="","",'Obra SG'!K15) -> A proveedor | E7: =IF('Obra SG'!F15="","",'Obra SG'!L15) -> Pagado | F7: =IF('Obra SG'!F15="","",'Obra SG'!M15) -> 0
A8: =IF('Obra SG'!F16="","","Obra SG") -> Obra SG | B8: =IF('Obra SG'!F16="","",'Obra SG'!F16) -> 1 cinta tramada y 1 lata de masilla | C8: =IF('Obra SG'!I16="","",'Obra SG'!I16) -> 26266.89 | D8: =IF('Obra SG'!F16="","",'Obra SG'!K16) -> A bauvek | E8: =IF('Obra SG'!F16="","",'Obra SG'!L16) -> Cuenta Corriente | F8: =IF('Obra SG'!F16="","",'Obra SG'!M16) -> 0
A9: =IF('Obra SG'!F17="","","Obra SG") -> Obra SG | B9: =IF('Obra SG'!F17="","",'Obra SG'!F17) -> Flete de tejuelas de Almada a obra SG | C9: =IF('Obra SG'!I17="","",'Obra SG'!I17) -> 57000 | D9: =IF('Obra SG'!F17="","",'Obra SG'!K17) -> A bauvek | E9: =IF('Obra SG'!F17="","",'Obra SG'!L17) -> Pagado | F9: =IF('Obra SG'!F17="","",'Obra SG'!M17) -> 0
A10: =IF('Obra SG'!F18="","","Obra SG") -> Obra SG | B10: =IF('Obra SG'!F18="","",'Obra SG'!F18) -> Devolucion de andamios de obra a Guaticor | C10: =IF('Obra SG'!I18="","",'Obra SG'!I18) -> 57000 | D10: =IF('Obra SG'!F18="","",'Obra SG'!K18) -> A bauvek | E10: =IF('Obra SG'!F18="","",'Obra SG'!L18) -> Pagado | F10: =IF('Obra SG'!F18="","",'Obra SG'!M18) -> 0
A11: =IF('Obra SG'!F19="","","Obra SG") -> Obra SG | B11: =IF('Obra SG'!F19="","",'Obra SG'!F19) -> Una placa vibradora | C11: =IF('Obra SG'!I19="","",'Obra SG'!I19) -> 60000 | D11: =IF('Obra SG'!F19="","",'Obra SG'!K19) -> A bauvek | E11: =IF('Obra SG'!F19="","",'Obra SG'!L19) -> Pagado | F11: =IF('Obra SG'!F19="","",'Obra SG'!M19) -> 0
A12: =IF('Obra SG'!F20="","","Obra SG") -> Obra SG | B12: =IF('Obra SG'!F20="","",'Obra SG'!F20) -> Flete de pegamento de contigiani y pintura de garin | C12: =IF('Obra SG'!I20="","",'Obra SG'!I20) -> 72000 | D12: =IF('Obra SG'!F20="","",'Obra SG'!K20) -> A bauvek | E12: =IF('Obra SG'!F20="","",'Obra SG'!L20) -> Pagado | F12: =IF('Obra SG'!F20="","",'Obra SG'!M20) -> 0
A13: =IF('Obra SG'!F21="","","Obra SG") | B13: =IF('Obra SG'!F21="","",'Obra SG'!F21) | C13: =IF('Obra SG'!I21="","",'Obra SG'!I21) | D13: =IF('Obra SG'!F21="","",'Obra SG'!K21) | E13: =IF('Obra SG'!F21="","",'Obra SG'!L21) | F13: =IF('Obra SG'!F21="","",'Obra SG'!M21)
A14: =IF('Obra SG'!F22="","","Obra SG") -> Obra SG | B14: =IF('Obra SG'!F22="","",'Obra SG'!F22) -> Alambre tejido + ganchos + alambre 2.2, etc | C14: =IF('Obra SG'!I22="","",'Obra SG'!I22) -> 85271.19 | D14: =IF('Obra SG'!F22="","",'Obra SG'!K22) -> A proveedor | E14: =IF('Obra SG'!F22="","",'Obra SG'!L22) -> Pagado | F14: =IF('Obra SG'!F22="","",'Obra SG'!M22) -> 0
A15: =IF('Obra SG'!F23="","","Obra SG") -> Obra SG | B15: =IF('Obra SG'!F23="","",'Obra SG'!F23) -> Material de plomeria | C15: =IF('Obra SG'!I23="","",'Obra SG'!I23) -> 465269.3 | D15: =IF('Obra SG'!F23="","",'Obra SG'!K23) -> A proveedor | E15: =IF('Obra SG'!F23="","",'Obra SG'!L23) -> Pagado | F15: =IF('Obra SG'!F23="","",'Obra SG'!M23) -> 0
A16: =IF('Obra SG'!F24="","","Obra SG") -> Obra SG | B16: =IF('Obra SG'!F24="","",'Obra SG'!F24) -> Bomba presurizadora | C16: =IF('Obra SG'!I24="","",'Obra SG'!I24) -> 385891.6 | D16: =IF('Obra SG'!F24="","",'Obra SG'!K24) -> A proveedor | E16: =IF('Obra SG'!F24="","",'Obra SG'!L24) -> Pagado | F16: =IF('Obra SG'!F24="","",'Obra SG'!M24) -> 0
... A30: =IF('Obra SG'!F38="","","Obra SG") -> Obra SG | B30: =IF('Obra SG'!F38="","",'Obra SG'!F38) -> Travesaños cortos | C30: =IF('Obra SG'!I38="","",'Obra SG'!I38) -> 18237.7 | D30: =IF('Obra SG'!F38="","",'Obra SG'!K38) -> A bauvek | E30: =IF('Obra SG'!F38="","",'Obra SG'!L38) -> Pagado | F30: =IF('Obra SG'!F38="","",'Obra SG'!M38) -> 0
A31: =IF('Obra SG'!F39="","","Obra SG") | B31: =IF('Obra SG'!F39="","",'Obra SG'!F39) | C31: =IF('Obra SG'!F39="","",'Obra SG'!H39) | D31: =IF('Obra SG'!F39="","",'Obra SG'!K39) | E31: =IF('Obra SG'!F39="","",'Obra SG'!L39) | F31: =IF('Obra SG'!F39="","",'Obra SG'!M39)
A32: =IF('Obra SG'!F40="","","Obra SG") | B32: =IF('Obra SG'!F40="","",'Obra SG'!F40) | C32: =IF('Obra SG'!F40="","",'Obra SG'!H40) | D32: =IF('Obra SG'!F40="","",'Obra SG'!K40) | E32: =IF('Obra SG'!F40="","",'Obra SG'!L40) | F32: =IF('Obra SG'!F40="","",'Obra SG'!M40)
A33: =IF('Obra SG'!F41="","","Obra SG") | B33: =IF('Obra SG'!F41="","",'Obra SG'!F41) | C33: =IF('Obra SG'!F41="","",'Obra SG'!H41) | D33: =IF('Obra SG'!F41="","",'Obra SG'!K41) | E33: =IF('Obra SG'!F41="","",'Obra SG'!L41) | F33: =IF('Obra SG'!F41="","",'Obra SG'!M41)
A34: =IF('Obra SG'!F42="","","Obra SG") | B34: =IF('Obra SG'!F42="","",'Obra SG'!F42) | C34: =IF('Obra SG'!F42="","",'Obra SG'!H42) | D34: =IF('Obra SG'!F42="","",'Obra SG'!K42) | E34: =IF('Obra SG'!F42="","",'Obra SG'!L42) | F34: =IF('Obra SG'!F42="","",'Obra SG'!M42)
A35: =IF('Obra SG'!F43="","","Obra SG") | B35: =IF('Obra SG'!F43="","",'Obra SG'!F43) | C35: =IF('Obra SG'!F43="","",'Obra SG'!H43) | D35: =IF('Obra SG'!F43="","",'Obra SG'!K43) | E35: =IF('Obra SG'!F43="","",'Obra SG'!L43) | F35: =IF('Obra SG'!F43="","",'Obra SG'!M43)
A36: =IF('Obra SG'!F44="","","Obra SG") | B36: =IF('Obra SG'!F44="","",'Obra SG'!F44) | C36: =IF('Obra SG'!F44="","",'Obra SG'!H44) | D36: =IF('Obra SG'!F44="","",'Obra SG'!K44) | E36: =IF('Obra SG'!F44="","",'Obra SG'!L44) | F36: =IF('Obra SG'!F44="","",'Obra SG'!M44)
A37: =IF('Obra SG'!F45="","","Obra SG") | B37: =IF('Obra SG'!F45="","",'Obra SG'!F45) | C37: =IF('Obra SG'!F45="","",'Obra SG'!H45) | D37: =IF('Obra SG'!F45="","",'Obra SG'!K45) | E37: =IF('Obra SG'!F45="","",'Obra SG'!L45) | F37: =IF('Obra SG'!F45="","",'Obra SG'!M45)
A38: =IF('Obra SG'!F46="","","Obra SG") | B38: =IF('Obra SG'!F46="","",'Obra SG'!F46) | C38: =IF('Obra SG'!F46="","",'Obra SG'!H46) | D38: =IF('Obra SG'!F46="","",'Obra SG'!K46) | E38: =IF('Obra SG'!F46="","",'Obra SG'!L46) | F38: =IF('Obra SG'!F46="","",'Obra SG'!M46)
A39: =IF('Obra SG'!F47="","","Obra SG") | B39: =IF('Obra SG'!F47="","",'Obra SG'!F47) | C39: =IF('Obra SG'!F47="","",'Obra SG'!H47) | D39: =IF('Obra SG'!F47="","",'Obra SG'!K47) | E39: =IF('Obra SG'!F47="","",'Obra SG'!L47) | F39: =IF('Obra SG'!F47="","",'Obra SG'!M47)
A40: =IF('Obra SG'!F48="","","Obra SG") | B40: =IF('Obra SG'!F48="","",'Obra SG'!F48) | C40: =IF('Obra SG'!F48="","",'Obra SG'!H48) | D40: =IF('Obra SG'!F48="","",'Obra SG'!K48) | E40: =IF('Obra SG'!F48="","",'Obra SG'!L48) | F40: =IF('Obra SG'!F48="","",'Obra SG'!M48)
A41: =IF('Obra SG'!F49="","","Obra SG") | B41: =IF('Obra SG'!F49="","",'Obra SG'!F49) | C41: =IF('Obra SG'!F49="","",'Obra SG'!H49) | D41: =IF('Obra SG'!F49="","",'Obra SG'!K49) | E41: =IF('Obra SG'!F49="","",'Obra SG'!L49) | F41: =IF('Obra SG'!F49="","",'Obra SG'!M49)
A42: =IF('Obra SG'!F50="","","Obra SG") | B42: =IF('Obra SG'!F50="","",'Obra SG'!F50) | C42: =IF('Obra SG'!F50="","",'Obra SG'!H50) | D42: =IF('Obra SG'!F50="","",'Obra SG'!K50) | E42: =IF('Obra SG'!F50="","",'Obra SG'!L50) | F42: =IF('Obra SG'!F50="","",'Obra SG'!M50)
... A50: =IF('Obra SG'!F58="","","Obra SG") | B50: =IF('Obra SG'!F58="","",'Obra SG'!F58) | C50: =IF('Obra SG'!F58="","",'Obra SG'!H58) | D50: =IF('Obra SG'!F58="","",'Obra SG'!K58) | E50: =IF('Obra SG'!F58="","",'Obra SG'!L58) | F50: =IF('Obra SG'!F58="","",'Obra SG'!M58)
A51: =IF('Obra SG'!F59="","","Obra SG") | B51: =IF('Obra SG'!F59="","",'Obra SG'!F59) | C51: =IF('Obra SG'!F59="","",'Obra SG'!H59) | D51: =IF('Obra SG'!F59="","",'Obra SG'!J59) | E51: =IF('Obra SG'!F59="","",'Obra SG'!K59) | F51: =IF('Obra SG'!F59="","",'Obra SG'!L59)
A52: =IF('Obra SG'!F60="","","Obra SG") | B52: =IF('Obra SG'!F60="","",'Obra SG'!F60) | C52: =IF('Obra SG'!F60="","",'Obra SG'!H60) | D52: =IF('Obra SG'!F60="","",'Obra SG'!J60) | E52: =IF('Obra SG'!F60="","",'Obra SG'!K60) | F52: =IF('Obra SG'!F60="","",'Obra SG'!L60)
A53: =IF('Obra SG'!F61="","","Obra SG") | B53: =IF('Obra SG'!F61="","",'Obra SG'!F61) | C53: =IF('Obra SG'!F61="","",'Obra SG'!H61) | D53: =IF('Obra SG'!F61="","",'Obra SG'!J61) | E53: =IF('Obra SG'!F61="","",'Obra SG'!K61) | F53: =IF('Obra SG'!F61="","",'Obra SG'!L61)
A54: =IF('Obra SG'!F62="","","Obra SG") | B54: =IF('Obra SG'!F62="","",'Obra SG'!F62) | C54: =IF('Obra SG'!F62="","",'Obra SG'!H62) | D54: =IF('Obra SG'!F62="","",'Obra SG'!J62) | E54: =IF('Obra SG'!F62="","",'Obra SG'!K62) | F54: =IF('Obra SG'!F62="","",'Obra SG'!L62)
A55: =IF('Obra SG'!F63="","","Obra SG") | B55: =IF('Obra SG'!F63="","",'Obra SG'!F63) | C55: =IF('Obra SG'!F63="","",'Obra SG'!H63) | D55: =IF('Obra SG'!F63="","",'Obra SG'!J63) | E55: =IF('Obra SG'!F63="","",'Obra SG'!K63) | F55: =IF('Obra SG'!F63="","",'Obra SG'!L63)
A56: =IF('Obra SG'!F64="","","Obra SG") | B56: =IF('Obra SG'!F64="","",'Obra SG'!F64) | C56: =IF('Obra SG'!F64="","",'Obra SG'!H64) | D56: =IF('Obra SG'!F64="","",'Obra SG'!J64) | E56: =IF('Obra SG'!F64="","",'Obra SG'!K64) | F56: =IF('Obra SG'!F64="","",'Obra SG'!L64)
A57: =IF('Obra SG'!F65="","","Obra SG") | B57: =IF('Obra SG'!F65="","",'Obra SG'!F65) | C57: =IF('Obra SG'!F65="","",'Obra SG'!H65) | D57: =IF('Obra SG'!F65="","",'Obra SG'!J65) | E57: =IF('Obra SG'!F65="","",'Obra SG'!K65) | F57: =IF('Obra SG'!F65="","",'Obra SG'!L65)
A58: =IF('Obra SG'!F66="","","Obra SG") | B58: =IF('Obra SG'!F66="","",'Obra SG'!F66) | C58: =IF('Obra SG'!F66="","",'Obra SG'!H66) | D58: =IF('Obra SG'!F66="","",'Obra SG'!J66) | E58: =IF('Obra SG'!F66="","",'Obra SG'!K66) | F58: =IF('Obra SG'!F66="","",'Obra SG'!L66)
A59: =IF('Obra SG'!F67="","","Obra SG") | B59: =IF('Obra SG'!F67="","",'Obra SG'!F67) | C59: =IF('Obra SG'!F67="","",'Obra SG'!H67) | D59: =IF('Obra SG'!F67="","",'Obra SG'!J67) | E59: =IF('Obra SG'!F67="","",'Obra SG'!K67) | F59: =IF('Obra SG'!F67="","",'Obra SG'!L67)
A60: =IF('Obra SG'!F68="","","Obra SG") | B60: =IF('Obra SG'!F68="","",'Obra SG'!F68) | C60: =IF('Obra SG'!F68="","",'Obra SG'!H68) | D60: =IF('Obra SG'!F68="","",'Obra SG'!J68) | E60: =IF('Obra SG'!F68="","",'Obra SG'!K68) | F60: =IF('Obra SG'!F68="","",'Obra SG'!L68)
A61: =IF('Obra SG'!F69="","","Obra SG") | B61: =IF('Obra SG'!F69="","",'Obra SG'!F69) | C61: =IF('Obra SG'!F69="","",'Obra SG'!H69) | D61: =IF('Obra SG'!F69="","",'Obra SG'!J69) | E61: =IF('Obra SG'!F69="","",'Obra SG'!K69) | F61: =IF('Obra SG'!F69="","",'Obra SG'!L69)
A62: =IF('Obra SG'!F70="","","Obra SG") | B62: =IF('Obra SG'!F70="","",'Obra SG'!F70) | C62: =IF('Obra SG'!F70="","",'Obra SG'!H70) | D62: =IF('Obra SG'!F70="","",'Obra SG'!J70) | E62: =IF('Obra SG'!F70="","",'Obra SG'!K70) | F62: =IF('Obra SG'!F70="","",'Obra SG'!L70)
A63: =IF('Obra HR'!G10="","","Obra HR") | B63: =IF('Obra HR'!G10="","",'Obra HR'!G10) | C63: =IF('Obra HR'!G10="","",'Obra HR'!I10) | D63: =IF('Obra HR'!G10="","",'Obra HR'!L10) | E63: =IF('Obra HR'!G10="","",'Obra HR'!M10) | F63: =IF('Obra HR'!G10="","",'Obra HR'!N10)
A64: =IF('Obra HR'!G11="","","Obra HR") | B64: =IF('Obra HR'!G11="","",'Obra HR'!G11) | C64: =IF('Obra HR'!G11="","",'Obra HR'!I11) | D64: =IF('Obra HR'!G11="","",'Obra HR'!L11) | E64: =IF('Obra HR'!G11="","",'Obra HR'!M11) | F64: =IF('Obra HR'!G11="","",'Obra HR'!N11)
A65: =IF('Obra HR'!G12="","","Obra HR") | B65: =IF('Obra HR'!G12="","",'Obra HR'!G12) | C65: =IF('Obra HR'!G12="","",'Obra HR'!I12) | D65: =IF('Obra HR'!G12="","",'Obra HR'!L12) | E65: =IF('Obra HR'!G12="","",'Obra HR'!M12) | F65: =IF('Obra HR'!G12="","",'Obra HR'!N12)
A66: =IF('Obra HR'!G13="","","Obra HR") | B66: =IF('Obra HR'!G13="","",'Obra HR'!G13) | C66: =IF('Obra HR'!G13="","",'Obra HR'!I13) | D66: =IF('Obra HR'!G13="","",'Obra HR'!L13) | E66: =IF('Obra HR'!G13="","",'Obra HR'!M13) | F66: =IF('Obra HR'!G13="","",'Obra HR'!N13)
A67: =IF('Obra HR'!G14="","","Obra HR") | B67: =IF('Obra HR'!G14="","",'Obra HR'!G14) | C67: =IF('Obra HR'!G14="","",'Obra HR'!I14) | D67: =IF('Obra HR'!G14="","",'Obra HR'!L14) | E67: =IF('Obra HR'!G14="","",'Obra HR'!M14) | F67: =IF('Obra HR'!G14="","",'Obra HR'!N14)
A68: =IF('Obra HR'!G15="","","Obra HR") | B68: =IF('Obra HR'!G15="","",'Obra HR'!G15) | C68: =IF('Obra HR'!G15="","",'Obra HR'!I15) | D68: =IF('Obra HR'!G15="","",'Obra HR'!L15) | E68: =IF('Obra HR'!G15="","",'Obra HR'!M15) | F68: =IF('Obra HR'!G15="","",'Obra HR'!N15)
A69: =IF('Obra HR'!G16="","","Obra HR") | B69: =IF('Obra HR'!G16="","",'Obra HR'!G16) | C69: =IF('Obra HR'!G16="","",'Obra HR'!I16) | D69: =IF('Obra HR'!G16="","",'Obra HR'!L16) | E69: =IF('Obra HR'!G16="","",'Obra HR'!M16) | F69: =IF('Obra HR'!G16="","",'Obra HR'!N16)
A70: =IF('Obra HR'!G17="","","Obra HR") | B70: =IF('Obra HR'!G17="","",'Obra HR'!G17) | C70: =IF('Obra HR'!G17="","",'Obra HR'!I17) | D70: =IF('Obra HR'!G17="","",'Obra HR'!L17) | E70: =IF('Obra HR'!G17="","",'Obra HR'!M17) | F70: =IF('Obra HR'!G17="","",'Obra HR'!N17)
A71: =IF('Obra HR'!G18="","","Obra HR") | B71: =IF('Obra HR'!G18="","",'Obra HR'!G18) | C71: =IF('Obra HR'!G18="","",'Obra HR'!I18) | D71: =IF('Obra HR'!G18="","",'Obra HR'!L18) | E71: =IF('Obra HR'!G18="","",'Obra HR'!M18) | F71: =IF('Obra HR'!G18="","",'Obra HR'!N18)
A72: =IF('Obra HR'!G19="","","Obra HR") | B72: =IF('Obra HR'!G19="","",'Obra HR'!G19) | C72: =IF('Obra HR'!G19="","",'Obra HR'!I19) | D72: =IF('Obra HR'!G19="","",'Obra HR'!L19) | E72: =IF('Obra HR'!G19="","",'Obra HR'!M19) | F72: =IF('Obra HR'!G19="","",'Obra HR'!N19)
A73: =IF('Obra HR'!G20="","","Obra HR") | B73: =IF('Obra HR'!G20="","",'Obra HR'!G20) | C73: =IF('Obra HR'!G20="","",'Obra HR'!I20) | D73: =IF('Obra HR'!G20="","",'Obra HR'!L20) | E73: =IF('Obra HR'!G20="","",'Obra HR'!M20) | F73: =IF('Obra HR'!G20="","",'Obra HR'!N20)
A74: =IF('Obra HR'!G21="","","Obra HR") | B74: =IF('Obra HR'!G21="","",'Obra HR'!G21) | C74: =IF('Obra HR'!G21="","",'Obra HR'!I21) | D74: =IF('Obra HR'!G21="","",'Obra HR'!L21) | E74: =IF('Obra HR'!G21="","",'Obra HR'!M21) | F74: =IF('Obra HR'!G21="","",'Obra HR'!N21)
... A102: =IF('Obra HR'!G49="","","Obra HR") | B102: =IF('Obra HR'!G49="","",'Obra HR'!G49) | C102: =IF('Obra HR'!G49="","",'Obra HR'!I49) | D102: =IF('Obra HR'!G49="","",'Obra HR'!L49) | E102: =IF('Obra HR'!G49="","",'Obra HR'!M49) | F102: =IF('Obra HR'!G49="","",'Obra HR'!N49)
A103: =IF('Obra HR'!G50="","","Obra HR") | B103: =IF('Obra HR'!G50="","",'Obra HR'!G50) | C103: =IF('Obra HR'!G50="","",'Obra HR'!I50) | D103: =IF('Obra HR'!G50="","",'Obra HR'!K50) | E103: =IF('Obra HR'!G50="","",'Obra HR'!L50) | F103: =IF('Obra HR'!G50="","",'Obra HR'!M50)
A104: =IF('Obra HR'!G51="","","Obra HR") -> Obra HR | B104: =IF('Obra HR'!G51="","",'Obra HR'!G51) -> TOTAL | C104: =IF('Obra HR'!G51="","",'Obra HR'!I51) -> 0 | D104: =IF('Obra HR'!G51="","",'Obra HR'!K51) -> 0 | E104: =IF('Obra HR'!G51="","",'Obra HR'!L51) -> 0 | F104: =IF('Obra HR'!G51="","",'Obra HR'!M51) -> 0
A105: =IF('Obra HR'!G52="","","Obra HR") | B105: =IF('Obra HR'!G52="","",'Obra HR'!G52) | C105: =IF('Obra HR'!G52="","",'Obra HR'!I52) | D105: =IF('Obra HR'!G52="","",'Obra HR'!K52) | E105: =IF('Obra HR'!G52="","",'Obra HR'!L52) | F105: =IF('Obra HR'!G52="","",'Obra HR'!M52)
A106: =IF('Obra HR'!G53="","","Obra HR") | B106: =IF('Obra HR'!G53="","",'Obra HR'!G53) | C106: =IF('Obra HR'!G53="","",'Obra HR'!I53) | D106: =IF('Obra HR'!G53="","",'Obra HR'!K53) | E106: =IF('Obra HR'!G53="","",'Obra HR'!L53) | F106: =IF('Obra HR'!G53="","",'Obra HR'!M53)
A107: =IF('Obra HR'!G54="","","Obra HR") | B107: =IF('Obra HR'!G54="","",'Obra HR'!G54) | C107: =IF('Obra HR'!G54="","",'Obra HR'!I54) | D107: =IF('Obra HR'!G54="","",'Obra HR'!K54) | E107: =IF('Obra HR'!G54="","",'Obra HR'!L54) | F107: =IF('Obra HR'!G54="","",'Obra HR'!M54)
A108: =IF('Obra HR'!G55="","","Obra HR") | B108: =IF('Obra HR'!G55="","",'Obra HR'!G55) | C108: =IF('Obra HR'!G55="","",'Obra HR'!I55) | D108: =IF('Obra HR'!G55="","",'Obra HR'!K55) | E108: =IF('Obra HR'!G55="","",'Obra HR'!L55) | F108: =IF('Obra HR'!G55="","",'Obra HR'!M55)
A109: =IF('Obra HR'!G56="","","Obra HR") | B109: =IF('Obra HR'!G56="","",'Obra HR'!G56) | C109: =IF('Obra HR'!G56="","",'Obra HR'!I56) | D109: =IF('Obra HR'!G56="","",'Obra HR'!K56) | E109: =IF('Obra HR'!G56="","",'Obra HR'!L56) | F109: =IF('Obra HR'!G56="","",'Obra HR'!M56)
A110: =IF('Obra HR'!G57="","","Obra HR") | B110: =IF('Obra HR'!G57="","",'Obra HR'!G57) | C110: =IF('Obra HR'!G57="","",'Obra HR'!I57) | D110: =IF('Obra HR'!G57="","",'Obra HR'!K57) | E110: =IF('Obra HR'!G57="","",'Obra HR'!L57) | F110: =IF('Obra HR'!G57="","",'Obra HR'!M57)
A111: =IF('Obra HR'!G58="","","Obra HR") | B111: =IF('Obra HR'!G58="","",'Obra HR'!G58) | C111: =IF('Obra HR'!G58="","",'Obra HR'!I58) | D111: =IF('Obra HR'!G58="","",'Obra HR'!K58) | E111: =IF('Obra HR'!G58="","",'Obra HR'!L58) | F111: =IF('Obra HR'!G58="","",'Obra HR'!M58)
A112: =IF('Obra HR'!G59="","","Obra HR") | B112: =IF('Obra HR'!G59="","",'Obra HR'!G59) | C112: =IF('Obra HR'!G59="","",'Obra HR'!I59) | D112: =IF('Obra HR'!G59="","",'Obra HR'!K59) | E112: =IF('Obra HR'!G59="","",'Obra HR'!L59) | F112: =IF('Obra HR'!G59="","",'Obra HR'!M59)
A113: =IF('Obra HR'!G60="","","Obra HR") | B113: =IF('Obra HR'!G60="","",'Obra HR'!G60) | C113: =IF('Obra HR'!G60="","",'Obra HR'!I60) | D113: =IF('Obra HR'!G60="","",'Obra HR'!K60) | E113: =IF('Obra HR'!G60="","",'Obra HR'!L60) | F113: =IF('Obra HR'!G60="","",'Obra HR'!M60)
A114: =IF('Obra HR'!G61="","","Obra HR") | B114: =IF('Obra HR'!G61="","",'Obra HR'!G61) | C114: =IF('Obra HR'!G61="","",'Obra HR'!I61) | D114: =IF('Obra HR'!G61="","",'Obra HR'!K61) | E114: =IF('Obra HR'!G61="","",'Obra HR'!L61) | F114: =IF('Obra HR'!G61="","",'Obra HR'!M61)
... A123: =IF('Obra HR'!G70="","","Obra HR") | B123: =IF('Obra HR'!G70="","",'Obra HR'!G70) | C123: =IF('Obra HR'!G70="","",'Obra HR'!I70) | D123: =IF('Obra HR'!G70="","",'Obra HR'!K70) | E123: =IF('Obra HR'!G70="","",'Obra HR'!L70) | F123: =IF('Obra HR'!G70="","",'Obra HR'!M70)
A124: =IF('Obra FAR'!#REF!="","","Obra FAR") -> #REF! | B124: =IF('Obra FAR'!#REF!="","",'Obra FAR'!#REF!) -> #REF! | C124: =IF('Obra FAR'!#REF!="","",'Obra FAR'!#REF!) -> #REF! | D124: =IF('Obra FAR'!#REF!="","",'Obra FAR'!#REF!) -> #REF! | E124: =IF('Obra FAR'!#REF!="","",'Obra FAR'!#REF!) -> #REF! | F124: =IF('Obra FAR'!#REF!="","",'Obra FAR'!#REF!) -> #REF!
A125: =IF('Obra FAR'!G10="","","Obra FAR") -> Obra FAR | B125: =IF('Obra FAR'!G10="","",'Obra FAR'!G10) -> Jack | C125: =IF('Obra FAR'!G10="","",'Obra FAR'!I10) -> 1228234.4 | D125: =IF('Obra FAR'!G10="","",'Obra FAR'!L10) -> Pagado | E125: =IF('Obra FAR'!G10="","",'Obra FAR'!M10) -> Pagado | F125: =IF('Obra FAR'!G10="","",'Obra FAR'!N10) -> 0
A126: =IF('Obra FAR'!G11="","","Obra FAR") -> Obra FAR | B126: =IF('Obra FAR'!G11="","",'Obra FAR'!G11) -> Almada | C126: =IF('Obra FAR'!G11="","",'Obra FAR'!I11) -> 1086246.8 | D126: =IF('Obra FAR'!G11="","",'Obra FAR'!L11) -> Pagado | E126: =IF('Obra FAR'!G11="","",'Obra FAR'!M11) -> Pagado | F126: =IF('Obra FAR'!G11="","",'Obra FAR'!N11) -> 0
A127: =IF('Obra FAR'!G12="","","Obra FAR") -> Obra FAR | B127: =IF('Obra FAR'!G12="","",'Obra FAR'!G12) -> Nico Carusso | C127: =IF('Obra FAR'!G12="","",'Obra FAR'!I12) -> 280000 | D127: =IF('Obra FAR'!G12="","",'Obra FAR'!L12) -> Pagado | E127: =IF('Obra FAR'!G12="","",'Obra FAR'!M12) -> Pagado | F127: =IF('Obra FAR'!G12="","",'Obra FAR'!N12) -> 0
A128: =IF('Obra FAR'!G13="","","Obra FAR") -> Obra FAR | B128: =IF('Obra FAR'!G13="","",'Obra FAR'!G13) -> Almada | C128: =IF('Obra FAR'!G13="","",'Obra FAR'!I13) -> 184187.15 | D128: =IF('Obra FAR'!G13="","",'Obra FAR'!L13) -> Pagado | E128: =IF('Obra FAR'!G13="","",'Obra FAR'!M13) -> Pagado | F128: =IF('Obra FAR'!G13="","",'Obra FAR'!N13) -> 0
A129: =IF('Obra FAR'!G14="","","Obra FAR") -> Obra FAR | B129: =IF('Obra FAR'!G14="","",'Obra FAR'!G14) -> Jack | C129: =IF('Obra FAR'!G14="","",'Obra FAR'!I14) -> 30223.92 | D129: =IF('Obra FAR'!G14="","",'Obra FAR'!L14) -> Pagado | E129: =IF('Obra FAR'!G14="","",'Obra FAR'!M14) -> Pagado | F129: =IF('Obra FAR'!G14="","",'Obra FAR'!N14) -> 0
A130: =IF('Obra FAR'!G15="","","Obra FAR") -> Obra FAR | B130: =IF('Obra FAR'!G15="","",'Obra FAR'!G15) -> Goldman | C130: =IF('Obra FAR'!G15="","",'Obra FAR'!I15) -> 6694875.3 | D130: =IF('Obra FAR'!G15="","",'Obra FAR'!L15) -> Pagado | E130: =IF('Obra FAR'!G15="","",'Obra FAR'!M15) -> Pagado | F130: =IF('Obra FAR'!G15="","",'Obra FAR'!N15) -> 0
A131: =IF('Obra FAR'!G16="","","Obra FAR") -> Obra FAR | B131: =IF('Obra FAR'!G16="","",'Obra FAR'!G16) -> Gabriel Bobcat | C131: =IF('Obra FAR'!G16="","",'Obra FAR'!I16) -> 600000 | D131: =IF('Obra FAR'!G16="","",'Obra FAR'!L16) -> Pagado | E131: =IF('Obra FAR'!G16="","",'Obra FAR'!M16) -> Pagado | F131: =IF('Obra FAR'!G16="","",'Obra FAR'!N16) -> 0
A132: =IF('Obra FAR'!G17="","","Obra FAR") -> Obra FAR | B132: =IF('Obra FAR'!G17="","",'Obra FAR'!G17) -> Jack | C132: =IF('Obra FAR'!G17="","",'Obra FAR'!I17) -> 685091.44 | D132: =IF('Obra FAR'!G17="","",'Obra FAR'!L17) -> Pagado | E132: =IF('Obra FAR'!G17="","",'Obra FAR'!M17) -> Pagado | F132: =IF('Obra FAR'!G17="","",'Obra FAR'!N17) -> 0
A133: =IF('Obra FAR'!G18="","","Obra FAR") -> Obra FAR | B133: =IF('Obra FAR'!G18="","",'Obra FAR'!G18) -> Almada | C133: =IF('Obra FAR'!G18="","",'Obra FAR'!I18) -> 3700000 | D133: =IF('Obra FAR'!G18="","",'Obra FAR'!L18) -> Pagado | E133: =IF('Obra FAR'!G18="","",'Obra FAR'!M18) -> Pagado | F133: =IF('Obra FAR'!G18="","",'Obra FAR'!N18) -> 0
A134: =IF('Obra FAR'!G19="","","Obra FAR") -> Obra FAR | B134: =IF('Obra FAR'!G19="","",'Obra FAR'!G19) -> Almada | C134: =IF('Obra FAR'!G19="","",'Obra FAR'!I19) -> 1200000 | D134: =IF('Obra FAR'!G19="","",'Obra FAR'!L19) -> Pagado | E134: =IF('Obra FAR'!G19="","",'Obra FAR'!M19) -> Pagado | F134: =IF('Obra FAR'!G19="","",'Obra FAR'!N19) -> 0
A135: =IF('Obra FAR'!G20="","","Obra FAR") -> Obra FAR | B135: =IF('Obra FAR'!G20="","",'Obra FAR'!G20) -> Almada | C135: =IF('Obra FAR'!G20="","",'Obra FAR'!I20) -> 49966.44 | D135: =IF('Obra FAR'!G20="","",'Obra FAR'!L20) -> Pagado | E135: =IF('Obra FAR'!G20="","",'Obra FAR'!M20) -> Pagado | F135: =IF('Obra FAR'!G20="","",'Obra FAR'!N20) -> 0
A136: =IF('Obra FAR'!G21="","","Obra FAR") -> Obra FAR | B136: =IF('Obra FAR'!G21="","",'Obra FAR'!G21) -> Adrian Giordano | C136: =IF('Obra FAR'!G21="","",'Obra FAR'!I21) -> 3773588 | D136: =IF('Obra FAR'!G21="","",'Obra FAR'!L21) -> Pagado | E136: =IF('Obra FAR'!G21="","",'Obra FAR'!M21) -> Pagado | F136: =IF('Obra FAR'!G21="","",'Obra FAR'!N21) -> 0
... A184: =IF('Obra FAR'!G69="","","Obra FAR") | B184: =IF('Obra FAR'!G69="","",'Obra FAR'!G69) | C184: =IF('Obra FAR'!G69="","",'Obra FAR'!I69) | D184: =IF('Obra FAR'!G69="","",'Obra FAR'!L69) | E184: =IF('Obra FAR'!G69="","",'Obra FAR'!M69) | F184: =IF('Obra FAR'!G69="","",'Obra FAR'!N69)
A185: =IF('Obra JS'!G10="","","Obra JS") -> Obra JS | B185: =IF('Obra JS'!G10="","",'Obra JS'!G10) -> Mendio | C185: =IF('Obra JS'!G10="","",'Obra JS'!I10) -> 295210.23 | D185: =IF('Obra JS'!G10="","",'Obra JS'!L10) -> Pagado | E185: =IF('Obra JS'!G10="","",'Obra JS'!M10) -> Pagado | F185: =IF('Obra JS'!G10="","",'Obra JS'!N10) -> Recibido en obra
A186: =IF('Obra JS'!G11="","","Obra JS") -> Obra JS | B186: =IF('Obra JS'!G11="","",'Obra JS'!G11) -> Cerroplast | C186: =IF('Obra JS'!G11="","",'Obra JS'!I11) -> 247755.37 | D186: =IF('Obra JS'!G11="","",'Obra JS'!L11) -> Pagado | E186: =IF('Obra JS'!G11="","",'Obra JS'!M11) -> Pagado | F186: =IF('Obra JS'!G11="","",'Obra JS'!N11) -> Recibido en obra
A187: =IF('Obra JS'!G12="","","Obra JS") -> Obra JS | B187: =IF('Obra JS'!G12="","",'Obra JS'!G12) -> Serin | C187: =IF('Obra JS'!G12="","",'Obra JS'!I12) -> 18176362 | D187: =IF('Obra JS'!G12="","",'Obra JS'!L12) -> Pagado | E187: =IF('Obra JS'!G12="","",'Obra JS'!M12) -> Pagado | F187: =IF('Obra JS'!G12="","",'Obra JS'!N12) -> Recibido en obra
A188: =IF('Obra JS'!G13="","","Obra JS") -> Obra JS | B188: =IF('Obra JS'!G13="","",'Obra JS'!G13) -> Serin | C188: =IF('Obra JS'!G13="","",'Obra JS'!I13) -> 895017.35 | D188: =IF('Obra JS'!G13="","",'Obra JS'!L13) -> Pagado | E188: =IF('Obra JS'!G13="","",'Obra JS'!M13) -> Pagado | F188: =IF('Obra JS'!G13="","",'Obra JS'!N13) -> Recibido en obra
A189: =IF('Obra JS'!G14="","","Obra JS") -> Obra JS | B189: =IF('Obra JS'!G14="","",'Obra JS'!G14) -> Serin | C189: =IF('Obra JS'!G14="","",'Obra JS'!I14) -> 222592.8 | D189: =IF('Obra JS'!G14="","",'Obra JS'!L14) -> Pagado | E189: =IF('Obra JS'!G14="","",'Obra JS'!M14) -> Pagado | F189: =IF('Obra JS'!G14="","",'Obra JS'!N14) -> Recibido en obra
A190: =IF('Obra JS'!G15="","","Obra JS") -> Obra JS | B190: =IF('Obra JS'!G15="","",'Obra JS'!G15) -> Natalia Obrador | C190: =IF('Obra JS'!G15="","",'Obra JS'!I15) -> 1100000 | D190: =IF('Obra JS'!G15="","",'Obra JS'!L15) -> Pagado | E190: =IF('Obra JS'!G15="","",'Obra JS'!M15) -> Pagado | F190: =IF('Obra JS'!G15="","",'Obra JS'!N15) -> Recibido en obra
A191: =IF('Obra JS'!G16="","","Obra JS") -> Obra JS | B191: =IF('Obra JS'!G16="","",'Obra JS'!G16) -> Mendio | C191: =IF('Obra JS'!G16="","",'Obra JS'!I16) -> 622770 | D191: =IF('Obra JS'!G16="","",'Obra JS'!L16) -> Pagado | E191: =IF('Obra JS'!G16="","",'Obra JS'!M16) -> Pagado | F191: =IF('Obra JS'!G16="","",'Obra JS'!N16) -> Recibido en obra
A192: =IF('Obra JS'!G17="","","Obra JS") -> Obra JS | B192: =IF('Obra JS'!G17="","",'Obra JS'!G17) -> Hormiblock | C192: =IF('Obra JS'!G17="","",'Obra JS'!I17) -> 8960000 | D192: =IF('Obra JS'!G17="","",'Obra JS'!L17) -> Pagado | E192: =IF('Obra JS'!G17="","",'Obra JS'!M17) -> Pagado | F192: =IF('Obra JS'!G17="","",'Obra JS'!N17) -> Recibido en obra
A193: =IF('Obra JS'!G18="","","Obra JS") | B193: =IF('Obra JS'!G18="","",'Obra JS'!G18) | C193: =IF('Obra JS'!G18="","",'Obra JS'!I18) | D193: =IF('Obra JS'!G18="","",'Obra JS'!L18) | E193: =IF('Obra JS'!G18="","",'Obra JS'!M18) | F193: =IF('Obra JS'!G18="","",'Obra JS'!N18)
A194: =IF('Obra JS'!G19="","","Obra JS") -> Obra JS | B194: =IF('Obra JS'!G19="","",'Obra JS'!G19) -> Hormiblock | C194: =IF('Obra JS'!G19="","",'Obra JS'!I19) -> 6305000 | D194: =IF('Obra JS'!G19="","",'Obra JS'!L19) -> Pagado | E194: =IF('Obra JS'!G19="","",'Obra JS'!M19) -> Pagado | F194: =IF('Obra JS'!G19="","",'Obra JS'!N19) -> Recibido en obra
A195: =IF('Obra JS'!G20="","","Obra JS") -> Obra JS | B195: =IF('Obra JS'!G20="","",'Obra JS'!G20) -> Mendio | C195: =IF('Obra JS'!G20="","",'Obra JS'!I20) -> 5900970 | D195: =IF('Obra JS'!G20="","",'Obra JS'!L20) -> Pagado | E195: =IF('Obra JS'!G20="","",'Obra JS'!M20) -> Pagado | F195: =IF('Obra JS'!G20="","",'Obra JS'!N20) -> Recibido en obra
A196: =IF('Obra JS'!G21="","","Obra JS") -> Obra JS | B196: =IF('Obra JS'!G21="","",'Obra JS'!G21) -> Roncaglia | C196: =IF('Obra JS'!G21="","",'Obra JS'!I21) -> 73000 | D196: =IF('Obra JS'!G21="","",'Obra JS'!L21) -> Pagado | E196: =IF('Obra JS'!G21="","",'Obra JS'!M21) -> Pagado | F196: =IF('Obra JS'!G21="","",'Obra JS'!N21) -> Recibido en obra
... A245: =IF('Obra JS'!G70="","","Obra JS") -> Obra JS | B245: =IF('Obra JS'!G70="","",'Obra JS'!G70) -> Alquilo Todo VGB | C245: =IF('Obra JS'!G70="","",'Obra JS'!I70) -> 160000 | D245: =IF('Obra JS'!G70="","",'Obra JS'!L70) -> Pagado | E245: =IF('Obra JS'!G70="","",'Obra JS'!M70) -> Pagado | F245: =IF('Obra JS'!G70="","",'Obra JS'!N70) -> Recibido en obra
A246: =IF('Obra Cañuelas'!G10="","","Obra Cañuelas") -> Obra Cañuelas | B246: =IF('Obra Cañuelas'!G10="","",'Obra Cañuelas'!G10) -> Feyro | C246: =IF('Obra Cañuelas'!G10="","",'Obra Cañuelas'!I10) -> 5295.3 | D246: =IF('Obra Cañuelas'!G10="","",'Obra Cañuelas'!L10) -> Pagado | E246: =IF('Obra Cañuelas'!G10="","",'Obra Cañuelas'!N10) -> Recibido en obra | F246: =IF('Obra Cañuelas'!G10="","",'Obra Cañuelas'!O10) -> No Pagado
A247: =IF('Obra Cañuelas'!G11="","","Obra Cañuelas") -> Obra Cañuelas | B247: =IF('Obra Cañuelas'!G11="","",'Obra Cañuelas'!G11) -> Feyro | C247: =IF('Obra Cañuelas'!G11="","",'Obra Cañuelas'!I11) -> 67820.75 | D247: =IF('Obra Cañuelas'!G11="","",'Obra Cañuelas'!L11) -> Pagado | E247: =IF('Obra Cañuelas'!G11="","",'Obra Cañuelas'!N11) -> Recibido en obra | F247: =IF('Obra Cañuelas'!G11="","",'Obra Cañuelas'!O11) -> No Pagado
A248: =IF('Obra Cañuelas'!G12="","","Obra Cañuelas") -> Obra Cañuelas | B248: =IF('Obra Cañuelas'!G12="","",'Obra Cañuelas'!G12) -> Feyro | C248: =IF('Obra Cañuelas'!G12="","",'Obra Cañuelas'!I12) -> 15476.44 | D248: =IF('Obra Cañuelas'!G12="","",'Obra Cañuelas'!L12) -> Pagado | E248: =IF('Obra Cañuelas'!G12="","",'Obra Cañuelas'!N12) -> Recibido en obra | F248: =IF('Obra Cañuelas'!G12="","",'Obra Cañuelas'!O12) -> No Pagado
A249: =IF('Obra Cañuelas'!G13="","","Obra Cañuelas") -> Obra Cañuelas | B249: =IF('Obra Cañuelas'!G13="","",'Obra Cañuelas'!G13) -> Feyro | C249: =IF('Obra Cañuelas'!G13="","",'Obra Cañuelas'!I13) -> 9900 | D249: =IF('Obra Cañuelas'!G13="","",'Obra Cañuelas'!L13) -> Pagado | E249: =IF('Obra Cañuelas'!G13="","",'Obra Cañuelas'!N13) -> Recibido en obra | F249: =IF('Obra Cañuelas'!G13="","",'Obra Cañuelas'!O13) -> No Pagado
A250: =IF('Obra Cañuelas'!G14="","","Obra Cañuelas") | B250: =IF('Obra Cañuelas'!G14="","",'Obra Cañuelas'!G14) | C250: =IF('Obra Cañuelas'!G14="","",'Obra Cañuelas'!I14) | D250: =IF('Obra Cañuelas'!G14="","",'Obra Cañuelas'!L14) | E250: =IF('Obra Cañuelas'!G14="","",'Obra Cañuelas'!N14) | F250: =IF('Obra Cañuelas'!G14="","",'Obra Cañuelas'!O14)
...

Sheet Consultas
B8: Estado factura
B9: Pagado
B10: No Pagado
B11: Cuenta Corriente
B12: Estado Material
B13: Pendiente
B14: Acopio
B15: Recibido en obra
B16: Programado
B17: Devolución
